Workbook
Name ListaCuentas: Cuentas!$B$9:$B$128
Name Finanzas_HistoricoProductos: 'Cálculos'!$B$278:$K$334
Name ListaFiltroCuentas: 'Cálculos'!$T$9:$T$1331
Name Finanzas_GraficoProductos: 'Cálculos'!$E$340:$F$459
Name ListaFiltroProductos: 'Cálculos'!$U$9:$U$1331
Name ListaSubcategorias: 'Configuración'!$E$15:$E$134
Name Finanzas_MesesInversiones: Inversiones!$B$928:$E$946
Name Finanzas_GraficoCiudades: 'Cálculos'!$P$17:$Q$21
Name Finanzas_CalculoMovimientos: 'Cálculos'!$B$9:$N$128
Name Finanzas_CalculoCategorias: 'Cálculos'!$B$151:$F$270
Name ListaProductos: Inversiones!$B$30:$B$149

Sheet Resumen financiero
B2: Resumen financiero
B4: Año | E4: 2026 | G4: Periodo | I4: Todo el año | N4: Cuenta | Q4: Todas
B7: Patrimonio neto | H7: Efectivo | M7: Inversiones | S7: Deuda
B8: =IF(COUNT('Cálculos'!D5)=0,"",SUM(tCuentas[Saldo calculado])+'Cálculos'!D5+'Cálculos'!C5-SUM(tDeudas[Saldo pendiente])) -> 0 | H8: =SUM(tCuentas[Saldo calculado]) -> 0 | M8: ='Cálculos'!D5 -> 0 | S8: =SUM(tDeudas[Saldo pendiente]) -> 0
B12: Ingresos | H12: Gastos propios | N12: Ahorro | T12: Tasa de ahorro
B13: ='Cálculos'!E4 -> 0 | H13: ='Cálculos'!F4 -> 0 | N13: ='Cálculos'!G4 -> 0 | T13: =IF('Cálculos'!H4="",0,'Cálculos'!H4) -> 0
B53: Resumen mensual
B55: Mes | D55: Ingresos | F55: Gastos | H55: Ahorro | J55: Efectivo
B56: =CHOOSE(MONTH('Cálculos'!B135),"ene","feb","mar","abr","may","jun","jul","ago","sep","oct","nov","dic")&" "&YEAR('Cálculos'!B135) -> ene 2026 | D56: =IF(COUNT('Cálculos'!C135)=0,"",'Cálculos'!C135) -> 0 | F56: =IF(COUNT('Cálculos'!D135)=0,"",'Cálculos'!D135) -> 0 | H56: =IF(COUNT('Cálculos'!E135)=0,"",'Cálculos'!E135) -> 0 | J56: =IF(COUNT('Cálculos'!F135)=0,"",'Cálculos'!F135) -> 0
B57: =CHOOSE(MONTH('Cálculos'!B136),"ene","feb","mar","abr","may","jun","jul","ago","sep","oct","nov","dic")&" "&YEAR('Cálculos'!B136) -> feb 2026 | D57: =IF(COUNT('Cálculos'!C136)=0,"",'Cálculos'!C136) | F57: =IF(COUNT('Cálculos'!D136)=0,"",'Cálculos'!D136) | H57: =IF(COUNT('Cálculos'!E136)=0,"",'Cálculos'!E136) | J57: =IF(COUNT('Cálculos'!F136)=0,"",'Cálculos'!F136)
B58: =CHOOSE(MONTH('Cálculos'!B137),"ene","feb","mar","abr","may","jun","jul","ago","sep","oct","nov","dic")&" "&YEAR('Cálculos'!B137) -> mar 2026 | D58: =IF(COUNT('Cálculos'!C137)=0,"",'Cálculos'!C137) | F58: =IF(COUNT('Cálculos'!D137)=0,"",'Cálculos'!D137) | H58: =IF(COUNT('Cálculos'!E137)=0,"",'Cálculos'!E137) | J58: =IF(COUNT('Cálculos'!F137)=0,"",'Cálculos'!F137)
B59: =CHOOSE(MONTH('Cálculos'!B138),"ene","feb","mar","abr","may","jun","jul","ago","sep","oct","nov","dic")&" "&YEAR('Cálculos'!B138) -> abr 2026 | D59: =IF(COUNT('Cálculos'!C138)=0,"",'Cálculos'!C138) | F59: =IF(COUNT('Cálculos'!D138)=0,"",'Cálculos'!D138) | H59: =IF(COUNT('Cálculos'!E138)=0,"",'Cálculos'!E138) | J59: =IF(COUNT('Cálculos'!F138)=0,"",'Cálculos'!F138)
B60: =CHOOSE(MONTH('Cálculos'!B139),"ene","feb","mar","abr","may","jun","jul","ago","sep","oct","nov","dic")&" "&YEAR('Cálculos'!B139) -> may 2026 | D60: =IF(COUNT('Cálculos'!C139)=0,"",'Cálculos'!C139) | F60: =IF(COUNT('Cálculos'!D139)=0,"",'Cálculos'!D139) | H60: =IF(COUNT('Cálculos'!E139)=0,"",'Cálculos'!E139) | J60: =IF(COUNT('Cálculos'!F139)=0,"",'Cálculos'!F139)
B61: =CHOOSE(MONTH('Cálculos'!B140),"ene","feb","mar","abr","may","jun","jul","ago","sep","oct","nov","dic")&" "&YEAR('Cálculos'!B140) -> jun 2026 | D61: =IF(COUNT('Cálculos'!C140)=0,"",'Cálculos'!C140) | F61: =IF(COUNT('Cálculos'!D140)=0,"",'Cálculos'!D140) | H61: =IF(COUNT('Cálculos'!E140)=0,"",'Cálculos'!E140) | J61: =IF(COUNT('Cálculos'!F140)=0,"",'Cálculos'!F140)
B62: =CHOOSE(MONTH('Cálculos'!B141),"ene","feb","mar","abr","may","jun","jul","ago","sep","oct","nov","dic")&" "&YEAR('Cálculos'!B141) -> jul 2026 | D62: =IF(COUNT('Cálculos'!C141)=0,"",'Cálculos'!C141) | F62: =IF(COUNT('Cálculos'!D141)=0,"",'Cálculos'!D141) | H62: =IF(COUNT('Cálculos'!E141)=0,"",'Cálculos'!E141) | J62: =IF(COUNT('Cálculos'!F141)=0,"",'Cálculos'!F141)
B63: =CHOOSE(MONTH('Cálculos'!B142),"ene","feb","mar","abr","may","jun","jul","ago","sep","oct","nov","dic")&" "&YEAR('Cálculos'!B142) -> ago 2026 | D63: =IF(COUNT('Cálculos'!C142)=0,"",'Cálculos'!C142) | F63: =IF(COUNT('Cálculos'!D142)=0,"",'Cálculos'!D142) | H63: =IF(COUNT('Cálculos'!E142)=0,"",'Cálculos'!E142) | J63: =IF(COUNT('Cálculos'!F142)=0,"",'Cálculos'!F142)
B64: =CHOOSE(MONTH('Cálculos'!B143),"ene","feb","mar","abr","may","jun","jul","ago","sep","oct","nov","dic")&" "&YEAR('Cálculos'!B143) -> sep 2026 | D64: =IF(COUNT('Cálculos'!C143)=0,"",'Cálculos'!C143) | F64: =IF(COUNT('Cálculos'!D143)=0,"",'Cálculos'!D143) | H64: =IF(COUNT('Cálculos'!E143)=0,"",'Cálculos'!E143) | J64: =IF(COUNT('Cálculos'!F143)=0,"",'Cálculos'!F143)
B65: =CHOOSE(MONTH('Cálculos'!B144),"ene","feb","mar","abr","may","jun","jul","ago","sep","oct","nov","dic")&" "&YEAR('Cálculos'!B144) -> oct 2026 | D65: =IF(COUNT('Cálculos'!C144)=0,"",'Cálculos'!C144) | F65: =IF(COUNT('Cálculos'!D144)=0,"",'Cálculos'!D144) | H65: =IF(COUNT('Cálculos'!E144)=0,"",'Cálculos'!E144) | J65: =IF(COUNT('Cálculos'!F144)=0,"",'Cálculos'!F144)
B66: =CHOOSE(MONTH('Cálculos'!B145),"ene","feb","mar","abr","may","jun","jul","ago","sep","oct","nov","dic")&" "&YEAR('Cálculos'!B145) -> nov 2026 | D66: =IF(COUNT('Cálculos'!C145)=0,"",'Cálculos'!C145) | F66: =IF(COUNT('Cálculos'!D145)=0,"",'Cálculos'!D145) | H66: =IF(COUNT('Cálculos'!E145)=0,"",'Cálculos'!E145) | J66: =IF(COUNT('Cálculos'!F145)=0,"",'Cálculos'!F145)
B67: =CHOOSE(MONTH('Cálculos'!B146),"ene","feb","mar","abr","may","jun","jul","ago","sep","oct","nov","dic")&" "&YEAR('Cálculos'!B146) -> dic 2026 | D67: =IF(COUNT('Cálculos'!C146)=0,"",'Cálculos'!C146) | F67: =IF(COUNT('Cálculos'!D146)=0,"",'Cálculos'!D146) | H67: =IF(COUNT('Cálculos'!E146)=0,"",'Cálculos'!E146) | J67: =IF(COUNT('Cálculos'!F146)=0,"",'Cálculos'!F146)

Sheet Movimientos
B2: Movimientos
B8: ID | C8: Fecha | D8: Tipo | E8: Concepto | F8: Subcategoría | G8: Origen | H8: Destino | I8: Importe | J8: Recuperable | K8: Localización | L8: Recurrente

Sheet Inversiones
B2: Inversiones
B4: Producto | D4: Todos | K4: Valoración | M4: ='Configuración'!$C$8 -> 46023
B5: Cartera | F5: Capital neto | J5: Resultado
B6: ='Cálculos'!D5 -> 0 | F6: =SUM(tProductos[Aportado neto]) -> 0 | J6: =IF(COUNT('Cálculos'!D5)=0,"",SUM(tProductos[Resultado])) -> 0
B29: ID | C29: Producto | D29: Cuenta | E29: Clase | F29: Fecha base | G29: Unidades base | H29: Coste base | I29: Participaciones | J29: Aportado neto | K29: Valor | L29: Resultado | M29: Rentabilidad | N29: Peso
I30: =IF(OR(B30="",'Configuración'!$C$8<F30),"",G30+SUMIFS(tOperaciones[Participaciones],tOperaciones[Producto],B30,tOperaciones[Tipo],"Compra",tOperaciones[Fecha],">="&F30,tOperaciones[Fecha],"<="&'Configuración'!$C$8)-SUMIFS(tOperaciones[Participaciones],tOperaciones[Producto],B30,tOperaciones[Tipo],"Venta",tOperaciones[Fecha],">="&F30,tOperaciones[Fecha],"<="&'Configuración'!$C$8)) | J30: =IF(OR(B30="",'Configuración'!$C$8<F30),"",H30+SUMIFS(tOperaciones[Importe],tOperaciones[Producto],B30,tOperaciones[Tipo],"Compra",tOperaciones[Fecha],">="&F30,tOperaciones[Fecha],"<="&'Configuración'!$C$8)-SUMIFS(tOperaciones[Importe],tOperaciones[Producto],B30,tOperaciones[Tipo],"Venta",tOperaciones[Fecha],">="&F30,tOperaciones[Fecha],"<="&'Configuración'!$C$8)) | K30: =IF(OR(B30="",COUNT(I30)=0),"",IF(I30=0,0,IF(COUNTIFS(tPrecios[Producto],B30,tPrecios[Fecha],"<="&'Configuración'!$C$8)=0,"",I30*SUMIFS(tPrecios[VL EUR],tPrecios[Producto],B30,tPrecios[Fecha],MAXIFS(tPrecios[Fecha],tPrecios[Producto],B30,tPrecios[Fecha],"<="&'Configuración'!$C$8))))) | L30: =IF(OR(B30="",COUNT(K30)=0),"",K30-J30+SUMIFS(tOperaciones[Importe],tOperaciones[Producto],B30,tOperaciones[Tipo],"Cobro",tOperaciones[Fecha],">="&F30,tOperaciones[Fecha],"<="&'Configuración'!$C$8)) | M30: =IF(OR(B30="",COUNT(L30)=0,H30+SUMIFS(tOperaciones[Importe],tOperaciones[Producto],B30,tOperaciones[Tipo],"Compra",tOperaciones[Fecha],"<="&'Configuración'!$C$8)=0),"",L30/(H30+SUMIFS(tOperaciones[Importe],tOperaciones[Producto],B30,tOperaciones[Tipo],"Compra",tOperaciones[Fecha],"<="&'Configuración'!$C$8))) | N30: =IF(OR(B30="",COUNT(K30)=0,COUNT(tProductos[Valor])<>COUNTA(tProductos[ID]),SUM(tProductos[Valor])=0),"",K30/SUM(tProductos[Valor]))
I31: =IF(OR(B31="",'Configuración'!$C$8<F31),"",G31+SUMIFS(tOperaciones[Participaciones],tOperaciones[Producto],B31,tOperaciones[Tipo],"Compra",tOperaciones[Fecha],">="&F31,tOperaciones[Fecha],"<="&'Configuración'!$C$8)-SUMIFS(tOperaciones[Participaciones],tOperaciones[Producto],B31,tOperaciones[Tipo],"Venta",tOperaciones[Fecha],">="&F31,tOperaciones[Fecha],"<="&'Configuración'!$C$8)) | J31: =IF(OR(B31="",'Configuración'!$C$8<F31),"",H31+SUMIFS(tOperaciones[Importe],tOperaciones[Producto],B31,tOperaciones[Tipo],"Compra",tOperaciones[Fecha],">="&F31,tOperaciones[Fecha],"<="&'Configuración'!$C$8)-SUMIFS(tOperaciones[Importe],tOperaciones[Producto],B31,tOperaciones[Tipo],"Venta",tOperaciones[Fecha],">="&F31,tOperaciones[Fecha],"<="&'Configuración'!$C$8)) | K31: =IF(OR(B31="",COUNT(I31)=0),"",IF(I31=0,0,IF(COUNTIFS(tPrecios[Producto],B31,tPrecios[Fecha],"<="&'Configuración'!$C$8)=0,"",I31*SUMIFS(tPrecios[VL EUR],tPrecios[Producto],B31,tPrecios[Fecha],MAXIFS(tPrecios[Fecha],tPrecios[Producto],B31,tPrecios[Fecha],"<="&'Configuración'!$C$8))))) | L31: =IF(OR(B31="",COUNT(K31)=0),"",K31-J31+SUMIFS(tOperaciones[Importe],tOperaciones[Producto],B31,tOperaciones[Tipo],"Cobro",tOperaciones[Fecha],">="&F31,tOperaciones[Fecha],"<="&'Configuración'!$C$8)) | M31: =IF(OR(B31="",COUNT(L31)=0,H31+SUMIFS(tOperaciones[Importe],tOperaciones[Producto],B31,tOperaciones[Tipo],"Compra",tOperaciones[Fecha],"<="&'Configuración'!$C$8)=0),"",L31/(H31+SUMIFS(tOperaciones[Importe],tOperaciones[Producto],B31,tOperaciones[Tipo],"Compra",tOperaciones[Fecha],"<="&'Configuración'!$C$8))) | N31: =IF(OR(B31="",COUNT(K31)=0,COUNT(tProductos[Valor])<>COUNTA(tProductos[ID]),SUM(tProductos[Valor])=0),"",K31/SUM(tProductos[Valor]))
I32: =IF(OR(B32="",'Configuración'!$C$8<F32),"",G32+SUMIFS(tOperaciones[Participaciones],tOperaciones[Producto],B32,tOperaciones[Tipo],"Compra",tOperaciones[Fecha],">="&F32,tOperaciones[Fecha],"<="&'Configuración'!$C$8)-SUMIFS(tOperaciones[Participaciones],tOperaciones[Producto],B32,tOperaciones[Tipo],"Venta",tOperaciones[Fecha],">="&F32,tOperaciones[Fecha],"<="&'Configuración'!$C$8)) | J32: =IF(OR(B32="",'Configuración'!$C$8<F32),"",H32+SUMIFS(tOperaciones[Importe],tOperaciones[Producto],B32,tOperaciones[Tipo],"Compra",tOperaciones[Fecha],">="&F32,tOperaciones[Fecha],"<="&'Configuración'!$C$8)-SUMIFS(tOperaciones[Importe],tOperaciones[Producto],B32,tOperaciones[Tipo],"Venta",tOperaciones[Fecha],">="&F32,tOperaciones[Fecha],"<="&'Configuración'!$C$8)) | K32: =IF(OR(B32="",COUNT(I32)=0),"",IF(I32=0,0,IF(COUNTIFS(tPrecios[Producto],B32,tPrecios[Fecha],"<="&'Configuración'!$C$8)=0,"",I32*SUMIFS(tPrecios[VL EUR],tPrecios[Producto],B32,tPrecios[Fecha],MAXIFS(tPrecios[Fecha],tPrecios[Producto],B32,tPrecios[Fecha],"<="&'Configuración'!$C$8))))) | L32: =IF(OR(B32="",COUNT(K32)=0),"",K32-J32+SUMIFS(tOperaciones[Importe],tOperaciones[Producto],B32,tOperaciones[Tipo],"Cobro",tOperaciones[Fecha],">="&F32,tOperaciones[Fecha],"<="&'Configuración'!$C$8)) | M32: =IF(OR(B32="",COUNT(L32)=0,H32+SUMIFS(tOperaciones[Importe],tOperaciones[Producto],B32,tOperaciones[Tipo],"Compra",tOperaciones[Fecha],"<="&'Configuración'!$C$8)=0),"",L32/(H32+SUMIFS(tOperaciones[Importe],tOperaciones[Producto],B32,tOperaciones[Tipo],"Compra",tOperaciones[Fecha],"<="&'Configuración'!$C$8))) | N32: =IF(OR(B32="",COUNT(K32)=0,COUNT(tProductos[Valor])<>COUNTA(tProductos[ID]),SUM(tProductos[Valor])=0),"",K32/SUM(tProductos[Valor]))
I33: =IF(OR(B33="",'Configuración'!$C$8<F33),"",G33+SUMIFS(tOperaciones[Participaciones],tOperaciones[Producto],B33,tOperaciones[Tipo],"Compra",tOperaciones[Fecha],">="&F33,tOperaciones[Fecha],"<="&'Configuración'!$C$8)-SUMIFS(tOperaciones[Participaciones],tOperaciones[Producto],B33,tOperaciones[Tipo],"Venta",tOperaciones[Fecha],">="&F33,tOperaciones[Fecha],"<="&'Configuración'!$C$8)) | J33: =IF(OR(B33="",'Configuración'!$C$8<F33),"",H33+SUMIFS(tOperaciones[Importe],tOperaciones[Producto],B33,tOperaciones[Tipo],"Compra",tOperaciones[Fecha],">="&F33,tOperaciones[Fecha],"<="&'Configuración'!$C$8)-SUMIFS(tOperaciones[Importe],tOperaciones[Producto],B33,tOperaciones[Tipo],"Venta",tOperaciones[Fecha],">="&F33,tOperaciones[Fecha],"<="&'Configuración'!$C$8)) | K33: =IF(OR(B33="",COUNT(I33)=0),"",IF(I33=0,0,IF(COUNTIFS(tPrecios[Producto],B33,tPrecios[Fecha],"<="&'Configuración'!$C$8)=0,"",I33*SUMIFS(tPrecios[VL EUR],tPrecios[Producto],B33,tPrecios[Fecha],MAXIFS(tPrecios[Fecha],tPrecios[Producto],B33,tPrecios[Fecha],"<="&'Configuración'!$C$8))))) | L33: =IF(OR(B33="",COUNT(K33)=0),"",K33-J33+SUMIFS(tOperaciones[Importe],tOperaciones[Producto],B33,tOperaciones[Tipo],"Cobro",tOperaciones[Fecha],">="&F33,tOperaciones[Fecha],"<="&'Configuración'!$C$8)) | M33: =IF(OR(B33="",COUNT(L33)=0,H33+SUMIFS(tOperaciones[Importe],tOperaciones[Producto],B33,tOperaciones[Tipo],"Compra",tOperaciones[Fecha],"<="&'Configuración'!$C$8)=0),"",L33/(H33+SUMIFS(tOperaciones[Importe],tOperaciones[Producto],B33,tOperaciones[Tipo],"Compra",tOperaciones[Fecha],"<="&'Configuración'!$C$8))) | N33: =IF(OR(B33="",COUNT(K33)=0,COUNT(tProductos[Valor])<>COUNTA(tProductos[ID]),SUM(tProductos[Valor])=0),"",K33/SUM(tProductos[Valor]))
I34: =IF(OR(B34="",'Configuración'!$C$8<F34),"",G34+SUMIFS(tOperaciones[Participaciones],tOperaciones[Producto],B34,tOperaciones[Tipo],"Compra",tOperaciones[Fecha],">="&F34,tOperaciones[Fecha],"<="&'Configuración'!$C$8)-SUMIFS(tOperaciones[Participaciones],tOperaciones[Producto],B34,tOperaciones[Tipo],"Venta",tOperaciones[Fecha],">="&F34,tOperaciones[Fecha],"<="&'Configuración'!$C$8)) | J34: =IF(OR(B34="",'Configuración'!$C$8<F34),"",H34+SUMIFS(tOperaciones[Importe],tOperaciones[Producto],B34,tOperaciones[Tipo],"Compra",tOperaciones[Fecha],">="&F34,tOperaciones[Fecha],"<="&'Configuración'!$C$8)-SUMIFS(tOperaciones[Importe],tOperaciones[Producto],B34,tOperaciones[Tipo],"Venta",tOperaciones[Fecha],">="&F34,tOperaciones[Fecha],"<="&'Configuración'!$C$8)) | K34: =IF(OR(B34="",COUNT(I34)=0),"",IF(I34=0,0,IF(COUNTIFS(tPrecios[Producto],B34,tPrecios[Fecha],"<="&'Configuración'!$C$8)=0,"",I34*SUMIFS(tPrecios[VL EUR],tPrecios[Producto],B34,tPrecios[Fecha],MAXIFS(tPrecios[Fecha],tPrecios[Producto],B34,tPrecios[Fecha],"<="&'Configuración'!$C$8))))) | L34: =IF(OR(B34="",COUNT(K34)=0),"",K34-J34+SUMIFS(tOperaciones[Importe],tOperaciones[Producto],B34,tOperaciones[Tipo],"Cobro",tOperaciones[Fecha],">="&F34,tOperaciones[Fecha],"<="&'Configuración'!$C$8)) | M34: =IF(OR(B34="",COUNT(L34)=0,H34+SUMIFS(tOperaciones[Importe],tOperaciones[Producto],B34,tOperaciones[Tipo],"Compra",tOperaciones[Fecha],"<="&'Configuración'!$C$8)=0),"",L34/(H34+SUMIFS(tOperaciones[Importe],tOperaciones[Producto],B34,tOperaciones[Tipo],"Compra",tOperaciones[Fecha],"<="&'Configuración'!$C$8))) | N34: =IF(OR(B34="",COUNT(K34)=0,COUNT(tProductos[Valor])<>COUNTA(tProductos[ID]),SUM(tProductos[Valor])=0),"",K34/SUM(tProductos[Valor]))
I35: =IF(OR(B35="",'Configuración'!$C$8<F35),"",G35+SUMIFS(tOperaciones[Participaciones],tOperaciones[Producto],B35,tOperaciones[Tipo],"Compra",tOperaciones[Fecha],">="&F35,tOperaciones[Fecha],"<="&'Configuración'!$C$8)-SUMIFS(tOperaciones[Participaciones],tOperaciones[Producto],B35,tOperaciones[Tipo],"Venta",tOperaciones[Fecha],">="&F35,tOperaciones[Fecha],"<="&'Configuración'!$C$8)) | J35: =IF(OR(B35="",'Configuración'!$C$8<F35),"",H35+SUMIFS(tOperaciones[Importe],tOperaciones[Producto],B35,tOperaciones[Tipo],"Compra",tOperaciones[Fecha],">="&F35,tOperaciones[Fecha],"<="&'Configuración'!$C$8)-SUMIFS(tOperaciones[Importe],tOperaciones[Producto],B35,tOperaciones[Tipo],"Venta",tOperaciones[Fecha],">="&F35,tOperaciones[Fecha],"<="&'Configuración'!$C$8)) | K35: =IF(OR(B35="",COUNT(I35)=0),"",IF(I35=0,0,IF(COUNTIFS(tPrecios[Producto],B35,tPrecios[Fecha],"<="&'Configuración'!$C$8)=0,"",I35*SUMIFS(tPrecios[VL EUR],tPrecios[Producto],B35,tPrecios[Fecha],MAXIFS(tPrecios[Fecha],tPrecios[Producto],B35,tPrecios[Fecha],"<="&'Configuración'!$C$8))))) | L35: =IF(OR(B35="",COUNT(K35)=0),"",K35-J35+SUMIFS(tOperaciones[Importe],tOperaciones[Producto],B35,tOperaciones[Tipo],"Cobro",tOperaciones[Fecha],">="&F35,tOperaciones[Fecha],"<="&'Configuración'!$C$8)) | M35: =IF(OR(B35="",COUNT(L35)=0,H35+SUMIFS(tOperaciones[Importe],tOperaciones[Producto],B35,tOperaciones[Tipo],"Compra",tOperaciones[Fecha],"<="&'Configuración'!$C$8)=0),"",L35/(H35+SUMIFS(tOperaciones[Importe],tOperaciones[Producto],B35,tOperaciones[Tipo],"Compra",tOperaciones[Fecha],"<="&'Configuración'!$C$8))) | N35: =IF(OR(B35="",COUNT(K35)=0,COUNT(tProductos[Valor])<>COUNTA(tProductos[ID]),SUM(tProductos[Valor])=0),"",K35/SUM(tProductos[Valor]))
I36: =IF(OR(B36="",'Configuración'!$C$8<F36),"",G36+SUMIFS(tOperaciones[Participaciones],tOperaciones[Producto],B36,tOperaciones[Tipo],"Compra",tOperaciones[Fecha],">="&F36,tOperaciones[Fecha],"<="&'Configuración'!$C$8)-SUMIFS(tOperaciones[Participaciones],tOperaciones[Producto],B36,tOperaciones[Tipo],"Venta",tOperaciones[Fecha],">="&F36,tOperaciones[Fecha],"<="&'Configuración'!$C$8)) | J36: =IF(OR(B36="",'Configuración'!$C$8<F36),"",H36+SUMIFS(tOperaciones[Importe],tOperaciones[Producto],B36,tOperaciones[Tipo],"Compra",tOperaciones[Fecha],">="&F36,tOperaciones[Fecha],"<="&'Configuración'!$C$8)-SUMIFS(tOperaciones[Importe],tOperaciones[Producto],B36,tOperaciones[Tipo],"Venta",tOperaciones[Fecha],">="&F36,tOperaciones[Fecha],"<="&'Configuración'!$C$8)) | K36: =IF(OR(B36="",COUNT(I36)=0),"",IF(I36=0,0,IF(COUNTIFS(tPrecios[Producto],B36,tPrecios[Fecha],"<="&'Configuración'!$C$8)=0,"",I36*SUMIFS(tPrecios[VL EUR],tPrecios[Producto],B36,tPrecios[Fecha],MAXIFS(tPrecios[Fecha],tPrecios[Producto],B36,tPrecios[Fecha],"<="&'Configuración'!$C$8))))) | L36: =IF(OR(B36="",COUNT(K36)=0),"",K36-J36+SUMIFS(tOperaciones[Importe],tOperaciones[Producto],B36,tOperaciones[Tipo],"Cobro",tOperaciones[Fecha],">="&F36,tOperaciones[Fecha],"<="&'Configuración'!$C$8)) | M36: =IF(OR(B36="",COUNT(L36)=0,H36+SUMIFS(tOperaciones[Importe],tOperaciones[Producto],B36,tOperaciones[Tipo],"Compra",tOperaciones[Fecha],"<="&'Configuración'!$C$8)=0),"",L36/(H36+SUMIFS(tOperaciones[Importe],tOperaciones[Producto],B36,tOperaciones[Tipo],"Compra",tOperaciones[Fecha],"<="&'Configuración'!$C$8))) | N36: =IF(OR(B36="",COUNT(K36)=0,COUNT(tProductos[Valor])<>COUNTA(tProductos[ID]),SUM(tProductos[Valor])=0),"",K36/SUM(tProductos[Valor]))
I37: =IF(OR(B37="",'Configuración'!$C$8<F37),"",G37+SUMIFS(tOperaciones[Participaciones],tOperaciones[Producto],B37,tOperaciones[Tipo],"Compra",tOperaciones[Fecha],">="&F37,tOperaciones[Fecha],"<="&'Configuración'!$C$8)-SUMIFS(tOperaciones[Participaciones],tOperaciones[Producto],B37,tOperaciones[Tipo],"Venta",tOperaciones[Fecha],">="&F37,tOperaciones[Fecha],"<="&'Configuración'!$C$8)) | J37: =IF(OR(B37="",'Configuración'!$C$8<F37),"",H37+SUMIFS(tOperaciones[Importe],tOperaciones[Producto],B37,tOperaciones[Tipo],"Compra",tOperaciones[Fecha],">="&F37,tOperaciones[Fecha],"<="&'Configuración'!$C$8)-SUMIFS(tOperaciones[Importe],tOperaciones[Producto],B37,tOperaciones[Tipo],"Venta",tOperaciones[Fecha],">="&F37,tOperaciones[Fecha],"<="&'Configuración'!$C$8)) | K37: =IF(OR(B37="",COUNT(I37)=0),"",IF(I37=0,0,IF(COUNTIFS(tPrecios[Producto],B37,tPrecios[Fecha],"<="&'Configuración'!$C$8)=0,"",I37*SUMIFS(tPrecios[VL EUR],tPrecios[Producto],B37,tPrecios[Fecha],MAXIFS(tPrecios[Fecha],tPrecios[Producto],B37,tPrecios[Fecha],"<="&'Configuración'!$C$8))))) | L37: =IF(OR(B37="",COUNT(K37)=0),"",K37-J37+SUMIFS(tOperaciones[Importe],tOperaciones[Producto],B37,tOperaciones[Tipo],"Cobro",tOperaciones[Fecha],">="&F37,tOperaciones[Fecha],"<="&'Configuración'!$C$8)) | M37: =IF(OR(B37="",COUNT(L37)=0,H37+SUMIFS(tOperaciones[Importe],tOperaciones[Producto],B37,tOperaciones[Tipo],"Compra",tOperaciones[Fecha],"<="&'Configuración'!$C$8)=0),"",L37/(H37+SUMIFS(tOperaciones[Importe],tOperaciones[Producto],B37,tOperaciones[Tipo],"Compra",tOperaciones[Fecha],"<="&'Configuración'!$C$8))) | N37: =IF(OR(B37="",COUNT(K37)=0,COUNT(tProductos[Valor])<>COUNTA(tProductos[ID]),SUM(tProductos[Valor])=0),"",K37/SUM(tProductos[Valor]))
I38: =IF(OR(B38="",'Configuración'!$C$8<F38),"",G38+SUMIFS(tOperaciones[Participaciones],tOperaciones[Producto],B38,tOperaciones[Tipo],"Compra",tOperaciones[Fecha],">="&F38,tOperaciones[Fecha],"<="&'Configuración'!$C$8)-SUMIFS(tOperaciones[Participaciones],tOperaciones[Producto],B38,tOperaciones[Tipo],"Venta",tOperaciones[Fecha],">="&F38,tOperaciones[Fecha],"<="&'Configuración'!$C$8)) | J38: =IF(OR(B38="",'Configuración'!$C$8<F38),"",H38+SUMIFS(tOperaciones[Importe],tOperaciones[Producto],B38,tOperaciones[Tipo],"Compra",tOperaciones[Fecha],">="&F38,tOperaciones[Fecha],"<="&'Configuración'!$C$8)-SUMIFS(tOperaciones[Importe],tOperaciones[Producto],B38,tOperaciones[Tipo],"Venta",tOperaciones[Fecha],">="&F38,tOperaciones[Fecha],"<="&'Configuración'!$C$8)) | K38: =IF(OR(B38="",COUNT(I38)=0),"",IF(I38=0,0,IF(COUNTIFS(tPrecios[Producto],B38,tPrecios[Fecha],"<="&'Configuración'!$C$8)=0,"",I38*SUMIFS(tPrecios[VL EUR],tPrecios[Producto],B38,tPrecios[Fecha],MAXIFS(tPrecios[Fecha],tPrecios[Producto],B38,tPrecios[Fecha],"<="&'Configuración'!$C$8))))) | L38: =IF(OR(B38="",COUNT(K38)=0),"",K38-J38+SUMIFS(tOperaciones[Importe],tOperaciones[Producto],B38,tOperaciones[Tipo],"Cobro",tOperaciones[Fecha],">="&F38,tOperaciones[Fecha],"<="&'Configuración'!$C$8)) | M38: =IF(OR(B38="",COUNT(L38)=0,H38+SUMIFS(tOperaciones[Importe],tOperaciones[Producto],B38,tOperaciones[Tipo],"Compra",tOperaciones[Fecha],"<="&'Configuración'!$C$8)=0),"",L38/(H38+SUMIFS(tOperaciones[Importe],tOperaciones[Producto],B38,tOperaciones[Tipo],"Compra",tOperaciones[Fecha],"<="&'Configuración'!$C$8))) | N38: =IF(OR(B38="",COUNT(K38)=0,COUNT(tProductos[Valor])<>COUNTA(tProductos[ID]),SUM(tProductos[Valor])=0),"",K38/SUM(tProductos[Valor]))
I39: =IF(OR(B39="",'Configuración'!$C$8<F39),"",G39+SUMIFS(tOperaciones[Participaciones],tOperaciones[Producto],B39,tOperaciones[Tipo],"Compra",tOperaciones[Fecha],">="&F39,tOperaciones[Fecha],"<="&'Configuración'!$C$8)-SUMIFS(tOperaciones[Participaciones],tOperaciones[Producto],B39,tOperaciones[Tipo],"Venta",tOperaciones[Fecha],">="&F39,tOperaciones[Fecha],"<="&'Configuración'!$C$8)) | J39: =IF(OR(B39="",'Configuración'!$C$8<F39),"",H39+SUMIFS(tOperaciones[Importe],tOperaciones[Producto],B39,tOperaciones[Tipo],"Compra",tOperaciones[Fecha],">="&F39,tOperaciones[Fecha],"<="&'Configuración'!$C$8)-SUMIFS(tOperaciones[Importe],tOperaciones[Producto],B39,tOperaciones[Tipo],"Venta",tOperaciones[Fecha],">="&F39,tOperaciones[Fecha],"<="&'Configuración'!$C$8)) | K39: =IF(OR(B39="",COUNT(I39)=0),"",IF(I39=0,0,IF(COUNTIFS(tPrecios[Producto],B39,tPrecios[Fecha],"<="&'Configuración'!$C$8)=0,"",I39*SUMIFS(tPrecios[VL EUR],tPrecios[Producto],B39,tPrecios[Fecha],MAXIFS(tPrecios[Fecha],tPrecios[Producto],B39,tPrecios[Fecha],"<="&'Configuración'!$C$8))))) | L39: =IF(OR(B39="",COUNT(K39)=0),"",K39-J39+SUMIFS(tOperaciones[Importe],tOperaciones[Producto],B39,tOperaciones[Tipo],"Cobro",tOperaciones[Fecha],">="&F39,tOperaciones[Fecha],"<="&'Configuración'!$C$8)) | M39: =IF(OR(B39="",COUNT(L39)=0,H39+SUMIFS(tOperaciones[Importe],tOperaciones[Producto],B39,tOperaciones[Tipo],"Compra",tOperaciones[Fecha],"<="&'Configuración'!$C$8)=0),"",L39/(H39+SUMIFS(tOperaciones[Importe],tOperaciones[Producto],B39,tOperaciones[Tipo],"Compra",tOperaciones[Fecha],"<="&'Configuración'!$C$8))) | N39: =IF(OR(B39="",COUNT(K39)=0,COUNT(tProductos[Valor])<>COUNTA(tProductos[ID]),SUM(tProductos[Valor])=0),"",K39/SUM(tProductos[Valor]))
I40: =IF(OR(B40="",'Configuración'!$C$8<F40),"",G40+SUMIFS(tOperaciones[Participaciones],tOperaciones[Producto],B40,tOperaciones[Tipo],"Compra",tOperaciones[Fecha],">="&F40,tOperaciones[Fecha],"<="&'Configuración'!$C$8)-SUMIFS(tOperaciones[Participaciones],tOperaciones[Producto],B40,tOperaciones[Tipo],"Venta",tOperaciones[Fecha],">="&F40,tOperaciones[Fecha],"<="&'Configuración'!$C$8)) | J40: =IF(OR(B40="",'Configuración'!$C$8<F40),"",H40+SUMIFS(tOperaciones[Importe],tOperaciones[Producto],B40,tOperaciones[Tipo],"Compra",tOperaciones[Fecha],">="&F40,tOperaciones[Fecha],"<="&'Configuración'!$C$8)-SUMIFS(tOperaciones[Importe],tOperaciones[Producto],B40,tOperaciones[Tipo],"Venta",tOperaciones[Fecha],">="&F40,tOperaciones[Fecha],"<="&'Configuración'!$C$8)) | K40: =IF(OR(B40="",COUNT(I40)=0),"",IF(I40=0,0,IF(COUNTIFS(tPrecios[Producto],B40,tPrecios[Fecha],"<="&'Configuración'!$C$8)=0,"",I40*SUMIFS(tPrecios[VL EUR],tPrecios[Producto],B40,tPrecios[Fecha],MAXIFS(tPrecios[Fecha],tPrecios[Producto],B40,tPrecios[Fecha],"<="&'Configuración'!$C$8))))) | L40: =IF(OR(B40="",COUNT(K40)=0),"",K40-J40+SUMIFS(tOperaciones[Importe],tOperaciones[Producto],B40,tOperaciones[Tipo],"Cobro",tOperaciones[Fecha],">="&F40,tOperaciones[Fecha],"<="&'Configuración'!$C$8)) | M40: =IF(OR(B40="",COUNT(L40)=0,H40+SUMIFS(tOperaciones[Importe],tOperaciones[Producto],B40,tOperaciones[Tipo],"Compra",tOperaciones[Fecha],"<="&'Configuración'!$C$8)=0),"",L40/(H40+SUMIFS(tOperaciones[Importe],tOperaciones[Producto],B40,tOperaciones[Tipo],"Compra",tOperaciones[Fecha],"<="&'Configuración'!$C$8))) | N40: =IF(OR(B40="",COUNT(K40)=0,COUNT(tProductos[Valor])<>COUNTA(tProductos[ID]),SUM(tProductos[Valor])=0),"",K40/SUM(tProductos[Valor]))
I41: =IF(OR(B41="",'Configuración'!$C$8<F41),"",G41+SUMIFS(tOperaciones[Participaciones],tOperaciones[Producto],B41,tOperaciones[Tipo],"Compra",tOperaciones[Fecha],">="&F41,tOperaciones[Fecha],"<="&'Configuración'!$C$8)-SUMIFS(tOperaciones[Participaciones],tOperaciones[Producto],B41,tOperaciones[Tipo],"Venta",tOperaciones[Fecha],">="&F41,tOperaciones[Fecha],"<="&'Configuración'!$C$8)) | J41: =IF(OR(B41="",'Configuración'!$C$8<F41),"",H41+SUMIFS(tOperaciones[Importe],tOperaciones[Producto],B41,tOperaciones[Tipo],"Compra",tOperaciones[Fecha],">="&F41,tOperaciones[Fecha],"<="&'Configuración'!$C$8)-SUMIFS(tOperaciones[Importe],tOperaciones[Producto],B41,tOperaciones[Tipo],"Venta",tOperaciones[Fecha],">="&F41,tOperaciones[Fecha],"<="&'Configuración'!$C$8)) | K41: =IF(OR(B41="",COUNT(I41)=0),"",IF(I41=0,0,IF(COUNTIFS(tPrecios[Producto],B41,tPrecios[Fecha],"<="&'Configuración'!$C$8)=0,"",I41*SUMIFS(tPrecios[VL EUR],tPrecios[Producto],B41,tPrecios[Fecha],MAXIFS(tPrecios[Fecha],tPrecios[Producto],B41,tPrecios[Fecha],"<="&'Configuración'!$C$8))))) | L41: =IF(OR(B41="",COUNT(K41)=0),"",K41-J41+SUMIFS(tOperaciones[Importe],tOperaciones[Producto],B41,tOperaciones[Tipo],"Cobro",tOperaciones[Fecha],">="&F41,tOperaciones[Fecha],"<="&'Configuración'!$C$8)) | M41: =IF(OR(B41="",COUNT(L41)=0,H41+SUMIFS(tOperaciones[Importe],tOperaciones[Producto],B41,tOperaciones[Tipo],"Compra",tOperaciones[Fecha],"<="&'Configuración'!$C$8)=0),"",L41/(H41+SUMIFS(tOperaciones[Importe],tOperaciones[Producto],B41,tOperaciones[Tipo],"Compra",tOperaciones[Fecha],"<="&'Configuración'!$C$8))) | N41: =IF(OR(B41="",COUNT(K41)=0,COUNT(tProductos[Valor])<>COUNTA(tProductos[ID]),SUM(tProductos[Valor])=0),"",K41/SUM(tProductos[Valor]))
... I149: =IF(OR(B149="",'Configuración'!$C$8<F149),"",G149+SUMIFS(tOperaciones[Participaciones],tOperaciones[Producto],B149,tOperaciones[Tipo],"Compra",tOperaciones[Fecha],">="&F149,tOperaciones[Fecha],"<="&'Configuración'!$C$8)-SUMIFS(tOperaciones[Participaciones],tOperaciones[Producto],B149,tOperaciones[Tipo],"Venta",tOperaciones[Fecha],">="&F149,tOperaciones[Fecha],"<="&'Configuración'!$C$8)) | J149: =IF(OR(B149="",'Configuración'!$C$8<F149),"",H149+SUMIFS(tOperaciones[Importe],tOperaciones[Producto],B149,tOperaciones[Tipo],"Compra",tOperaciones[Fecha],">="&F149,tOperaciones[Fecha],"<="&'Configuración'!$C$8)-SUMIFS(tOperaciones[Importe],tOperaciones[Producto],B149,tOperaciones[Tipo],"Venta",tOperaciones[Fecha],">="&F149,tOperaciones[Fecha],"<="&'Configuración'!$C$8)) | K149: =IF(OR(B149="",COUNT(I149)=0),"",IF(I149=0,0,IF(COUNTIFS(tPrecios[Producto],B149,tPrecios[Fecha],"<="&'Configuración'!$C$8)=0,"",I149*SUMIFS(tPrecios[VL EUR],tPrecios[Producto],B149,tPrecios[Fecha],MAXIFS(tPrecios[Fecha],tPrecios[Producto],B149,tPrecios[Fecha],"<="&'Configuración'!$C$8))))) | L149: =IF(OR(B149="",COUNT(K149)=0),"",K149-J149+SUMIFS(tOperaciones[Importe],tOperaciones[Producto],B149,tOperaciones[Tipo],"Cobro",tOperaciones[Fecha],">="&F149,tOperaciones[Fecha],"<="&'Configuración'!$C$8)) | M149: =IF(OR(B149="",COUNT(L149)=0,H149+SUMIFS(tOperaciones[Importe],tOperaciones[Producto],B149,tOperaciones[Tipo],"Compra",tOperaciones[Fecha],"<="&'Configuración'!$C$8)=0),"",L149/(H149+SUMIFS(tOperaciones[Importe],tOperaciones[Producto],B149,tOperaciones[Tipo],"Compra",tOperaciones[Fecha],"<="&'Configuración'!$C$8))) | N149: =IF(OR(B149="",COUNT(K149)=0,COUNT(tProductos[Valor])<>COUNTA(tProductos[ID]),SUM(tProductos[Valor])=0),"",K149/SUM(tProductos[Valor]))
B153: Compras, ventas y cobros
B155: ID | C155: Fecha | D155: Producto | E155: Tipo | F155: Participaciones | G155: Precio | H155: Comisión | I155: Retención | J155: Importe | K155: Movimiento
J156: =IF(B156="","",IF(E156="Compra",F156*G156+H156,IF(E156="Venta",F156*G156-H156-I156,IF(E156="Cobro",G156-H156-I156,0))))
J157: =IF(B157="","",IF(E157="Compra",F157*G157+H157,IF(E157="Venta",F157*G157-H157-I157,IF(E157="Cobro",G157-H157-I157,0))))
J158: =IF(B158="","",IF(E158="Compra",F158*G158+H158,IF(E158="Venta",F158*G158-H158-I158,IF(E158="Cobro",G158-H158-I158,0))))
J159: =IF(B159="","",IF(E159="Compra",F159*G159+H159,IF(E159="Venta",F159*G159-H159-I159,IF(E159="Cobro",G159-H159-I159,0))))
J160: =IF(B160="","",IF(E160="Compra",F160*G160+H160,IF(E160="Venta",F160*G160-H160-I160,IF(E160="Cobro",G160-H160-I160,0))))
J161: =IF(B161="","",IF(E161="Compra",F161*G161+H161,IF(E161="Venta",F161*G161-H161-I161,IF(E161="Cobro",G161-H161-I161,0))))
J162: =IF(B162="","",IF(E162="Compra",F162*G162+H162,IF(E162="Venta",F162*G162-H162-I162,IF(E162="Cobro",G162-H162-I162,0))))
J163: =IF(B163="","",IF(E163="Compra",F163*G163+H163,IF(E163="Venta",F163*G163-H163-I163,IF(E163="Cobro",G163-H163-I163,0))))
J164: =IF(B164="","",IF(E164="Compra",F164*G164+H164,IF(E164="Venta",F164*G164-H164-I164,IF(E164="Cobro",G164-H164-I164,0))))
J165: =IF(B165="","",IF(E165="Compra",F165*G165+H165,IF(E165="Venta",F165*G165-H165-I165,IF(E165="Cobro",G165-H165-I165,0))))
J166: =IF(B166="","",IF(E166="Compra",F166*G166+H166,IF(E166="Venta",F166*G166-H166-I166,IF(E166="Cobro",G166-H166-I166,0))))
J167: =IF(B167="","",IF(E167="Compra",F167*G167+H167,IF(E167="Venta",F167*G167-H167-I167,IF(E167="Cobro",G167-H167-I167,0))))
... J285: =IF(B285="","",IF(E285="Compra",F285*G285+H285,IF(E285="Venta",F285*G285-H285-I285,IF(E285="Cobro",G285-H285-I285,0))))
B289: Valores liquidativos
B291: Producto | C291: Fecha | D291: VL EUR | E291: Fuente
B925: Evolución mensual
B927: Mes | C927: Capital invertido | D927: Valor de mercado | E927: Resultado
B928: =IF(EDATE(DATE(YEAR(IF(COUNT(Inversiones!$F$30:$F$149)=0,'Configuración'!$C$8,MIN(Inversiones!$F$30:$F$149))),MONTH(IF(COUNT(Inversiones!$F$30:$F$149)=0,'Configuración'!$C$8,MIN(Inversiones!$F$30:$F$149))),1),0)>EOMONTH('Configuración'!$C$8,0),"",TEXT(EDATE(DATE(YEAR(IF(COUNT(Inversiones!$F$30:$F$149)=0,'Configuración'!$C$8,MIN(Inversiones!$F$30:$F$149))),MONTH(IF(COUNT(Inversiones!$F$30:$F$149)=0,'Configuración'!$C$8,MIN(Inversiones!$F$30:$F$149))),1),0),"mmm yyyy")) -> ene 2026 | C928: =IF(EDATE(DATE(YEAR(IF(COUNT(Inversiones!$F$30:$F$149)=0,'Configuración'!$C$8,MIN(Inversiones!$F$30:$F$149))),MONTH(IF(COUNT(Inversiones!$F$30:$F$149)=0,'Configuración'!$C$8,MIN(Inversiones!$F$30:$F$149))),1),0)>EOMONTH('Configuración'!$C$8,0),"",IF(Inversiones!$D$4="Todos",IF(SUMIFS('Cálculos'!$E$278:$E$334,'Cálculos'!$B$278:$B$334,EDATE(DATE(YEAR(IF(COUNT(Inversiones!$F$30:$F$149)=0,'Configuración'!$C$8,MIN(Inversiones!$F$30:$F$149))),MONTH(IF(COUNT(Inversiones!$F$30:$F$149)=0,'Configuración'!$C$8,MIN(Inversiones!$F$30:$F$149))),1),0))=COUNTA(Inversiones!$B$30:$B$149),SUMIFS('Cálculos'!$G$278:$G$334,'Cálculos'!$B$278:$B$334,EDATE(DATE(YEAR(IF(COUNT(Inversiones!$F$30:$F$149)=0,'Configuración'!$C$8,MIN(Inversiones!$F$30:$F$149))),MONTH(IF(COUNT(Inversiones!$F$30:$F$149)=0,'Configuración'!$C$8,MIN(Inversiones!$F$30:$F$149))),1),0)),""),IF(SUMIFS('Cálculos'!$E$278:$E$334,'Cálculos'!$B$278:$B$334,EDATE(DATE(YEAR(IF(COUNT(Inversiones!$F$30:$F$149)=0,'Configuración'!$C$8,MIN(Inversiones!$F$30:$F$149))),MONTH(IF(COUNT(Inversiones!$F$30:$F$149)=0,'Configuración'!$C$8,MIN(Inversiones!$F$30:$F$149))),1),0),'Cálculos'!$C$278:$C$334,'Cálculos'!$I$4)=1,SUMIFS('Cálculos'!$G$278:$G$334,'Cálculos'!$B$278:$B$334,EDATE(DATE(YEAR(IF(COUNT(Inversiones!$F$30:$F$149)=0,'Configuración'!$C$8,MIN(Inversiones!$F$30:$F$149))),MONTH(IF(COUNT(Inversiones!$F$30:$F$149)=0,'Configuración'!$C$8,MIN(Inversiones!$F$30:$F$149))),1),0),'Cálculos'!$C$278:$C$334,'Cálculos'!$I$4),""))) -> 0 | D928: =IF(EDATE(DATE(YEAR(IF(COUNT(Inversiones!$F$30:$F$149)=0,'Configuración'!$C$8,MIN(Inversiones!$F$30:$F$149))),MONTH(IF(COUNT(Inversiones!$F$30:$F$149)=0,'Configuración'!$C$8,MIN(Inversiones!$F$30:$F$149))),1),0)>EOMONTH('Configuración'!$C$8,0),"",IF(Inversiones!$D$4="Todos",IF(SUMIFS('Cálculos'!$K$278:$K$334,'Cálculos'!$B$278:$B$334,EDATE(DATE(YEAR(IF(COUNT(Inversiones!$F$30:$F$149)=0,'Configuración'!$C$8,MIN(Inversiones!$F$30:$F$149))),MONTH(IF(COUNT(Inversiones!$F$30:$F$149)=0,'Configuración'!$C$8,MIN(Inversiones!$F$30:$F$149))),1),0))=COUNTA(Inversiones!$B$30:$B$149),SUMIFS('Cálculos'!$J$278:$J$334,'Cálculos'!$B$278:$B$334,EDATE(DATE(YEAR(IF(COUNT(Inversiones!$F$30:$F$149)=0,'Configuración'!$C$8,MIN(Inversiones!$F$30:$F$149))),MONTH(IF(COUNT(Inversiones!$F$30:$F$149)=0,'Configuración'!$C$8,MIN(Inversiones!$F$30:$F$149))),1),0)),""),IF(SUMIFS('Cálculos'!$K$278:$K$334,'Cálculos'!$B$278:$B$334,EDATE(DATE(YEAR(IF(COUNT(Inversiones!$F$30:$F$149)=0,'Configuración'!$C$8,MIN(Inversiones!$F$30:$F$149))),MONTH(IF(COUNT(Inversiones!$F$30:$F$149)=0,'Configuración'!$C$8,MIN(Inversiones!$F$30:$F$149))),1),0),'Cálculos'!$C$278:$C$334,'Cálculos'!$I$4)=1,SUMIFS('Cálculos'!$J$278:$J$334,'Cálculos'!$B$278:$B$334,EDATE(DATE(YEAR(IF(COUNT(Inversiones!$F$30:$F$149)=0,'Configuración'!$C$8,MIN(Inversiones!$F$30:$F$149))),MONTH(IF(COUNT(Inversiones!$F$30:$F$149)=0,'Configuración'!$C$8,MIN(Inversiones!$F$30:$F$149))),1),0),'Cálculos'!$C$278:$C$334,'Cálculos'!$I$4),""))) -> 0 | E928: =IF(COUNT(C928,D928)<2,"",D928-C928) -> 0
B929: =IF(EDATE(DATE(YEAR(IF(COUNT(Inversiones!$F$30:$F$149)=0,'Configuración'!$C$8,MIN(Inversiones!$F$30:$F$149))),MONTH(IF(COUNT(Inversiones!$F$30:$F$149)=0,'Configuración'!$C$8,MIN(Inversiones!$F$30:$F$149))),1),1)>EOMONTH('Configuración'!$C$8,0),"",TEXT(EDATE(DATE(YEAR(IF(COUNT(Inversiones!$F$30:$F$149)=0,'Configuración'!$C$8,MIN(Inversiones!$F$30:$F$149))),MONTH(IF(COUNT(Inversiones!$F$30:$F$149)=0,'Configuración'!$C$8,MIN(Inversiones!$F$30:$F$149))),1),1),"mmm yyyy")) | C929: =IF(EDATE(DATE(YEAR(IF(COUNT(Inversiones!$F$30:$F$149)=0,'Configuración'!$C$8,MIN(Inversiones!$F$30:$F$149))),MONTH(IF(COUNT(Inversiones!$F$30:$F$149)=0,'Configuración'!$C$8,MIN(Inversiones!$F$30:$F$149))),1),1)>EOMONTH('Configuración'!$C$8,0),"",IF(Inversiones!$D$4="Todos",IF(SUMIFS('Cálculos'!$E$278:$E$334,'Cálculos'!$B$278:$B$334,EDATE(DATE(YEAR(IF(COUNT(Inversiones!$F$30:$F$149)=0,'Configuración'!$C$8,MIN(Inversiones!$F$30:$F$149))),MONTH(IF(COUNT(Inversiones!$F$30:$F$149)=0,'Configuración'!$C$8,MIN(Inversiones!$F$30:$F$149))),1),1))=COUNTA(Inversiones!$B$30:$B$149),SUMIFS('Cálculos'!$G$278:$G$334,'Cálculos'!$B$278:$B$334,EDATE(DATE(YEAR(IF(COUNT(Inversiones!$F$30:$F$149)=0,'Configuración'!$C$8,MIN(Inversiones!$F$30:$F$149))),MONTH(IF(COUNT(Inversiones!$F$30:$F$149)=0,'Configuración'!$C$8,MIN(Inversiones!$F$30:$F$149))),1),1)),""),IF(SUMIFS('Cálculos'!$E$278:$E$334,'Cálculos'!$B$278:$B$334,EDATE(DATE(YEAR(IF(COUNT(Inversiones!$F$30:$F$149)=0,'Configuración'!$C$8,MIN(Inversiones!$F$30:$F$149))),MONTH(IF(COUNT(Inversiones!$F$30:$F$149)=0,'Configuración'!$C$8,MIN(Inversiones!$F$30:$F$149))),1),1),'Cálculos'!$C$278:$C$334,'Cálculos'!$I$4)=1,SUMIFS('Cálculos'!$G$278:$G$334,'Cálculos'!$B$278:$B$334,EDATE(DATE(YEAR(IF(COUNT(Inversiones!$F$30:$F$149)=0,'Configuración'!$C$8,MIN(Inversiones!$F$30:$F$149))),MONTH(IF(COUNT(Inversiones!$F$30:$F$149)=0,'Configuración'!$C$8,MIN(Inversiones!$F$30:$F$149))),1),1),'Cálculos'!$C$278:$C$334,'Cálculos'!$I$4),""))) | D929: =IF(EDATE(DATE(YEAR(IF(COUNT(Inversiones!$F$30:$F$149)=0,'Configuración'!$C$8,MIN(Inversiones!$F$30:$F$149))),MONTH(IF(COUNT(Inversiones!$F$30:$F$149)=0,'Configuración'!$C$8,MIN(Inversiones!$F$30:$F$149))),1),1)>EOMONTH('Configuración'!$C$8,0),"",IF(Inversiones!$D$4="Todos",IF(SUMIFS('Cálculos'!$K$278:$K$334,'Cálculos'!$B$278:$B$334,EDATE(DATE(YEAR(IF(COUNT(Inversiones!$F$30:$F$149)=0,'Configuración'!$C$8,MIN(Inversiones!$F$30:$F$149))),MONTH(IF(COUNT(Inversiones!$F$30:$F$149)=0,'Configuración'!$C$8,MIN(Inversiones!$F$30:$F$149))),1),1))=COUNTA(Inversiones!$B$30:$B$149),SUMIFS('Cálculos'!$J$278:$J$334,'Cálculos'!$B$278:$B$334,EDATE(DATE(YEAR(IF(COUNT(Inversiones!$F$30:$F$149)=0,'Configuración'!$C$8,MIN(Inversiones!$F$30:$F$149))),MONTH(IF(COUNT(Inversiones!$F$30:$F$149)=0,'Configuración'!$C$8,MIN(Inversiones!$F$30:$F$149))),1),1)),""),IF(SUMIFS('Cálculos'!$K$278:$K$334,'Cálculos'!$B$278:$B$334,EDATE(DATE(YEAR(IF(COUNT(Inversiones!$F$30:$F$149)=0,'Configuración'!$C$8,MIN(Inversiones!$F$30:$F$149))),MONTH(IF(COUNT(Inversiones!$F$30:$F$149)=0,'Configuración'!$C$8,MIN(Inversiones!$F$30:$F$149))),1),1),'Cálculos'!$C$278:$C$334,'Cálculos'!$I$4)=1,SUMIFS('Cálculos'!$J$278:$J$334,'Cálculos'!$B$278:$B$334,EDATE(DATE(YEAR(IF(COUNT(Inversiones!$F$30:$F$149)=0,'Configuración'!$C$8,MIN(Inversiones!$F$30:$F$149))),MONTH(IF(COUNT(Inversiones!$F$30:$F$149)=0,'Configuración'!$C$8,MIN(Inversiones!$F$30:$F$149))),1),1),'Cálculos'!$C$278:$C$334,'Cálculos'!$I$4),""))) | E929: =IF(COUNT(C929,D929)<2,"",D929-C929)
B930: =IF(EDATE(DATE(YEAR(IF(COUNT(Inversiones!$F$30:$F$149)=0,'Configuración'!$C$8,MIN(Inversiones!$F$30:$F$149))),MONTH(IF(COUNT(Inversiones!$F$30:$F$149)=0,'Configuración'!$C$8,MIN(Inversiones!$F$30:$F$149))),1),2)>EOMONTH('Configuración'!$C$8,0),"",TEXT(EDATE(DATE(YEAR(IF(COUNT(Inversiones!$F$30:$F$149)=0,'Configuración'!$C$8,MIN(Inversiones!$F$30:$F$149))),MONTH(IF(COUNT(Inversiones!$F$30:$F$149)=0,'Configuración'!$C$8,MIN(Inversiones!$F$30:$F$149))),1),2),"mmm yyyy")) | C930: =IF(EDATE(DATE(YEAR(IF(COUNT(Inversiones!$F$30:$F$149)=0,'Configuración'!$C$8,MIN(Inversiones!$F$30:$F$149))),MONTH(IF(COUNT(Inversiones!$F$30:$F$149)=0,'Configuración'!$C$8,MIN(Inversiones!$F$30:$F$149))),1),2)>EOMONTH('Configuración'!$C$8,0),"",IF(Inversiones!$D$4="Todos",IF(SUMIFS('Cálculos'!$E$278:$E$334,'Cálculos'!$B$278:$B$334,EDATE(DATE(YEAR(IF(COUNT(Inversiones!$F$30:$F$149)=0,'Configuración'!$C$8,MIN(Inversiones!$F$30:$F$149))),MONTH(IF(COUNT(Inversiones!$F$30:$F$149)=0,'Configuración'!$C$8,MIN(Inversiones!$F$30:$F$149))),1),2))=COUNTA(Inversiones!$B$30:$B$149),SUMIFS('Cálculos'!$G$278:$G$334,'Cálculos'!$B$278:$B$334,EDATE(DATE(YEAR(IF(COUNT(Inversiones!$F$30:$F$149)=0,'Configuración'!$C$8,MIN(Inversiones!$F$30:$F$149))),MONTH(IF(COUNT(Inversiones!$F$30:$F$149)=0,'Configuración'!$C$8,MIN(Inversiones!$F$30:$F$149))),1),2)),""),IF(SUMIFS('Cálculos'!$E$278:$E$334,'Cálculos'!$B$278:$B$334,EDATE(DATE(YEAR(IF(COUNT(Inversiones!$F$30:$F$149)=0,'Configuración'!$C$8,MIN(Inversiones!$F$30:$F$149))),MONTH(IF(COUNT(Inversiones!$F$30:$F$149)=0,'Configuración'!$C$8,MIN(Inversiones!$F$30:$F$149))),1),2),'Cálculos'!$C$278:$C$334,'Cálculos'!$I$4)=1,SUMIFS('Cálculos'!$G$278:$G$334,'Cálculos'!$B$278:$B$334,EDATE(DATE(YEAR(IF(COUNT(Inversiones!$F$30:$F$149)=0,'Configuración'!$C$8,MIN(Inversiones!$F$30:$F$149))),MONTH(IF(COUNT(Inversiones!$F$30:$F$149)=0,'Configuración'!$C$8,MIN(Inversiones!$F$30:$F$149))),1),2),'Cálculos'!$C$278:$C$334,'Cálculos'!$I$4),""))) | D930: =IF(EDATE(DATE(YEAR(IF(COUNT(Inversiones!$F$30:$F$149)=0,'Configuración'!$C$8,MIN(Inversiones!$F$30:$F$149))),MONTH(IF(COUNT(Inversiones!$F$30:$F$149)=0,'Configuración'!$C$8,MIN(Inversiones!$F$30:$F$149))),1),2)>EOMONTH('Configuración'!$C$8,0),"",IF(Inversiones!$D$4="Todos",IF(SUMIFS('Cálculos'!$K$278:$K$334,'Cálculos'!$B$278:$B$334,EDATE(DATE(YEAR(IF(COUNT(Inversiones!$F$30:$F$149)=0,'Configuración'!$C$8,MIN(Inversiones!$F$30:$F$149))),MONTH(IF(COUNT(Inversiones!$F$30:$F$149)=0,'Configuración'!$C$8,MIN(Inversiones!$F$30:$F$149))),1),2))=COUNTA(Inversiones!$B$30:$B$149),SUMIFS('Cálculos'!$J$278:$J$334,'Cálculos'!$B$278:$B$334,EDATE(DATE(YEAR(IF(COUNT(Inversiones!$F$30:$F$149)=0,'Configuración'!$C$8,MIN(Inversiones!$F$30:$F$149))),MONTH(IF(COUNT(Inversiones!$F$30:$F$149)=0,'Configuración'!$C$8,MIN(Inversiones!$F$30:$F$149))),1),2)),""),IF(SUMIFS('Cálculos'!$K$278:$K$334,'Cálculos'!$B$278:$B$334,EDATE(DATE(YEAR(IF(COUNT(Inversiones!$F$30:$F$149)=0,'Configuración'!$C$8,MIN(Inversiones!$F$30:$F$149))),MONTH(IF(COUNT(Inversiones!$F$30:$F$149)=0,'Configuración'!$C$8,MIN(Inversiones!$F$30:$F$149))),1),2),'Cálculos'!$C$278:$C$334,'Cálculos'!$I$4)=1,SUMIFS('Cálculos'!$J$278:$J$334,'Cálculos'!$B$278:$B$334,EDATE(DATE(YEAR(IF(COUNT(Inversiones!$F$30:$F$149)=0,'Configuración'!$C$8,MIN(Inversiones!$F$30:$F$149))),MONTH(IF(COUNT(Inversiones!$F$30:$F$149)=0,'Configuración'!$C$8,MIN(Inversiones!$F$30:$F$149))),1),2),'Cálculos'!$C$278:$C$334,'Cálculos'!$I$4),""))) | E930: =IF(COUNT(C930,D930)<2,"",D930-C930)
B931: =IF(EDATE(DATE(YEAR(IF(COUNT(Inversiones!$F$30:$F$149)=0,'Configuración'!$C$8,MIN(Inversiones!$F$30:$F$149))),MONTH(IF(COUNT(Inversiones!$F$30:$F$149)=0,'Configuración'!$C$8,MIN(Inversiones!$F$30:$F$149))),1),3)>EOMONTH('Configuración'!$C$8,0),"",TEXT(EDATE(DATE(YEAR(IF(COUNT(Inversiones!$F$30:$F$149)=0,'Configuración'!$C$8,MIN(Inversiones!$F$30:$F$149))),MONTH(IF(COUNT(Inversiones!$F$30:$F$149)=0,'Configuración'!$C$8,MIN(Inversiones!$F$30:$F$149))),1),3),"mmm yyyy")) | C931: =IF(EDATE(DATE(YEAR(IF(COUNT(Inversiones!$F$30:$F$149)=0,'Configuración'!$C$8,MIN(Inversiones!$F$30:$F$149))),MONTH(IF(COUNT(Inversiones!$F$30:$F$149)=0,'Configuración'!$C$8,MIN(Inversiones!$F$30:$F$149))),1),3)>EOMONTH('Configuración'!$C$8,0),"",IF(Inversiones!$D$4="Todos",IF(SUMIFS('Cálculos'!$E$278:$E$334,'Cálculos'!$B$278:$B$334,EDATE(DATE(YEAR(IF(COUNT(Inversiones!$F$30:$F$149)=0,'Configuración'!$C$8,MIN(Inversiones!$F$30:$F$149))),MONTH(IF(COUNT(Inversiones!$F$30:$F$149)=0,'Configuración'!$C$8,MIN(Inversiones!$F$30:$F$149))),1),3))=COUNTA(Inversiones!$B$30:$B$149),SUMIFS('Cálculos'!$G$278:$G$334,'Cálculos'!$B$278:$B$334,EDATE(DATE(YEAR(IF(COUNT(Inversiones!$F$30:$F$149)=0,'Configuración'!$C$8,MIN(Inversiones!$F$30:$F$149))),MONTH(IF(COUNT(Inversiones!$F$30:$F$149)=0,'Configuración'!$C$8,MIN(Inversiones!$F$30:$F$149))),1),3)),""),IF(SUMIFS('Cálculos'!$E$278:$E$334,'Cálculos'!$B$278:$B$334,EDATE(DATE(YEAR(IF(COUNT(Inversiones!$F$30:$F$149)=0,'Configuración'!$C$8,MIN(Inversiones!$F$30:$F$149))),MONTH(IF(COUNT(Inversiones!$F$30:$F$149)=0,'Configuración'!$C$8,MIN(Inversiones!$F$30:$F$149))),1),3),'Cálculos'!$C$278:$C$334,'Cálculos'!$I$4)=1,SUMIFS('Cálculos'!$G$278:$G$334,'Cálculos'!$B$278:$B$334,EDATE(DATE(YEAR(IF(COUNT(Inversiones!$F$30:$F$149)=0,'Configuración'!$C$8,MIN(Inversiones!$F$30:$F$149))),MONTH(IF(COUNT(Inversiones!$F$30:$F$149)=0,'Configuración'!$C$8,MIN(Inversiones!$F$30:$F$149))),1),3),'Cálculos'!$C$278:$C$334,'Cálculos'!$I$4),""))) | D931: =IF(EDATE(DATE(YEAR(IF(COUNT(Inversiones!$F$30:$F$149)=0,'Configuración'!$C$8,MIN(Inversiones!$F$30:$F$149))),MONTH(IF(COUNT(Inversiones!$F$30:$F$149)=0,'Configuración'!$C$8,MIN(Inversiones!$F$30:$F$149))),1),3)>EOMONTH('Configuración'!$C$8,0),"",IF(Inversiones!$D$4="Todos",IF(SUMIFS('Cálculos'!$K$278:$K$334,'Cálculos'!$B$278:$B$334,EDATE(DATE(YEAR(IF(COUNT(Inversiones!$F$30:$F$149)=0,'Configuración'!$C$8,MIN(Inversiones!$F$30:$F$149))),MONTH(IF(COUNT(Inversiones!$F$30:$F$149)=0,'Configuración'!$C$8,MIN(Inversiones!$F$30:$F$149))),1),3))=COUNTA(Inversiones!$B$30:$B$149),SUMIFS('Cálculos'!$J$278:$J$334,'Cálculos'!$B$278:$B$334,EDATE(DATE(YEAR(IF(COUNT(Inversiones!$F$30:$F$149)=0,'Configuración'!$C$8,MIN(Inversiones!$F$30:$F$149))),MONTH(IF(COUNT(Inversiones!$F$30:$F$149)=0,'Configuración'!$C$8,MIN(Inversiones!$F$30:$F$149))),1),3)),""),IF(SUMIFS('Cálculos'!$K$278:$K$334,'Cálculos'!$B$278:$B$334,EDATE(DATE(YEAR(IF(COUNT(Inversiones!$F$30:$F$149)=0,'Configuración'!$C$8,MIN(Inversiones!$F$30:$F$149))),MONTH(IF(COUNT(Inversiones!$F$30:$F$149)=0,'Configuración'!$C$8,MIN(Inversiones!$F$30:$F$149))),1),3),'Cálculos'!$C$278:$C$334,'Cálculos'!$I$4)=1,SUMIFS('Cálculos'!$J$278:$J$334,'Cálculos'!$B$278:$B$334,EDATE(DATE(YEAR(IF(COUNT(Inversiones!$F$30:$F$149)=0,'Configuración'!$C$8,MIN(Inversiones!$F$30:$F$149))),MONTH(IF(COUNT(Inversiones!$F$30:$F$149)=0,'Configuración'!$C$8,MIN(Inversiones!$F$30:$F$149))),1),3),'Cálculos'!$C$278:$C$334,'Cálculos'!$I$4),""))) | E931: =IF(COUNT(C931,D931)<2,"",D931-C931)
B932: =IF(EDATE(DATE(YEAR(IF(COUNT(Inversiones!$F$30:$F$149)=0,'Configuración'!$C$8,MIN(Inversiones!$F$30:$F$149))),MONTH(IF(COUNT(Inversiones!$F$30:$F$149)=0,'Configuración'!$C$8,MIN(Inversiones!$F$30:$F$149))),1),4)>EOMONTH('Configuración'!$C$8,0),"",TEXT(EDATE(DATE(YEAR(IF(COUNT(Inversiones!$F$30:$F$149)=0,'Configuración'!$C$8,MIN(Inversiones!$F$30:$F$149))),MONTH(IF(COUNT(Inversiones!$F$30:$F$149)=0,'Configuración'!$C$8,MIN(Inversiones!$F$30:$F$149))),1),4),"mmm yyyy")) | C932: =IF(EDATE(DATE(YEAR(IF(COUNT(Inversiones!$F$30:$F$149)=0,'Configuración'!$C$8,MIN(Inversiones!$F$30:$F$149))),MONTH(IF(COUNT(Inversiones!$F$30:$F$149)=0,'Configuración'!$C$8,MIN(Inversiones!$F$30:$F$149))),1),4)>EOMONTH('Configuración'!$C$8,0),"",IF(Inversiones!$D$4="Todos",IF(SUMIFS('Cálculos'!$E$278:$E$334,'Cálculos'!$B$278:$B$334,EDATE(DATE(YEAR(IF(COUNT(Inversiones!$F$30:$F$149)=0,'Configuración'!$C$8,MIN(Inversiones!$F$30:$F$149))),MONTH(IF(COUNT(Inversiones!$F$30:$F$149)=0,'Configuración'!$C$8,MIN(Inversiones!$F$30:$F$149))),1),4))=COUNTA(Inversiones!$B$30:$B$149),SUMIFS('Cálculos'!$G$278:$G$334,'Cálculos'!$B$278:$B$334,EDATE(DATE(YEAR(IF(COUNT(Inversiones!$F$30:$F$149)=0,'Configuración'!$C$8,MIN(Inversiones!$F$30:$F$149))),MONTH(IF(COUNT(Inversiones!$F$30:$F$149)=0,'Configuración'!$C$8,MIN(Inversiones!$F$30:$F$149))),1),4)),""),IF(SUMIFS('Cálculos'!$E$278:$E$334,'Cálculos'!$B$278:$B$334,EDATE(DATE(YEAR(IF(COUNT(Inversiones!$F$30:$F$149)=0,'Configuración'!$C$8,MIN(Inversiones!$F$30:$F$149))),MONTH(IF(COUNT(Inversiones!$F$30:$F$149)=0,'Configuración'!$C$8,MIN(Inversiones!$F$30:$F$149))),1),4),'Cálculos'!$C$278:$C$334,'Cálculos'!$I$4)=1,SUMIFS('Cálculos'!$G$278:$G$334,'Cálculos'!$B$278:$B$334,EDATE(DATE(YEAR(IF(COUNT(Inversiones!$F$30:$F$149)=0,'Configuración'!$C$8,MIN(Inversiones!$F$30:$F$149))),MONTH(IF(COUNT(Inversiones!$F$30:$F$149)=0,'Configuración'!$C$8,MIN(Inversiones!$F$30:$F$149))),1),4),'Cálculos'!$C$278:$C$334,'Cálculos'!$I$4),""))) | D932: =IF(EDATE(DATE(YEAR(IF(COUNT(Inversiones!$F$30:$F$149)=0,'Configuración'!$C$8,MIN(Inversiones!$F$30:$F$149))),MONTH(IF(COUNT(Inversiones!$F$30:$F$149)=0,'Configuración'!$C$8,MIN(Inversiones!$F$30:$F$149))),1),4)>EOMONTH('Configuración'!$C$8,0),"",IF(Inversiones!$D$4="Todos",IF(SUMIFS('Cálculos'!$K$278:$K$334,'Cálculos'!$B$278:$B$334,EDATE(DATE(YEAR(IF(COUNT(Inversiones!$F$30:$F$149)=0,'Configuración'!$C$8,MIN(Inversiones!$F$30:$F$149))),MONTH(IF(COUNT(Inversiones!$F$30:$F$149)=0,'Configuración'!$C$8,MIN(Inversiones!$F$30:$F$149))),1),4))=COUNTA(Inversiones!$B$30:$B$149),SUMIFS('Cálculos'!$J$278:$J$334,'Cálculos'!$B$278:$B$334,EDATE(DATE(YEAR(IF(COUNT(Inversiones!$F$30:$F$149)=0,'Configuración'!$C$8,MIN(Inversiones!$F$30:$F$149))),MONTH(IF(COUNT(Inversiones!$F$30:$F$149)=0,'Configuración'!$C$8,MIN(Inversiones!$F$30:$F$149))),1),4)),""),IF(SUMIFS('Cálculos'!$K$278:$K$334,'Cálculos'!$B$278:$B$334,EDATE(DATE(YEAR(IF(COUNT(Inversiones!$F$30:$F$149)=0,'Configuración'!$C$8,MIN(Inversiones!$F$30:$F$149))),MONTH(IF(COUNT(Inversiones!$F$30:$F$149)=0,'Configuración'!$C$8,MIN(Inversiones!$F$30:$F$149))),1),4),'Cálculos'!$C$278:$C$334,'Cálculos'!$I$4)=1,SUMIFS('Cálculos'!$J$278:$J$334,'Cálculos'!$B$278:$B$334,EDATE(DATE(YEAR(IF(COUNT(Inversiones!$F$30:$F$149)=0,'Configuración'!$C$8,MIN(Inversiones!$F$30:$F$149))),MONTH(IF(COUNT(Inversiones!$F$30:$F$149)=0,'Configuración'!$C$8,MIN(Inversiones!$F$30:$F$149))),1),4),'Cálculos'!$C$278:$C$334,'Cálculos'!$I$4),""))) | E932: =IF(COUNT(C932,D932)<2,"",D932-C932)
B933: =IF(EDATE(DATE(YEAR(IF(COUNT(Inversiones!$F$30:$F$149)=0,'Configuración'!$C$8,MIN(Inversiones!$F$30:$F$149))),MONTH(IF(COUNT(Inversiones!$F$30:$F$149)=0,'Configuración'!$C$8,MIN(Inversiones!$F$30:$F$149))),1),5)>EOMONTH('Configuración'!$C$8,0),"",TEXT(EDATE(DATE(YEAR(IF(COUNT(Inversiones!$F$30:$F$149)=0,'Configuración'!$C$8,MIN(Inversiones!$F$30:$F$149))),MONTH(IF(COUNT(Inversiones!$F$30:$F$149)=0,'Configuración'!$C$8,MIN(Inversiones!$F$30:$F$149))),1),5),"mmm yyyy")) | C933: =IF(EDATE(DATE(YEAR(IF(COUNT(Inversiones!$F$30:$F$149)=0,'Configuración'!$C$8,MIN(Inversiones!$F$30:$F$149))),MONTH(IF(COUNT(Inversiones!$F$30:$F$149)=0,'Configuración'!$C$8,MIN(Inversiones!$F$30:$F$149))),1),5)>EOMONTH('Configuración'!$C$8,0),"",IF(Inversiones!$D$4="Todos",IF(SUMIFS('Cálculos'!$E$278:$E$334,'Cálculos'!$B$278:$B$334,EDATE(DATE(YEAR(IF(COUNT(Inversiones!$F$30:$F$149)=0,'Configuración'!$C$8,MIN(Inversiones!$F$30:$F$149))),MONTH(IF(COUNT(Inversiones!$F$30:$F$149)=0,'Configuración'!$C$8,MIN(Inversiones!$F$30:$F$149))),1),5))=COUNTA(Inversiones!$B$30:$B$149),SUMIFS('Cálculos'!$G$278:$G$334,'Cálculos'!$B$278:$B$334,EDATE(DATE(YEAR(IF(COUNT(Inversiones!$F$30:$F$149)=0,'Configuración'!$C$8,MIN(Inversiones!$F$30:$F$149))),MONTH(IF(COUNT(Inversiones!$F$30:$F$149)=0,'Configuración'!$C$8,MIN(Inversiones!$F$30:$F$149))),1),5)),""),IF(SUMIFS('Cálculos'!$E$278:$E$334,'Cálculos'!$B$278:$B$334,EDATE(DATE(YEAR(IF(COUNT(Inversiones!$F$30:$F$149)=0,'Configuración'!$C$8,MIN(Inversiones!$F$30:$F$149))),MONTH(IF(COUNT(Inversiones!$F$30:$F$149)=0,'Configuración'!$C$8,MIN(Inversiones!$F$30:$F$149))),1),5),'Cálculos'!$C$278:$C$334,'Cálculos'!$I$4)=1,SUMIFS('Cálculos'!$G$278:$G$334,'Cálculos'!$B$278:$B$334,EDATE(DATE(YEAR(IF(COUNT(Inversiones!$F$30:$F$149)=0,'Configuración'!$C$8,MIN(Inversiones!$F$30:$F$149))),MONTH(IF(COUNT(Inversiones!$F$30:$F$149)=0,'Configuración'!$C$8,MIN(Inversiones!$F$30:$F$149))),1),5),'Cálculos'!$C$278:$C$334,'Cálculos'!$I$4),""))) | D933: =IF(EDATE(DATE(YEAR(IF(COUNT(Inversiones!$F$30:$F$149)=0,'Configuración'!$C$8,MIN(Inversiones!$F$30:$F$149))),MONTH(IF(COUNT(Inversiones!$F$30:$F$149)=0,'Configuración'!$C$8,MIN(Inversiones!$F$30:$F$149))),1),5)>EOMONTH('Configuración'!$C$8,0),"",IF(Inversiones!$D$4="Todos",IF(SUMIFS('Cálculos'!$K$278:$K$334,'Cálculos'!$B$278:$B$334,EDATE(DATE(YEAR(IF(COUNT(Inversiones!$F$30:$F$149)=0,'Configuración'!$C$8,MIN(Inversiones!$F$30:$F$149))),MONTH(IF(COUNT(Inversiones!$F$30:$F$149)=0,'Configuración'!$C$8,MIN(Inversiones!$F$30:$F$149))),1),5))=COUNTA(Inversiones!$B$30:$B$149),SUMIFS('Cálculos'!$J$278:$J$334,'Cálculos'!$B$278:$B$334,EDATE(DATE(YEAR(IF(COUNT(Inversiones!$F$30:$F$149)=0,'Configuración'!$C$8,MIN(Inversiones!$F$30:$F$149))),MONTH(IF(COUNT(Inversiones!$F$30:$F$149)=0,'Configuración'!$C$8,MIN(Inversiones!$F$30:$F$149))),1),5)),""),IF(SUMIFS('Cálculos'!$K$278:$K$334,'Cálculos'!$B$278:$B$334,EDATE(DATE(YEAR(IF(COUNT(Inversiones!$F$30:$F$149)=0,'Configuración'!$C$8,MIN(Inversiones!$F$30:$F$149))),MONTH(IF(COUNT(Inversiones!$F$30:$F$149)=0,'Configuración'!$C$8,MIN(Inversiones!$F$30:$F$149))),1),5),'Cálculos'!$C$278:$C$334,'Cálculos'!$I$4)=1,SUMIFS('Cálculos'!$J$278:$J$334,'Cálculos'!$B$278:$B$334,EDATE(DATE(YEAR(IF(COUNT(Inversiones!$F$30:$F$149)=0,'Configuración'!$C$8,MIN(Inversiones!$F$30:$F$149))),MONTH(IF(COUNT(Inversiones!$F$30:$F$149)=0,'Configuración'!$C$8,MIN(Inversiones!$F$30:$F$149))),1),5),'Cálculos'!$C$278:$C$334,'Cálculos'!$I$4),""))) | E933: =IF(COUNT(C933,D933)<2,"",D933-C933)
B934: =IF(EDATE(DATE(YEAR(IF(COUNT(Inversiones!$F$30:$F$149)=0,'Configuración'!$C$8,MIN(Inversiones!$F$30:$F$149))),MONTH(IF(COUNT(Inversiones!$F$30:$F$149)=0,'Configuración'!$C$8,MIN(Inversiones!$F$30:$F$149))),1),6)>EOMONTH('Configuración'!$C$8,0),"",TEXT(EDATE(DATE(YEAR(IF(COUNT(Inversiones!$F$30:$F$149)=0,'Configuración'!$C$8,MIN(Inversiones!$F$30:$F$149))),MONTH(IF(COUNT(Inversiones!$F$30:$F$149)=0,'Configuración'!$C$8,MIN(Inversiones!$F$30:$F$149))),1),6),"mmm yyyy")) | C934: =IF(EDATE(DATE(YEAR(IF(COUNT(Inversiones!$F$30:$F$149)=0,'Configuración'!$C$8,MIN(Inversiones!$F$30:$F$149))),MONTH(IF(COUNT(Inversiones!$F$30:$F$149)=0,'Configuración'!$C$8,MIN(Inversiones!$F$30:$F$149))),1),6)>EOMONTH('Configuración'!$C$8,0),"",IF(Inversiones!$D$4="Todos",IF(SUMIFS('Cálculos'!$E$278:$E$334,'Cálculos'!$B$278:$B$334,EDATE(DATE(YEAR(IF(COUNT(Inversiones!$F$30:$F$149)=0,'Configuración'!$C$8,MIN(Inversiones!$F$30:$F$149))),MONTH(IF(COUNT(Inversiones!$F$30:$F$149)=0,'Configuración'!$C$8,MIN(Inversiones!$F$30:$F$149))),1),6))=COUNTA(Inversiones!$B$30:$B$149),SUMIFS('Cálculos'!$G$278:$G$334,'Cálculos'!$B$278:$B$334,EDATE(DATE(YEAR(IF(COUNT(Inversiones!$F$30:$F$149)=0,'Configuración'!$C$8,MIN(Inversiones!$F$30:$F$149))),MONTH(IF(COUNT(Inversiones!$F$30:$F$149)=0,'Configuración'!$C$8,MIN(Inversiones!$F$30:$F$149))),1),6)),""),IF(SUMIFS('Cálculos'!$E$278:$E$334,'Cálculos'!$B$278:$B$334,EDATE(DATE(YEAR(IF(COUNT(Inversiones!$F$30:$F$149)=0,'Configuración'!$C$8,MIN(Inversiones!$F$30:$F$149))),MONTH(IF(COUNT(Inversiones!$F$30:$F$149)=0,'Configuración'!$C$8,MIN(Inversiones!$F$30:$F$149))),1),6),'Cálculos'!$C$278:$C$334,'Cálculos'!$I$4)=1,SUMIFS('Cálculos'!$G$278:$G$334,'Cálculos'!$B$278:$B$334,EDATE(DATE(YEAR(IF(COUNT(Inversiones!$F$30:$F$149)=0,'Configuración'!$C$8,MIN(Inversiones!$F$30:$F$149))),MONTH(IF(COUNT(Inversiones!$F$30:$F$149)=0,'Configuración'!$C$8,MIN(Inversiones!$F$30:$F$149))),1),6),'Cálculos'!$C$278:$C$334,'Cálculos'!$I$4),""))) | D934: =IF(EDATE(DATE(YEAR(IF(COUNT(Inversiones!$F$30:$F$149)=0,'Configuración'!$C$8,MIN(Inversiones!$F$30:$F$149))),MONTH(IF(COUNT(Inversiones!$F$30:$F$149)=0,'Configuración'!$C$8,MIN(Inversiones!$F$30:$F$149))),1),6)>EOMONTH('Configuración'!$C$8,0),"",IF(Inversiones!$D$4="Todos",IF(SUMIFS('Cálculos'!$K$278:$K$334,'Cálculos'!$B$278:$B$334,EDATE(DATE(YEAR(IF(COUNT(Inversiones!$F$30:$F$149)=0,'Configuración'!$C$8,MIN(Inversiones!$F$30:$F$149))),MONTH(IF(COUNT(Inversiones!$F$30:$F$149)=0,'Configuración'!$C$8,MIN(Inversiones!$F$30:$F$149))),1),6))=COUNTA(Inversiones!$B$30:$B$149),SUMIFS('Cálculos'!$J$278:$J$334,'Cálculos'!$B$278:$B$334,EDATE(DATE(YEAR(IF(COUNT(Inversiones!$F$30:$F$149)=0,'Configuración'!$C$8,MIN(Inversiones!$F$30:$F$149))),MONTH(IF(COUNT(Inversiones!$F$30:$F$149)=0,'Configuración'!$C$8,MIN(Inversiones!$F$30:$F$149))),1),6)),""),IF(SUMIFS('Cálculos'!$K$278:$K$334,'Cálculos'!$B$278:$B$334,EDATE(DATE(YEAR(IF(COUNT(Inversiones!$F$30:$F$149)=0,'Configuración'!$C$8,MIN(Inversiones!$F$30:$F$149))),MONTH(IF(COUNT(Inversiones!$F$30:$F$149)=0,'Configuración'!$C$8,MIN(Inversiones!$F$30:$F$149))),1),6),'Cálculos'!$C$278:$C$334,'Cálculos'!$I$4)=1,SUMIFS('Cálculos'!$J$278:$J$334,'Cálculos'!$B$278:$B$334,EDATE(DATE(YEAR(IF(COUNT(Inversiones!$F$30:$F$149)=0,'Configuración'!$C$8,MIN(Inversiones!$F$30:$F$149))),MONTH(IF(COUNT(Inversiones!$F$30:$F$149)=0,'Configuración'!$C$8,MIN(Inversiones!$F$30:$F$149))),1),6),'Cálculos'!$C$278:$C$334,'Cálculos'!$I$4),""))) | E934: =IF(COUNT(C934,D934)<2,"",D934-C934)
B935: =IF(EDATE(DATE(YEAR(IF(COUNT(Inversiones!$F$30:$F$149)=0,'Configuración'!$C$8,MIN(Inversiones!$F$30:$F$149))),MONTH(IF(COUNT(Inversiones!$F$30:$F$149)=0,'Configuración'!$C$8,MIN(Inversiones!$F$30:$F$149))),1),7)>EOMONTH('Configuración'!$C$8,0),"",TEXT(EDATE(DATE(YEAR(IF(COUNT(Inversiones!$F$30:$F$149)=0,'Configuración'!$C$8,MIN(Inversiones!$F$30:$F$149))),MONTH(IF(COUNT(Inversiones!$F$30:$F$149)=0,'Configuración'!$C$8,MIN(Inversiones!$F$30:$F$149))),1),7),"mmm yyyy")) | C935: =IF(EDATE(DATE(YEAR(IF(COUNT(Inversiones!$F$30:$F$149)=0,'Configuración'!$C$8,MIN(Inversiones!$F$30:$F$149))),MONTH(IF(COUNT(Inversiones!$F$30:$F$149)=0,'Configuración'!$C$8,MIN(Inversiones!$F$30:$F$149))),1),7)>EOMONTH('Configuración'!$C$8,0),"",IF(Inversiones!$D$4="Todos",IF(SUMIFS('Cálculos'!$E$278:$E$334,'Cálculos'!$B$278:$B$334,EDATE(DATE(YEAR(IF(COUNT(Inversiones!$F$30:$F$149)=0,'Configuración'!$C$8,MIN(Inversiones!$F$30:$F$149))),MONTH(IF(COUNT(Inversiones!$F$30:$F$149)=0,'Configuración'!$C$8,MIN(Inversiones!$F$30:$F$149))),1),7))=COUNTA(Inversiones!$B$30:$B$149),SUMIFS('Cálculos'!$G$278:$G$334,'Cálculos'!$B$278:$B$334,EDATE(DATE(YEAR(IF(COUNT(Inversiones!$F$30:$F$149)=0,'Configuración'!$C$8,MIN(Inversiones!$F$30:$F$149))),MONTH(IF(COUNT(Inversiones!$F$30:$F$149)=0,'Configuración'!$C$8,MIN(Inversiones!$F$30:$F$149))),1),7)),""),IF(SUMIFS('Cálculos'!$E$278:$E$334,'Cálculos'!$B$278:$B$334,EDATE(DATE(YEAR(IF(COUNT(Inversiones!$F$30:$F$149)=0,'Configuración'!$C$8,MIN(Inversiones!$F$30:$F$149))),MONTH(IF(COUNT(Inversiones!$F$30:$F$149)=0,'Configuración'!$C$8,MIN(Inversiones!$F$30:$F$149))),1),7),'Cálculos'!$C$278:$C$334,'Cálculos'!$I$4)=1,SUMIFS('Cálculos'!$G$278:$G$334,'Cálculos'!$B$278:$B$334,EDATE(DATE(YEAR(IF(COUNT(Inversiones!$F$30:$F$149)=0,'Configuración'!$C$8,MIN(Inversiones!$F$30:$F$149))),MONTH(IF(COUNT(Inversiones!$F$30:$F$149)=0,'Configuración'!$C$8,MIN(Inversiones!$F$30:$F$149))),1),7),'Cálculos'!$C$278:$C$334,'Cálculos'!$I$4),""))) | D935: =IF(EDATE(DATE(YEAR(IF(COUNT(Inversiones!$F$30:$F$149)=0,'Configuración'!$C$8,MIN(Inversiones!$F$30:$F$149))),MONTH(IF(COUNT(Inversiones!$F$30:$F$149)=0,'Configuración'!$C$8,MIN(Inversiones!$F$30:$F$149))),1),7)>EOMONTH('Configuración'!$C$8,0),"",IF(Inversiones!$D$4="Todos",IF(SUMIFS('Cálculos'!$K$278:$K$334,'Cálculos'!$B$278:$B$334,EDATE(DATE(YEAR(IF(COUNT(Inversiones!$F$30:$F$149)=0,'Configuración'!$C$8,MIN(Inversiones!$F$30:$F$149))),MONTH(IF(COUNT(Inversiones!$F$30:$F$149)=0,'Configuración'!$C$8,MIN(Inversiones!$F$30:$F$149))),1),7))=COUNTA(Inversiones!$B$30:$B$149),SUMIFS('Cálculos'!$J$278:$J$334,'Cálculos'!$B$278:$B$334,EDATE(DATE(YEAR(IF(COUNT(Inversiones!$F$30:$F$149)=0,'Configuración'!$C$8,MIN(Inversiones!$F$30:$F$149))),MONTH(IF(COUNT(Inversiones!$F$30:$F$149)=0,'Configuración'!$C$8,MIN(Inversiones!$F$30:$F$149))),1),7)),""),IF(SUMIFS('Cálculos'!$K$278:$K$334,'Cálculos'!$B$278:$B$334,EDATE(DATE(YEAR(IF(COUNT(Inversiones!$F$30:$F$149)=0,'Configuración'!$C$8,MIN(Inversiones!$F$30:$F$149))),MONTH(IF(COUNT(Inversiones!$F$30:$F$149)=0,'Configuración'!$C$8,MIN(Inversiones!$F$30:$F$149))),1),7),'Cálculos'!$C$278:$C$334,'Cálculos'!$I$4)=1,SUMIFS('Cálculos'!$J$278:$J$334,'Cálculos'!$B$278:$B$334,EDATE(DATE(YEAR(IF(COUNT(Inversiones!$F$30:$F$149)=0,'Configuración'!$C$8,MIN(Inversiones!$F$30:$F$149))),MONTH(IF(COUNT(Inversiones!$F$30:$F$149)=0,'Configuración'!$C$8,MIN(Inversiones!$F$30:$F$149))),1),7),'Cálculos'!$C$278:$C$334,'Cálculos'!$I$4),""))) | E935: =IF(COUNT(C935,D935)<2,"",D935-C935)
B936: =IF(EDATE(DATE(YEAR(IF(COUNT(Inversiones!$F$30:$F$149)=0,'Configuración'!$C$8,MIN(Inversiones!$F$30:$F$149))),MONTH(IF(COUNT(Inversiones!$F$30:$F$149)=0,'Configuración'!$C$8,MIN(Inversiones!$F$30:$F$149))),1),8)>EOMONTH('Configuración'!$C$8,0),"",TEXT(EDATE(DATE(YEAR(IF(COUNT(Inversiones!$F$30:$F$149)=0,'Configuración'!$C$8,MIN(Inversiones!$F$30:$F$149))),MONTH(IF(COUNT(Inversiones!$F$30:$F$149)=0,'Configuración'!$C$8,MIN(Inversiones!$F$30:$F$149))),1),8),"mmm yyyy")) | C936: =IF(EDATE(DATE(YEAR(IF(COUNT(Inversiones!$F$30:$F$149)=0,'Configuración'!$C$8,MIN(Inversiones!$F$30:$F$149))),MONTH(IF(COUNT(Inversiones!$F$30:$F$149)=0,'Configuración'!$C$8,MIN(Inversiones!$F$30:$F$149))),1),8)>EOMONTH('Configuración'!$C$8,0),"",IF(Inversiones!$D$4="Todos",IF(SUMIFS('Cálculos'!$E$278:$E$334,'Cálculos'!$B$278:$B$334,EDATE(DATE(YEAR(IF(COUNT(Inversiones!$F$30:$F$149)=0,'Configuración'!$C$8,MIN(Inversiones!$F$30:$F$149))),MONTH(IF(COUNT(Inversiones!$F$30:$F$149)=0,'Configuración'!$C$8,MIN(Inversiones!$F$30:$F$149))),1),8))=COUNTA(Inversiones!$B$30:$B$149),SUMIFS('Cálculos'!$G$278:$G$334,'Cálculos'!$B$278:$B$334,EDATE(DATE(YEAR(IF(COUNT(Inversiones!$F$30:$F$149)=0,'Configuración'!$C$8,MIN(Inversiones!$F$30:$F$149))),MONTH(IF(COUNT(Inversiones!$F$30:$F$149)=0,'Configuración'!$C$8,MIN(Inversiones!$F$30:$F$149))),1),8)),""),IF(SUMIFS('Cálculos'!$E$278:$E$334,'Cálculos'!$B$278:$B$334,EDATE(DATE(YEAR(IF(COUNT(Inversiones!$F$30:$F$149)=0,'Configuración'!$C$8,MIN(Inversiones!$F$30:$F$149))),MONTH(IF(COUNT(Inversiones!$F$30:$F$149)=0,'Configuración'!$C$8,MIN(Inversiones!$F$30:$F$149))),1),8),'Cálculos'!$C$278:$C$334,'Cálculos'!$I$4)=1,SUMIFS('Cálculos'!$G$278:$G$334,'Cálculos'!$B$278:$B$334,EDATE(DATE(YEAR(IF(COUNT(Inversiones!$F$30:$F$149)=0,'Configuración'!$C$8,MIN(Inversiones!$F$30:$F$149))),MONTH(IF(COUNT(Inversiones!$F$30:$F$149)=0,'Configuración'!$C$8,MIN(Inversiones!$F$30:$F$149))),1),8),'Cálculos'!$C$278:$C$334,'Cálculos'!$I$4),""))) | D936: =IF(EDATE(DATE(YEAR(IF(COUNT(Inversiones!$F$30:$F$149)=0,'Configuración'!$C$8,MIN(Inversiones!$F$30:$F$149))),MONTH(IF(COUNT(Inversiones!$F$30:$F$149)=0,'Configuración'!$C$8,MIN(Inversiones!$F$30:$F$149))),1),8)>EOMONTH('Configuración'!$C$8,0),"",IF(Inversiones!$D$4="Todos",IF(SUMIFS('Cálculos'!$K$278:$K$334,'Cálculos'!$B$278:$B$334,EDATE(DATE(YEAR(IF(COUNT(Inversiones!$F$30:$F$149)=0,'Configuración'!$C$8,MIN(Inversiones!$F$30:$F$149))),MONTH(IF(COUNT(Inversiones!$F$30:$F$149)=0,'Configuración'!$C$8,MIN(Inversiones!$F$30:$F$149))),1),8))=COUNTA(Inversiones!$B$30:$B$149),SUMIFS('Cálculos'!$J$278:$J$334,'Cálculos'!$B$278:$B$334,EDATE(DATE(YEAR(IF(COUNT(Inversiones!$F$30:$F$149)=0,'Configuración'!$C$8,MIN(Inversiones!$F$30:$F$149))),MONTH(IF(COUNT(Inversiones!$F$30:$F$149)=0,'Configuración'!$C$8,MIN(Inversiones!$F$30:$F$149))),1),8)),""),IF(SUMIFS('Cálculos'!$K$278:$K$334,'Cálculos'!$B$278:$B$334,EDATE(DATE(YEAR(IF(COUNT(Inversiones!$F$30:$F$149)=0,'Configuración'!$C$8,MIN(Inversiones!$F$30:$F$149))),MONTH(IF(COUNT(Inversiones!$F$30:$F$149)=0,'Configuración'!$C$8,MIN(Inversiones!$F$30:$F$149))),1),8),'Cálculos'!$C$278:$C$334,'Cálculos'!$I$4)=1,SUMIFS('Cálculos'!$J$278:$J$334,'Cálculos'!$B$278:$B$334,EDATE(DATE(YEAR(IF(COUNT(Inversiones!$F$30:$F$149)=0,'Configuración'!$C$8,MIN(Inversiones!$F$30:$F$149))),MONTH(IF(COUNT(Inversiones!$F$30:$F$149)=0,'Configuración'!$C$8,MIN(Inversiones!$F$30:$F$149))),1),8),'Cálculos'!$C$278:$C$334,'Cálculos'!$I$4),""))) | E936: =IF(COUNT(C936,D936)<2,"",D936-C936)
B937: =IF(EDATE(DATE(YEAR(IF(COUNT(Inversiones!$F$30:$F$149)=0,'Configuración'!$C$8,MIN(Inversiones!$F$30:$F$149))),MONTH(IF(COUNT(Inversiones!$F$30:$F$149)=0,'Configuración'!$C$8,MIN(Inversiones!$F$30:$F$149))),1),9)>EOMONTH('Configuración'!$C$8,0),"",TEXT(EDATE(DATE(YEAR(IF(COUNT(Inversiones!$F$30:$F$149)=0,'Configuración'!$C$8,MIN(Inversiones!$F$30:$F$149))),MONTH(IF(COUNT(Inversiones!$F$30:$F$149)=0,'Configuración'!$C$8,MIN(Inversiones!$F$30:$F$149))),1),9),"mmm yyyy")) | C937: =IF(EDATE(DATE(YEAR(IF(COUNT(Inversiones!$F$30:$F$149)=0,'Configuración'!$C$8,MIN(Inversiones!$F$30:$F$149))),MONTH(IF(COUNT(Inversiones!$F$30:$F$149)=0,'Configuración'!$C$8,MIN(Inversiones!$F$30:$F$149))),1),9)>EOMONTH('Configuración'!$C$8,0),"",IF(Inversiones!$D$4="Todos",IF(SUMIFS('Cálculos'!$E$278:$E$334,'Cálculos'!$B$278:$B$334,EDATE(DATE(YEAR(IF(COUNT(Inversiones!$F$30:$F$149)=0,'Configuración'!$C$8,MIN(Inversiones!$F$30:$F$149))),MONTH(IF(COUNT(Inversiones!$F$30:$F$149)=0,'Configuración'!$C$8,MIN(Inversiones!$F$30:$F$149))),1),9))=COUNTA(Inversiones!$B$30:$B$149),SUMIFS('Cálculos'!$G$278:$G$334,'Cálculos'!$B$278:$B$334,EDATE(DATE(YEAR(IF(COUNT(Inversiones!$F$30:$F$149)=0,'Configuración'!$C$8,MIN(Inversiones!$F$30:$F$149))),MONTH(IF(COUNT(Inversiones!$F$30:$F$149)=0,'Configuración'!$C$8,MIN(Inversiones!$F$30:$F$149))),1),9)),""),IF(SUMIFS('Cálculos'!$E$278:$E$334,'Cálculos'!$B$278:$B$334,EDATE(DATE(YEAR(IF(COUNT(Inversiones!$F$30:$F$149)=0,'Configuración'!$C$8,MIN(Inversiones!$F$30:$F$149))),MONTH(IF(COUNT(Inversiones!$F$30:$F$149)=0,'Configuración'!$C$8,MIN(Inversiones!$F$30:$F$149))),1),9),'Cálculos'!$C$278:$C$334,'Cálculos'!$I$4)=1,SUMIFS('Cálculos'!$G$278:$G$334,'Cálculos'!$B$278:$B$334,EDATE(DATE(YEAR(IF(COUNT(Inversiones!$F$30:$F$149)=0,'Configuración'!$C$8,MIN(Inversiones!$F$30:$F$149))),MONTH(IF(COUNT(Inversiones!$F$30:$F$149)=0,'Configuración'!$C$8,MIN(Inversiones!$F$30:$F$149))),1),9),'Cálculos'!$C$278:$C$334,'Cálculos'!$I$4),""))) | D937: =IF(EDATE(DATE(YEAR(IF(COUNT(Inversiones!$F$30:$F$149)=0,'Configuración'!$C$8,MIN(Inversiones!$F$30:$F$149))),MONTH(IF(COUNT(Inversiones!$F$30:$F$149)=0,'Configuración'!$C$8,MIN(Inversiones!$F$30:$F$149))),1),9)>EOMONTH('Configuración'!$C$8,0),"",IF(Inversiones!$D$4="Todos",IF(SUMIFS('Cálculos'!$K$278:$K$334,'Cálculos'!$B$278:$B$334,EDATE(DATE(YEAR(IF(COUNT(Inversiones!$F$30:$F$149)=0,'Configuración'!$C$8,MIN(Inversiones!$F$30:$F$149))),MONTH(IF(COUNT(Inversiones!$F$30:$F$149)=0,'Configuración'!$C$8,MIN(Inversiones!$F$30:$F$149))),1),9))=COUNTA(Inversiones!$B$30:$B$149),SUMIFS('Cálculos'!$J$278:$J$334,'Cálculos'!$B$278:$B$334,EDATE(DATE(YEAR(IF(COUNT(Inversiones!$F$30:$F$149)=0,'Configuración'!$C$8,MIN(Inversiones!$F$30:$F$149))),MONTH(IF(COUNT(Inversiones!$F$30:$F$149)=0,'Configuración'!$C$8,MIN(Inversiones!$F$30:$F$149))),1),9)),""),IF(SUMIFS('Cálculos'!$K$278:$K$334,'Cálculos'!$B$278:$B$334,EDATE(DATE(YEAR(IF(COUNT(Inversiones!$F$30:$F$149)=0,'Configuración'!$C$8,MIN(Inversiones!$F$30:$F$149))),MONTH(IF(COUNT(Inversiones!$F$30:$F$149)=0,'Configuración'!$C$8,MIN(Inversiones!$F$30:$F$149))),1),9),'Cálculos'!$C$278:$C$334,'Cálculos'!$I$4)=1,SUMIFS('Cálculos'!$J$278:$J$334,'Cálculos'!$B$278:$B$334,EDATE(DATE(YEAR(IF(COUNT(Inversiones!$F$30:$F$149)=0,'Configuración'!$C$8,MIN(Inversiones!$F$30:$F$149))),MONTH(IF(COUNT(Inversiones!$F$30:$F$149)=0,'Configuración'!$C$8,MIN(Inversiones!$F$30:$F$149))),1),9),'Cálculos'!$C$278:$C$334,'Cálculos'!$I$4),""))) | E937: =IF(COUNT(C937,D937)<2,"",D937-C937)
B938: =IF(EDATE(DATE(YEAR(IF(COUNT(Inversiones!$F$30:$F$149)=0,'Configuración'!$C$8,MIN(Inversiones!$F$30:$F$149))),MONTH(IF(COUNT(Inversiones!$F$30:$F$149)=0,'Configuración'!$C$8,MIN(Inversiones!$F$30:$F$149))),1),10)>EOMONTH('Configuración'!$C$8,0),"",TEXT(EDATE(DATE(YEAR(IF(COUNT(Inversiones!$F$30:$F$149)=0,'Configuración'!$C$8,MIN(Inversiones!$F$30:$F$149))),MONTH(IF(COUNT(Inversiones!$F$30:$F$149)=0,'Configuración'!$C$8,MIN(Inversiones!$F$30:$F$149))),1),10),"mmm yyyy")) | C938: =IF(EDATE(DATE(YEAR(IF(COUNT(Inversiones!$F$30:$F$149)=0,'Configuración'!$C$8,MIN(Inversiones!$F$30:$F$149))),MONTH(IF(COUNT(Inversiones!$F$30:$F$149)=0,'Configuración'!$C$8,MIN(Inversiones!$F$30:$F$149))),1),10)>EOMONTH('Configuración'!$C$8,0),"",IF(Inversiones!$D$4="Todos",IF(SUMIFS('Cálculos'!$E$278:$E$334,'Cálculos'!$B$278:$B$334,EDATE(DATE(YEAR(IF(COUNT(Inversiones!$F$30:$F$149)=0,'Configuración'!$C$8,MIN(Inversiones!$F$30:$F$149))),MONTH(IF(COUNT(Inversiones!$F$30:$F$149)=0,'Configuración'!$C$8,MIN(Inversiones!$F$30:$F$149))),1),10))=COUNTA(Inversiones!$B$30:$B$149),SUMIFS('Cálculos'!$G$278:$G$334,'Cálculos'!$B$278:$B$334,EDATE(DATE(YEAR(IF(COUNT(Inversiones!$F$30:$F$149)=0,'Configuración'!$C$8,MIN(Inversiones!$F$30:$F$149))),MONTH(IF(COUNT(Inversiones!$F$30:$F$149)=0,'Configuración'!$C$8,MIN(Inversiones!$F$30:$F$149))),1),10)),""),IF(SUMIFS('Cálculos'!$E$278:$E$334,'Cálculos'!$B$278:$B$334,EDATE(DATE(YEAR(IF(COUNT(Inversiones!$F$30:$F$149)=0,'Configuración'!$C$8,MIN(Inversiones!$F$30:$F$149))),MONTH(IF(COUNT(Inversiones!$F$30:$F$149)=0,'Configuración'!$C$8,MIN(Inversiones!$F$30:$F$149))),1),10),'Cálculos'!$C$278:$C$334,'Cálculos'!$I$4)=1,SUMIFS('Cálculos'!$G$278:$G$334,'Cálculos'!$B$278:$B$334,EDATE(DATE(YEAR(IF(COUNT(Inversiones!$F$30:$F$149)=0,'Configuración'!$C$8,MIN(Inversiones!$F$30:$F$149))),MONTH(IF(COUNT(Inversiones!$F$30:$F$149)=0,'Configuración'!$C$8,MIN(Inversiones!$F$30:$F$149))),1),10),'Cálculos'!$C$278:$C$334,'Cálculos'!$I$4),""))) | D938: =IF(EDATE(DATE(YEAR(IF(COUNT(Inversiones!$F$30:$F$149)=0,'Configuración'!$C$8,MIN(Inversiones!$F$30:$F$149))),MONTH(IF(COUNT(Inversiones!$F$30:$F$149)=0,'Configuración'!$C$8,MIN(Inversiones!$F$30:$F$149))),1),10)>EOMONTH('Configuración'!$C$8,0),"",IF(Inversiones!$D$4="Todos",IF(SUMIFS('Cálculos'!$K$278:$K$334,'Cálculos'!$B$278:$B$334,EDATE(DATE(YEAR(IF(COUNT(Inversiones!$F$30:$F$149)=0,'Configuración'!$C$8,MIN(Inversiones!$F$30:$F$149))),MONTH(IF(COUNT(Inversiones!$F$30:$F$149)=0,'Configuración'!$C$8,MIN(Inversiones!$F$30:$F$149))),1),10))=COUNTA(Inversiones!$B$30:$B$149),SUMIFS('Cálculos'!$J$278:$J$334,'Cálculos'!$B$278:$B$334,EDATE(DATE(YEAR(IF(COUNT(Inversiones!$F$30:$F$149)=0,'Configuración'!$C$8,MIN(Inversiones!$F$30:$F$149))),MONTH(IF(COUNT(Inversiones!$F$30:$F$149)=0,'Configuración'!$C$8,MIN(Inversiones!$F$30:$F$149))),1),10)),""),IF(SUMIFS('Cálculos'!$K$278:$K$334,'Cálculos'!$B$278:$B$334,EDATE(DATE(YEAR(IF(COUNT(Inversiones!$F$30:$F$149)=0,'Configuración'!$C$8,MIN(Inversiones!$F$30:$F$149))),MONTH(IF(COUNT(Inversiones!$F$30:$F$149)=0,'Configuración'!$C$8,MIN(Inversiones!$F$30:$F$149))),1),10),'Cálculos'!$C$278:$C$334,'Cálculos'!$I$4)=1,SUMIFS('Cálculos'!$J$278:$J$334,'Cálculos'!$B$278:$B$334,EDATE(DATE(YEAR(IF(COUNT(Inversiones!$F$30:$F$149)=0,'Configuración'!$C$8,MIN(Inversiones!$F$30:$F$149))),MONTH(IF(COUNT(Inversiones!$F$30:$F$149)=0,'Configuración'!$C$8,MIN(Inversiones!$F$30:$F$149))),1),10),'Cálculos'!$C$278:$C$334,'Cálculos'!$I$4),""))) | E938: =IF(COUNT(C938,D938)<2,"",D938-C938)
B939: =IF(EDATE(DATE(YEAR(IF(COUNT(Inversiones!$F$30:$F$149)=0,'Configuración'!$C$8,MIN(Inversiones!$F$30:$F$149))),MONTH(IF(COUNT(Inversiones!$F$30:$F$149)=0,'Configuración'!$C$8,MIN(Inversiones!$F$30:$F$149))),1),11)>EOMONTH('Configuración'!$C$8,0),"",TEXT(EDATE(DATE(YEAR(IF(COUNT(Inversiones!$F$30:$F$149)=0,'Configuración'!$C$8,MIN(Inversiones!$F$30:$F$149))),MONTH(IF(COUNT(Inversiones!$F$30:$F$149)=0,'Configuración'!$C$8,MIN(Inversiones!$F$30:$F$149))),1),11),"mmm yyyy")) | C939: =IF(EDATE(DATE(YEAR(IF(COUNT(Inversiones!$F$30:$F$149)=0,'Configuración'!$C$8,MIN(Inversiones!$F$30:$F$149))),MONTH(IF(COUNT(Inversiones!$F$30:$F$149)=0,'Configuración'!$C$8,MIN(Inversiones!$F$30:$F$149))),1),11)>EOMONTH('Configuración'!$C$8,0),"",IF(Inversiones!$D$4="Todos",IF(SUMIFS('Cálculos'!$E$278:$E$334,'Cálculos'!$B$278:$B$334,EDATE(DATE(YEAR(IF(COUNT(Inversiones!$F$30:$F$149)=0,'Configuración'!$C$8,MIN(Inversiones!$F$30:$F$149))),MONTH(IF(COUNT(Inversiones!$F$30:$F$149)=0,'Configuración'!$C$8,MIN(Inversiones!$F$30:$F$149))),1),11))=COUNTA(Inversiones!$B$30:$B$149),SUMIFS('Cálculos'!$G$278:$G$334,'Cálculos'!$B$278:$B$334,EDATE(DATE(YEAR(IF(COUNT(Inversiones!$F$30:$F$149)=0,'Configuración'!$C$8,MIN(Inversiones!$F$30:$F$149))),MONTH(IF(COUNT(Inversiones!$F$30:$F$149)=0,'Configuración'!$C$8,MIN(Inversiones!$F$30:$F$149))),1),11)),""),IF(SUMIFS('Cálculos'!$E$278:$E$334,'Cálculos'!$B$278:$B$334,EDATE(DATE(YEAR(IF(COUNT(Inversiones!$F$30:$F$149)=0,'Configuración'!$C$8,MIN(Inversiones!$F$30:$F$149))),MONTH(IF(COUNT(Inversiones!$F$30:$F$149)=0,'Configuración'!$C$8,MIN(Inversiones!$F$30:$F$149))),1),11),'Cálculos'!$C$278:$C$334,'Cálculos'!$I$4)=1,SUMIFS('Cálculos'!$G$278:$G$334,'Cálculos'!$B$278:$B$334,EDATE(DATE(YEAR(IF(COUNT(Inversiones!$F$30:$F$149)=0,'Configuración'!$C$8,MIN(Inversiones!$F$30:$F$149))),MONTH(IF(COUNT(Inversiones!$F$30:$F$149)=0,'Configuración'!$C$8,MIN(Inversiones!$F$30:$F$149))),1),11),'Cálculos'!$C$278:$C$334,'Cálculos'!$I$4),""))) | D939: =IF(EDATE(DATE(YEAR(IF(COUNT(Inversiones!$F$30:$F$149)=0,'Configuración'!$C$8,MIN(Inversiones!$F$30:$F$149))),MONTH(IF(COUNT(Inversiones!$F$30:$F$149)=0,'Configuración'!$C$8,MIN(Inversiones!$F$30:$F$149))),1),11)>EOMONTH('Configuración'!$C$8,0),"",IF(Inversiones!$D$4="Todos",IF(SUMIFS('Cálculos'!$K$278:$K$334,'Cálculos'!$B$278:$B$334,EDATE(DATE(YEAR(IF(COUNT(Inversiones!$F$30:$F$149)=0,'Configuración'!$C$8,MIN(Inversiones!$F$30:$F$149))),MONTH(IF(COUNT(Inversiones!$F$30:$F$149)=0,'Configuración'!$C$8,MIN(Inversiones!$F$30:$F$149))),1),11))=COUNTA(Inversiones!$B$30:$B$149),SUMIFS('Cálculos'!$J$278:$J$334,'Cálculos'!$B$278:$B$334,EDATE(DATE(YEAR(IF(COUNT(Inversiones!$F$30:$F$149)=0,'Configuración'!$C$8,MIN(Inversiones!$F$30:$F$149))),MONTH(IF(COUNT(Inversiones!$F$30:$F$149)=0,'Configuración'!$C$8,MIN(Inversiones!$F$30:$F$149))),1),11)),""),IF(SUMIFS('Cálculos'!$K$278:$K$334,'Cálculos'!$B$278:$B$334,EDATE(DATE(YEAR(IF(COUNT(Inversiones!$F$30:$F$149)=0,'Configuración'!$C$8,MIN(Inversiones!$F$30:$F$149))),MONTH(IF(COUNT(Inversiones!$F$30:$F$149)=0,'Configuración'!$C$8,MIN(Inversiones!$F$30:$F$149))),1),11),'Cálculos'!$C$278:$C$334,'Cálculos'!$I$4)=1,SUMIFS('Cálculos'!$J$278:$J$334,'Cálculos'!$B$278:$B$334,EDATE(DATE(YEAR(IF(COUNT(Inversiones!$F$30:$F$149)=0,'Configuración'!$C$8,MIN(Inversiones!$F$30:$F$149))),MONTH(IF(COUNT(Inversiones!$F$30:$F$149)=0,'Configuración'!$C$8,MIN(Inversiones!$F$30:$F$149))),1),11),'Cálculos'!$C$278:$C$334,'Cálculos'!$I$4),""))) | E939: =IF(COUNT(C939,D939)<2,"",D939-C939)
B940: =IF(EDATE(DATE(YEAR(IF(COUNT(Inversiones!$F$30:$F$149)=0,'Configuración'!$C$8,MIN(Inversiones!$F$30:$F$149))),MONTH(IF(COUNT(Inversiones!$F$30:$F$149)=0,'Configuración'!$C$8,MIN(Inversiones!$F$30:$F$149))),1),12)>EOMONTH('Configuración'!$C$8,0),"",TEXT(EDATE(DATE(YEAR(IF(COUNT(Inversiones!$F$30:$F$149)=0,'Configuración'!$C$8,MIN(Inversiones!$F$30:$F$149))),MONTH(IF(COUNT(Inversiones!$F$30:$F$149)=0,'Configuración'!$C$8,MIN(Inversiones!$F$30:$F$149))),1),12),"mmm yyyy")) | C940: =IF(EDATE(DATE(YEAR(IF(COUNT(Inversiones!$F$30:$F$149)=0,'Configuración'!$C$8,MIN(Inversiones!$F$30:$F$149))),MONTH(IF(COUNT(Inversiones!$F$30:$F$149)=0,'Configuración'!$C$8,MIN(Inversiones!$F$30:$F$149))),1),12)>EOMONTH('Configuración'!$C$8,0),"",IF(Inversiones!$D$4="Todos",IF(SUMIFS('Cálculos'!$E$278:$E$334,'Cálculos'!$B$278:$B$334,EDATE(DATE(YEAR(IF(COUNT(Inversiones!$F$30:$F$149)=0,'Configuración'!$C$8,MIN(Inversiones!$F$30:$F$149))),MONTH(IF(COUNT(Inversiones!$F$30:$F$149)=0,'Configuración'!$C$8,MIN(Inversiones!$F$30:$F$149))),1),12))=COUNTA(Inversiones!$B$30:$B$149),SUMIFS('Cálculos'!$G$278:$G$334,'Cálculos'!$B$278:$B$334,EDATE(DATE(YEAR(IF(COUNT(Inversiones!$F$30:$F$149)=0,'Configuración'!$C$8,MIN(Inversiones!$F$30:$F$149))),MONTH(IF(COUNT(Inversiones!$F$30:$F$149)=0,'Configuración'!$C$8,MIN(Inversiones!$F$30:$F$149))),1),12)),""),IF(SUMIFS('Cálculos'!$E$278:$E$334,'Cálculos'!$B$278:$B$334,EDATE(DATE(YEAR(IF(COUNT(Inversiones!$F$30:$F$149)=0,'Configuración'!$C$8,MIN(Inversiones!$F$30:$F$149))),MONTH(IF(COUNT(Inversiones!$F$30:$F$149)=0,'Configuración'!$C$8,MIN(Inversiones!$F$30:$F$149))),1),12),'Cálculos'!$C$278:$C$334,'Cálculos'!$I$4)=1,SUMIFS('Cálculos'!$G$278:$G$334,'Cálculos'!$B$278:$B$334,EDATE(DATE(YEAR(IF(COUNT(Inversiones!$F$30:$F$149)=0,'Configuración'!$C$8,MIN(Inversiones!$F$30:$F$149))),MONTH(IF(COUNT(Inversiones!$F$30:$F$149)=0,'Configuración'!$C$8,MIN(Inversiones!$F$30:$F$149))),1),12),'Cálculos'!$C$278:$C$334,'Cálculos'!$I$4),""))) | D940: =IF(EDATE(DATE(YEAR(IF(COUNT(Inversiones!$F$30:$F$149)=0,'Configuración'!$C$8,MIN(Inversiones!$F$30:$F$149))),MONTH(IF(COUNT(Inversiones!$F$30:$F$149)=0,'Configuración'!$C$8,MIN(Inversiones!$F$30:$F$149))),1),12)>EOMONTH('Configuración'!$C$8,0),"",IF(Inversiones!$D$4="Todos",IF(SUMIFS('Cálculos'!$K$278:$K$334,'Cálculos'!$B$278:$B$334,EDATE(DATE(YEAR(IF(COUNT(Inversiones!$F$30:$F$149)=0,'Configuración'!$C$8,MIN(Inversiones!$F$30:$F$149))),MONTH(IF(COUNT(Inversiones!$F$30:$F$149)=0,'Configuración'!$C$8,MIN(Inversiones!$F$30:$F$149))),1),12))=COUNTA(Inversiones!$B$30:$B$149),SUMIFS('Cálculos'!$J$278:$J$334,'Cálculos'!$B$278:$B$334,EDATE(DATE(YEAR(IF(COUNT(Inversiones!$F$30:$F$149)=0,'Configuración'!$C$8,MIN(Inversiones!$F$30:$F$149))),MONTH(IF(COUNT(Inversiones!$F$30:$F$149)=0,'Configuración'!$C$8,MIN(Inversiones!$F$30:$F$149))),1),12)),""),IF(SUMIFS('Cálculos'!$K$278:$K$334,'Cálculos'!$B$278:$B$334,EDATE(DATE(YEAR(IF(COUNT(Inversiones!$F$30:$F$149)=0,'Configuración'!$C$8,MIN(Inversiones!$F$30:$F$149))),MONTH(IF(COUNT(Inversiones!$F$30:$F$149)=0,'Configuración'!$C$8,MIN(Inversiones!$F$30:$F$149))),1),12),'Cálculos'!$C$278:$C$334,'Cálculos'!$I$4)=1,SUMIFS('Cálculos'!$J$278:$J$334,'Cálculos'!$B$278:$B$334,EDATE(DATE(YEAR(IF(COUNT(Inversiones!$F$30:$F$149)=0,'Configuración'!$C$8,MIN(Inversiones!$F$30:$F$149))),MONTH(IF(COUNT(Inversiones!$F$30:$F$149)=0,'Configuración'!$C$8,MIN(Inversiones!$F$30:$F$149))),1),12),'Cálculos'!$C$278:$C$334,'Cálculos'!$I$4),""))) | E940: =IF(COUNT(C940,D940)<2,"",D940-C940)
B941: =IF(EDATE(DATE(YEAR(IF(COUNT(Inversiones!$F$30:$F$149)=0,'Configuración'!$C$8,MIN(Inversiones!$F$30:$F$149))),MONTH(IF(COUNT(Inversiones!$F$30:$F$149)=0,'Configuración'!$C$8,MIN(Inversiones!$F$30:$F$149))),1),13)>EOMONTH('Configuración'!$C$8,0),"",TEXT(EDATE(DATE(YEAR(IF(COUNT(Inversiones!$F$30:$F$149)=0,'Configuración'!$C$8,MIN(Inversiones!$F$30:$F$149))),MONTH(IF(COUNT(Inversiones!$F$30:$F$149)=0,'Configuración'!$C$8,MIN(Inversiones!$F$30:$F$149))),1),13),"mmm yyyy")) | C941: =IF(EDATE(DATE(YEAR(IF(COUNT(Inversiones!$F$30:$F$149)=0,'Configuración'!$C$8,MIN(Inversiones!$F$30:$F$149))),MONTH(IF(COUNT(Inversiones!$F$30:$F$149)=0,'Configuración'!$C$8,MIN(Inversiones!$F$30:$F$149))),1),13)>EOMONTH('Configuración'!$C$8,0),"",IF(Inversiones!$D$4="Todos",IF(SUMIFS('Cálculos'!$E$278:$E$334,'Cálculos'!$B$278:$B$334,EDATE(DATE(YEAR(IF(COUNT(Inversiones!$F$30:$F$149)=0,'Configuración'!$C$8,MIN(Inversiones!$F$30:$F$149))),MONTH(IF(COUNT(Inversiones!$F$30:$F$149)=0,'Configuración'!$C$8,MIN(Inversiones!$F$30:$F$149))),1),13))=COUNTA(Inversiones!$B$30:$B$149),SUMIFS('Cálculos'!$G$278:$G$334,'Cálculos'!$B$278:$B$334,EDATE(DATE(YEAR(IF(COUNT(Inversiones!$F$30:$F$149)=0,'Configuración'!$C$8,MIN(Inversiones!$F$30:$F$149))),MONTH(IF(COUNT(Inversiones!$F$30:$F$149)=0,'Configuración'!$C$8,MIN(Inversiones!$F$30:$F$149))),1),13)),""),IF(SUMIFS('Cálculos'!$E$278:$E$334,'Cálculos'!$B$278:$B$334,EDATE(DATE(YEAR(IF(COUNT(Inversiones!$F$30:$F$149)=0,'Configuración'!$C$8,MIN(Inversiones!$F$30:$F$149))),MONTH(IF(COUNT(Inversiones!$F$30:$F$149)=0,'Configuración'!$C$8,MIN(Inversiones!$F$30:$F$149))),1),13),'Cálculos'!$C$278:$C$334,'Cálculos'!$I$4)=1,SUMIFS('Cálculos'!$G$278:$G$334,'Cálculos'!$B$278:$B$334,EDATE(DATE(YEAR(IF(COUNT(Inversiones!$F$30:$F$149)=0,'Configuración'!$C$8,MIN(Inversiones!$F$30:$F$149))),MONTH(IF(COUNT(Inversiones!$F$30:$F$149)=0,'Configuración'!$C$8,MIN(Inversiones!$F$30:$F$149))),1),13),'Cálculos'!$C$278:$C$334,'Cálculos'!$I$4),""))) | D941: =IF(EDATE(DATE(YEAR(IF(COUNT(Inversiones!$F$30:$F$149)=0,'Configuración'!$C$8,MIN(Inversiones!$F$30:$F$149))),MONTH(IF(COUNT(Inversiones!$F$30:$F$149)=0,'Configuración'!$C$8,MIN(Inversiones!$F$30:$F$149))),1),13)>EOMONTH('Configuración'!$C$8,0),"",IF(Inversiones!$D$4="Todos",IF(SUMIFS('Cálculos'!$K$278:$K$334,'Cálculos'!$B$278:$B$334,EDATE(DATE(YEAR(IF(COUNT(Inversiones!$F$30:$F$149)=0,'Configuración'!$C$8,MIN(Inversiones!$F$30:$F$149))),MONTH(IF(COUNT(Inversiones!$F$30:$F$149)=0,'Configuración'!$C$8,MIN(Inversiones!$F$30:$F$149))),1),13))=COUNTA(Inversiones!$B$30:$B$149),SUMIFS('Cálculos'!$J$278:$J$334,'Cálculos'!$B$278:$B$334,EDATE(DATE(YEAR(IF(COUNT(Inversiones!$F$30:$F$149)=0,'Configuración'!$C$8,MIN(Inversiones!$F$30:$F$149))),MONTH(IF(COUNT(Inversiones!$F$30:$F$149)=0,'Configuración'!$C$8,MIN(Inversiones!$F$30:$F$149))),1),13)),""),IF(SUMIFS('Cálculos'!$K$278:$K$334,'Cálculos'!$B$278:$B$334,EDATE(DATE(YEAR(IF(COUNT(Inversiones!$F$30:$F$149)=0,'Configuración'!$C$8,MIN(Inversiones!$F$30:$F$149))),MONTH(IF(COUNT(Inversiones!$F$30:$F$149)=0,'Configuración'!$C$8,MIN(Inversiones!$F$30:$F$149))),1),13),'Cálculos'!$C$278:$C$334,'Cálculos'!$I$4)=1,SUMIFS('Cálculos'!$J$278:$J$334,'Cálculos'!$B$278:$B$334,EDATE(DATE(YEAR(IF(COUNT(Inversiones!$F$30:$F$149)=0,'Configuración'!$C$8,MIN(Inversiones!$F$30:$F$149))),MONTH(IF(COUNT(Inversiones!$F$30:$F$149)=0,'Configuración'!$C$8,MIN(Inversiones!$F$30:$F$149))),1),13),'Cálculos'!$C$278:$C$334,'Cálculos'!$I$4),""))) | E941: =IF(COUNT(C941,D941)<2,"",D941-C941)
B942: =IF(EDATE(DATE(YEAR(IF(COUNT(Inversiones!$F$30:$F$149)=0,'Configuración'!$C$8,MIN(Inversiones!$F$30:$F$149))),MONTH(IF(COUNT(Inversiones!$F$30:$F$149)=0,'Configuración'!$C$8,MIN(Inversiones!$F$30:$F$149))),1),14)>EOMONTH('Configuración'!$C$8,0),"",TEXT(EDATE(DATE(YEAR(IF(COUNT(Inversiones!$F$30:$F$149)=0,'Configuración'!$C$8,MIN(Inversiones!$F$30:$F$149))),MONTH(IF(COUNT(Inversiones!$F$30:$F$149)=0,'Configuración'!$C$8,MIN(Inversiones!$F$30:$F$149))),1),14),"mmm yyyy")) | C942: =IF(EDATE(DATE(YEAR(IF(COUNT(Inversiones!$F$30:$F$149)=0,'Configuración'!$C$8,MIN(Inversiones!$F$30:$F$149))),MONTH(IF(COUNT(Inversiones!$F$30:$F$149)=0,'Configuración'!$C$8,MIN(Inversiones!$F$30:$F$149))),1),14)>EOMONTH('Configuración'!$C$8,0),"",IF(Inversiones!$D$4="Todos",IF(SUMIFS('Cálculos'!$E$278:$E$334,'Cálculos'!$B$278:$B$334,EDATE(DATE(YEAR(IF(COUNT(Inversiones!$F$30:$F$149)=0,'Configuración'!$C$8,MIN(Inversiones!$F$30:$F$149))),MONTH(IF(COUNT(Inversiones!$F$30:$F$149)=0,'Configuración'!$C$8,MIN(Inversiones!$F$30:$F$149))),1),14))=COUNTA(Inversiones!$B$30:$B$149),SUMIFS('Cálculos'!$G$278:$G$334,'Cálculos'!$B$278:$B$334,EDATE(DATE(YEAR(IF(COUNT(Inversiones!$F$30:$F$149)=0,'Configuración'!$C$8,MIN(Inversiones!$F$30:$F$149))),MONTH(IF(COUNT(Inversiones!$F$30:$F$149)=0,'Configuración'!$C$8,MIN(Inversiones!$F$30:$F$149))),1),14)),""),IF(SUMIFS('Cálculos'!$E$278:$E$334,'Cálculos'!$B$278:$B$334,EDATE(DATE(YEAR(IF(COUNT(Inversiones!$F$30:$F$149)=0,'Configuración'!$C$8,MIN(Inversiones!$F$30:$F$149))),MONTH(IF(COUNT(Inversiones!$F$30:$F$149)=0,'Configuración'!$C$8,MIN(Inversiones!$F$30:$F$149))),1),14),'Cálculos'!$C$278:$C$334,'Cálculos'!$I$4)=1,SUMIFS('Cálculos'!$G$278:$G$334,'Cálculos'!$B$278:$B$334,EDATE(DATE(YEAR(IF(COUNT(Inversiones!$F$30:$F$149)=0,'Configuración'!$C$8,MIN(Inversiones!$F$30:$F$149))),MONTH(IF(COUNT(Inversiones!$F$30:$F$149)=0,'Configuración'!$C$8,MIN(Inversiones!$F$30:$F$149))),1),14),'Cálculos'!$C$278:$C$334,'Cálculos'!$I$4),""))) | D942: =IF(EDATE(DATE(YEAR(IF(COUNT(Inversiones!$F$30:$F$149)=0,'Configuración'!$C$8,MIN(Inversiones!$F$30:$F$149))),MONTH(IF(COUNT(Inversiones!$F$30:$F$149)=0,'Configuración'!$C$8,MIN(Inversiones!$F$30:$F$149))),1),14)>EOMONTH('Configuración'!$C$8,0),"",IF(Inversiones!$D$4="Todos",IF(SUMIFS('Cálculos'!$K$278:$K$334,'Cálculos'!$B$278:$B$334,EDATE(DATE(YEAR(IF(COUNT(Inversiones!$F$30:$F$149)=0,'Configuración'!$C$8,MIN(Inversiones!$F$30:$F$149))),MONTH(IF(COUNT(Inversiones!$F$30:$F$149)=0,'Configuración'!$C$8,MIN(Inversiones!$F$30:$F$149))),1),14))=COUNTA(Inversiones!$B$30:$B$149),SUMIFS('Cálculos'!$J$278:$J$334,'Cálculos'!$B$278:$B$334,EDATE(DATE(YEAR(IF(COUNT(Inversiones!$F$30:$F$149)=0,'Configuración'!$C$8,MIN(Inversiones!$F$30:$F$149))),MONTH(IF(COUNT(Inversiones!$F$30:$F$149)=0,'Configuración'!$C$8,MIN(Inversiones!$F$30:$F$149))),1),14)),""),IF(SUMIFS('Cálculos'!$K$278:$K$334,'Cálculos'!$B$278:$B$334,EDATE(DATE(YEAR(IF(COUNT(Inversiones!$F$30:$F$149)=0,'Configuración'!$C$8,MIN(Inversiones!$F$30:$F$149))),MONTH(IF(COUNT(Inversiones!$F$30:$F$149)=0,'Configuración'!$C$8,MIN(Inversiones!$F$30:$F$149))),1),14),'Cálculos'!$C$278:$C$334,'Cálculos'!$I$4)=1,SUMIFS('Cálculos'!$J$278:$J$334,'Cálculos'!$B$278:$B$334,EDATE(DATE(YEAR(IF(COUNT(Inversiones!$F$30:$F$149)=0,'Configuración'!$C$8,MIN(Inversiones!$F$30:$F$149))),MONTH(IF(COUNT(Inversiones!$F$30:$F$149)=0,'Configuración'!$C$8,MIN(Inversiones!$F$30:$F$149))),1),14),'Cálculos'!$C$278:$C$334,'Cálculos'!$I$4),""))) | E942: =IF(COUNT(C942,D942)<2,"",D942-C942)
B943: =IF(EDATE(DATE(YEAR(IF(COUNT(Inversiones!$F$30:$F$149)=0,'Configuración'!$C$8,MIN(Inversiones!$F$30:$F$149))),MONTH(IF(COUNT(Inversiones!$F$30:$F$149)=0,'Configuración'!$C$8,MIN(Inversiones!$F$30:$F$149))),1),15)>EOMONTH('Configuración'!$C$8,0),"",TEXT(EDATE(DATE(YEAR(IF(COUNT(Inversiones!$F$30:$F$149)=0,'Configuración'!$C$8,MIN(Inversiones!$F$30:$F$149))),MONTH(IF(COUNT(Inversiones!$F$30:$F$149)=0,'Configuración'!$C$8,MIN(Inversiones!$F$30:$F$149))),1),15),"mmm yyyy")) | C943: =IF(EDATE(DATE(YEAR(IF(COUNT(Inversiones!$F$30:$F$149)=0,'Configuración'!$C$8,MIN(Inversiones!$F$30:$F$149))),MONTH(IF(COUNT(Inversiones!$F$30:$F$149)=0,'Configuración'!$C$8,MIN(Inversiones!$F$30:$F$149))),1),15)>EOMONTH('Configuración'!$C$8,0),"",IF(Inversiones!$D$4="Todos",IF(SUMIFS('Cálculos'!$E$278:$E$334,'Cálculos'!$B$278:$B$334,EDATE(DATE(YEAR(IF(COUNT(Inversiones!$F$30:$F$149)=0,'Configuración'!$C$8,MIN(Inversiones!$F$30:$F$149))),MONTH(IF(COUNT(Inversiones!$F$30:$F$149)=0,'Configuración'!$C$8,MIN(Inversiones!$F$30:$F$149))),1),15))=COUNTA(Inversiones!$B$30:$B$149),SUMIFS('Cálculos'!$G$278:$G$334,'Cálculos'!$B$278:$B$334,EDATE(DATE(YEAR(IF(COUNT(Inversiones!$F$30:$F$149)=0,'Configuración'!$C$8,MIN(Inversiones!$F$30:$F$149))),MONTH(IF(COUNT(Inversiones!$F$30:$F$149)=0,'Configuración'!$C$8,MIN(Inversiones!$F$30:$F$149))),1),15)),""),IF(SUMIFS('Cálculos'!$E$278:$E$334,'Cálculos'!$B$278:$B$334,EDATE(DATE(YEAR(IF(COUNT(Inversiones!$F$30:$F$149)=0,'Configuración'!$C$8,MIN(Inversiones!$F$30:$F$149))),MONTH(IF(COUNT(Inversiones!$F$30:$F$149)=0,'Configuración'!$C$8,MIN(Inversiones!$F$30:$F$149))),1),15),'Cálculos'!$C$278:$C$334,'Cálculos'!$I$4)=1,SUMIFS('Cálculos'!$G$278:$G$334,'Cálculos'!$B$278:$B$334,EDATE(DATE(YEAR(IF(COUNT(Inversiones!$F$30:$F$149)=0,'Configuración'!$C$8,MIN(Inversiones!$F$30:$F$149))),MONTH(IF(COUNT(Inversiones!$F$30:$F$149)=0,'Configuración'!$C$8,MIN(Inversiones!$F$30:$F$149))),1),15),'Cálculos'!$C$278:$C$334,'Cálculos'!$I$4),""))) | D943: =IF(EDATE(DATE(YEAR(IF(COUNT(Inversiones!$F$30:$F$149)=0,'Configuración'!$C$8,MIN(Inversiones!$F$30:$F$149))),MONTH(IF(COUNT(Inversiones!$F$30:$F$149)=0,'Configuración'!$C$8,MIN(Inversiones!$F$30:$F$149))),1),15)>EOMONTH('Configuración'!$C$8,0),"",IF(Inversiones!$D$4="Todos",IF(SUMIFS('Cálculos'!$K$278:$K$334,'Cálculos'!$B$278:$B$334,EDATE(DATE(YEAR(IF(COUNT(Inversiones!$F$30:$F$149)=0,'Configuración'!$C$8,MIN(Inversiones!$F$30:$F$149))),MONTH(IF(COUNT(Inversiones!$F$30:$F$149)=0,'Configuración'!$C$8,MIN(Inversiones!$F$30:$F$149))),1),15))=COUNTA(Inversiones!$B$30:$B$149),SUMIFS('Cálculos'!$J$278:$J$334,'Cálculos'!$B$278:$B$334,EDATE(DATE(YEAR(IF(COUNT(Inversiones!$F$30:$F$149)=0,'Configuración'!$C$8,MIN(Inversiones!$F$30:$F$149))),MONTH(IF(COUNT(Inversiones!$F$30:$F$149)=0,'Configuración'!$C$8,MIN(Inversiones!$F$30:$F$149))),1),15)),""),IF(SUMIFS('Cálculos'!$K$278:$K$334,'Cálculos'!$B$278:$B$334,EDATE(DATE(YEAR(IF(COUNT(Inversiones!$F$30:$F$149)=0,'Configuración'!$C$8,MIN(Inversiones!$F$30:$F$149))),MONTH(IF(COUNT(Inversiones!$F$30:$F$149)=0,'Configuración'!$C$8,MIN(Inversiones!$F$30:$F$149))),1),15),'Cálculos'!$C$278:$C$334,'Cálculos'!$I$4)=1,SUMIFS('Cálculos'!$J$278:$J$334,'Cálculos'!$B$278:$B$334,EDATE(DATE(YEAR(IF(COUNT(Inversiones!$F$30:$F$149)=0,'Configuración'!$C$8,MIN(Inversiones!$F$30:$F$149))),MONTH(IF(COUNT(Inversiones!$F$30:$F$149)=0,'Configuración'!$C$8,MIN(Inversiones!$F$30:$F$149))),1),15),'Cálculos'!$C$278:$C$334,'Cálculos'!$I$4),""))) | E943: =IF(COUNT(C943,D943)<2,"",D943-C943)
B944: =IF(EDATE(DATE(YEAR(IF(COUNT(Inversiones!$F$30:$F$149)=0,'Configuración'!$C$8,MIN(Inversiones!$F$30:$F$149))),MONTH(IF(COUNT(Inversiones!$F$30:$F$149)=0,'Configuración'!$C$8,MIN(Inversiones!$F$30:$F$149))),1),16)>EOMONTH('Configuración'!$C$8,0),"",TEXT(EDATE(DATE(YEAR(IF(COUNT(Inversiones!$F$30:$F$149)=0,'Configuración'!$C$8,MIN(Inversiones!$F$30:$F$149))),MONTH(IF(COUNT(Inversiones!$F$30:$F$149)=0,'Configuración'!$C$8,MIN(Inversiones!$F$30:$F$149))),1),16),"mmm yyyy")) | C944: =IF(EDATE(DATE(YEAR(IF(COUNT(Inversiones!$F$30:$F$149)=0,'Configuración'!$C$8,MIN(Inversiones!$F$30:$F$149))),MONTH(IF(COUNT(Inversiones!$F$30:$F$149)=0,'Configuración'!$C$8,MIN(Inversiones!$F$30:$F$149))),1),16)>EOMONTH('Configuración'!$C$8,0),"",IF(Inversiones!$D$4="Todos",IF(SUMIFS('Cálculos'!$E$278:$E$334,'Cálculos'!$B$278:$B$334,EDATE(DATE(YEAR(IF(COUNT(Inversiones!$F$30:$F$149)=0,'Configuración'!$C$8,MIN(Inversiones!$F$30:$F$149))),MONTH(IF(COUNT(Inversiones!$F$30:$F$149)=0,'Configuración'!$C$8,MIN(Inversiones!$F$30:$F$149))),1),16))=COUNTA(Inversiones!$B$30:$B$149),SUMIFS('Cálculos'!$G$278:$G$334,'Cálculos'!$B$278:$B$334,EDATE(DATE(YEAR(IF(COUNT(Inversiones!$F$30:$F$149)=0,'Configuración'!$C$8,MIN(Inversiones!$F$30:$F$149))),MONTH(IF(COUNT(Inversiones!$F$30:$F$149)=0,'Configuración'!$C$8,MIN(Inversiones!$F$30:$F$149))),1),16)),""),IF(SUMIFS('Cálculos'!$E$278:$E$334,'Cálculos'!$B$278:$B$334,EDATE(DATE(YEAR(IF(COUNT(Inversiones!$F$30:$F$149)=0,'Configuración'!$C$8,MIN(Inversiones!$F$30:$F$149))),MONTH(IF(COUNT(Inversiones!$F$30:$F$149)=0,'Configuración'!$C$8,MIN(Inversiones!$F$30:$F$149))),1),16),'Cálculos'!$C$278:$C$334,'Cálculos'!$I$4)=1,SUMIFS('Cálculos'!$G$278:$G$334,'Cálculos'!$B$278:$B$334,EDATE(DATE(YEAR(IF(COUNT(Inversiones!$F$30:$F$149)=0,'Configuración'!$C$8,MIN(Inversiones!$F$30:$F$149))),MONTH(IF(COUNT(Inversiones!$F$30:$F$149)=0,'Configuración'!$C$8,MIN(Inversiones!$F$30:$F$149))),1),16),'Cálculos'!$C$278:$C$334,'Cálculos'!$I$4),""))) | D944: =IF(EDATE(DATE(YEAR(IF(COUNT(Inversiones!$F$30:$F$149)=0,'Configuración'!$C$8,MIN(Inversiones!$F$30:$F$149))),MONTH(IF(COUNT(Inversiones!$F$30:$F$149)=0,'Configuración'!$C$8,MIN(Inversiones!$F$30:$F$149))),1),16)>EOMONTH('Configuración'!$C$8,0),"",IF(Inversiones!$D$4="Todos",IF(SUMIFS('Cálculos'!$K$278:$K$334,'Cálculos'!$B$278:$B$334,EDATE(DATE(YEAR(IF(COUNT(Inversiones!$F$30:$F$149)=0,'Configuración'!$C$8,MIN(Inversiones!$F$30:$F$149))),MONTH(IF(COUNT(Inversiones!$F$30:$F$149)=0,'Configuración'!$C$8,MIN(Inversiones!$F$30:$F$149))),1),16))=COUNTA(Inversiones!$B$30:$B$149),SUMIFS('Cálculos'!$J$278:$J$334,'Cálculos'!$B$278:$B$334,EDATE(DATE(YEAR(IF(COUNT(Inversiones!$F$30:$F$149)=0,'Configuración'!$C$8,MIN(Inversiones!$F$30:$F$149))),MONTH(IF(COUNT(Inversiones!$F$30:$F$149)=0,'Configuración'!$C$8,MIN(Inversiones!$F$30:$F$149))),1),16)),""),IF(SUMIFS('Cálculos'!$K$278:$K$334,'Cálculos'!$B$278:$B$334,EDATE(DATE(YEAR(IF(COUNT(Inversiones!$F$30:$F$149)=0,'Configuración'!$C$8,MIN(Inversiones!$F$30:$F$149))),MONTH(IF(COUNT(Inversiones!$F$30:$F$149)=0,'Configuración'!$C$8,MIN(Inversiones!$F$30:$F$149))),1),16),'Cálculos'!$C$278:$C$334,'Cálculos'!$I$4)=1,SUMIFS('Cálculos'!$J$278:$J$334,'Cálculos'!$B$278:$B$334,EDATE(DATE(YEAR(IF(COUNT(Inversiones!$F$30:$F$149)=0,'Configuración'!$C$8,MIN(Inversiones!$F$30:$F$149))),MONTH(IF(COUNT(Inversiones!$F$30:$F$149)=0,'Configuración'!$C$8,MIN(Inversiones!$F$30:$F$149))),1),16),'Cálculos'!$C$278:$C$334,'Cálculos'!$I$4),""))) | E944: =IF(COUNT(C944,D944)<2,"",D944-C944)
B945: =IF(EDATE(DATE(YEAR(IF(COUNT(Inversiones!$F$30:$F$149)=0,'Configuración'!$C$8,MIN(Inversiones!$F$30:$F$149))),MONTH(IF(COUNT(Inversiones!$F$30:$F$149)=0,'Configuración'!$C$8,MIN(Inversiones!$F$30:$F$149))),1),17)>EOMONTH('Configuración'!$C$8,0),"",TEXT(EDATE(DATE(YEAR(IF(COUNT(Inversiones!$F$30:$F$149)=0,'Configuración'!$C$8,MIN(Inversiones!$F$30:$F$149))),MONTH(IF(COUNT(Inversiones!$F$30:$F$149)=0,'Configuración'!$C$8,MIN(Inversiones!$F$30:$F$149))),1),17),"mmm yyyy")) | C945: =IF(EDATE(DATE(YEAR(IF(COUNT(Inversiones!$F$30:$F$149)=0,'Configuración'!$C$8,MIN(Inversiones!$F$30:$F$149))),MONTH(IF(COUNT(Inversiones!$F$30:$F$149)=0,'Configuración'!$C$8,MIN(Inversiones!$F$30:$F$149))),1),17)>EOMONTH('Configuración'!$C$8,0),"",IF(Inversiones!$D$4="Todos",IF(SUMIFS('Cálculos'!$E$278:$E$334,'Cálculos'!$B$278:$B$334,EDATE(DATE(YEAR(IF(COUNT(Inversiones!$F$30:$F$149)=0,'Configuración'!$C$8,MIN(Inversiones!$F$30:$F$149))),MONTH(IF(COUNT(Inversiones!$F$30:$F$149)=0,'Configuración'!$C$8,MIN(Inversiones!$F$30:$F$149))),1),17))=COUNTA(Inversiones!$B$30:$B$149),SUMIFS('Cálculos'!$G$278:$G$334,'Cálculos'!$B$278:$B$334,EDATE(DATE(YEAR(IF(COUNT(Inversiones!$F$30:$F$149)=0,'Configuración'!$C$8,MIN(Inversiones!$F$30:$F$149))),MONTH(IF(COUNT(Inversiones!$F$30:$F$149)=0,'Configuración'!$C$8,MIN(Inversiones!$F$30:$F$149))),1),17)),""),IF(SUMIFS('Cálculos'!$E$278:$E$334,'Cálculos'!$B$278:$B$334,EDATE(DATE(YEAR(IF(COUNT(Inversiones!$F$30:$F$149)=0,'Configuración'!$C$8,MIN(Inversiones!$F$30:$F$149))),MONTH(IF(COUNT(Inversiones!$F$30:$F$149)=0,'Configuración'!$C$8,MIN(Inversiones!$F$30:$F$149))),1),17),'Cálculos'!$C$278:$C$334,'Cálculos'!$I$4)=1,SUMIFS('Cálculos'!$G$278:$G$334,'Cálculos'!$B$278:$B$334,EDATE(DATE(YEAR(IF(COUNT(Inversiones!$F$30:$F$149)=0,'Configuración'!$C$8,MIN(Inversiones!$F$30:$F$149))),MONTH(IF(COUNT(Inversiones!$F$30:$F$149)=0,'Configuración'!$C$8,MIN(Inversiones!$F$30:$F$149))),1),17),'Cálculos'!$C$278:$C$334,'Cálculos'!$I$4),""))) | D945: =IF(EDATE(DATE(YEAR(IF(COUNT(Inversiones!$F$30:$F$149)=0,'Configuración'!$C$8,MIN(Inversiones!$F$30:$F$149))),MONTH(IF(COUNT(Inversiones!$F$30:$F$149)=0,'Configuración'!$C$8,MIN(Inversiones!$F$30:$F$149))),1),17)>EOMONTH('Configuración'!$C$8,0),"",IF(Inversiones!$D$4="Todos",IF(SUMIFS('Cálculos'!$K$278:$K$334,'Cálculos'!$B$278:$B$334,EDATE(DATE(YEAR(IF(COUNT(Inversiones!$F$30:$F$149)=0,'Configuración'!$C$8,MIN(Inversiones!$F$30:$F$149))),MONTH(IF(COUNT(Inversiones!$F$30:$F$149)=0,'Configuración'!$C$8,MIN(Inversiones!$F$30:$F$149))),1),17))=COUNTA(Inversiones!$B$30:$B$149),SUMIFS('Cálculos'!$J$278:$J$334,'Cálculos'!$B$278:$B$334,EDATE(DATE(YEAR(IF(COUNT(Inversiones!$F$30:$F$149)=0,'Configuración'!$C$8,MIN(Inversiones!$F$30:$F$149))),MONTH(IF(COUNT(Inversiones!$F$30:$F$149)=0,'Configuración'!$C$8,MIN(Inversiones!$F$30:$F$149))),1),17)),""),IF(SUMIFS('Cálculos'!$K$278:$K$334,'Cálculos'!$B$278:$B$334,EDATE(DATE(YEAR(IF(COUNT(Inversiones!$F$30:$F$149)=0,'Configuración'!$C$8,MIN(Inversiones!$F$30:$F$149))),MONTH(IF(COUNT(Inversiones!$F$30:$F$149)=0,'Configuración'!$C$8,MIN(Inversiones!$F$30:$F$149))),1),17),'Cálculos'!$C$278:$C$334,'Cálculos'!$I$4)=1,SUMIFS('Cálculos'!$J$278:$J$334,'Cálculos'!$B$278:$B$334,EDATE(DATE(YEAR(IF(COUNT(Inversiones!$F$30:$F$149)=0,'Configuración'!$C$8,MIN(Inversiones!$F$30:$F$149))),MONTH(IF(COUNT(Inversiones!$F$30:$F$149)=0,'Configuración'!$C$8,MIN(Inversiones!$F$30:$F$149))),1),17),'Cálculos'!$C$278:$C$334,'Cálculos'!$I$4),""))) | E945: =IF(COUNT(C945,D945)<2,"",D945-C945)
B946: =IF(EDATE(DATE(YEAR(IF(COUNT(Inversiones!$F$30:$F$149)=0,'Configuración'!$C$8,MIN(Inversiones!$F$30:$F$149))),MONTH(IF(COUNT(Inversiones!$F$30:$F$149)=0,'Configuración'!$C$8,MIN(Inversiones!$F$30:$F$149))),1),18)>EOMONTH('Configuración'!$C$8,0),"",TEXT(EDATE(DATE(YEAR(IF(COUNT(Inversiones!$F$30:$F$149)=0,'Configuración'!$C$8,MIN(Inversiones!$F$30:$F$149))),MONTH(IF(COUNT(Inversiones!$F$30:$F$149)=0,'Configuración'!$C$8,MIN(Inversiones!$F$30:$F$149))),1),18),"mmm yyyy")) | C946: =IF(EDATE(DATE(YEAR(IF(COUNT(Inversiones!$F$30:$F$149)=0,'Configuración'!$C$8,MIN(Inversiones!$F$30:$F$149))),MONTH(IF(COUNT(Inversiones!$F$30:$F$149)=0,'Configuración'!$C$8,MIN(Inversiones!$F$30:$F$149))),1),18)>EOMONTH('Configuración'!$C$8,0),"",IF(Inversiones!$D$4="Todos",IF(SUMIFS('Cálculos'!$E$278:$E$334,'Cálculos'!$B$278:$B$334,EDATE(DATE(YEAR(IF(COUNT(Inversiones!$F$30:$F$149)=0,'Configuración'!$C$8,MIN(Inversiones!$F$30:$F$149))),MONTH(IF(COUNT(Inversiones!$F$30:$F$149)=0,'Configuración'!$C$8,MIN(Inversiones!$F$30:$F$149))),1),18))=COUNTA(Inversiones!$B$30:$B$149),SUMIFS('Cálculos'!$G$278:$G$334,'Cálculos'!$B$278:$B$334,EDATE(DATE(YEAR(IF(COUNT(Inversiones!$F$30:$F$149)=0,'Configuración'!$C$8,MIN(Inversiones!$F$30:$F$149))),MONTH(IF(COUNT(Inversiones!$F$30:$F$149)=0,'Configuración'!$C$8,MIN(Inversiones!$F$30:$F$149))),1),18)),""),IF(SUMIFS('Cálculos'!$E$278:$E$334,'Cálculos'!$B$278:$B$334,EDATE(DATE(YEAR(IF(COUNT(Inversiones!$F$30:$F$149)=0,'Configuración'!$C$8,MIN(Inversiones!$F$30:$F$149))),MONTH(IF(COUNT(Inversiones!$F$30:$F$149)=0,'Configuración'!$C$8,MIN(Inversiones!$F$30:$F$149))),1),18),'Cálculos'!$C$278:$C$334,'Cálculos'!$I$4)=1,SUMIFS('Cálculos'!$G$278:$G$334,'Cálculos'!$B$278:$B$334,EDATE(DATE(YEAR(IF(COUNT(Inversiones!$F$30:$F$149)=0,'Configuración'!$C$8,MIN(Inversiones!$F$30:$F$149))),MONTH(IF(COUNT(Inversiones!$F$30:$F$149)=0,'Configuración'!$C$8,MIN(Inversiones!$F$30:$F$149))),1),18),'Cálculos'!$C$278:$C$334,'Cálculos'!$I$4),""))) | D946: =IF(EDATE(DATE(YEAR(IF(COUNT(Inversiones!$F$30:$F$149)=0,'Configuración'!$C$8,MIN(Inversiones!$F$30:$F$149))),MONTH(IF(COUNT(Inversiones!$F$30:$F$149)=0,'Configuración'!$C$8,MIN(Inversiones!$F$30:$F$149))),1),18)>EOMONTH('Configuración'!$C$8,0),"",IF(Inversiones!$D$4="Todos",IF(SUMIFS('Cálculos'!$K$278:$K$334,'Cálculos'!$B$278:$B$334,EDATE(DATE(YEAR(IF(COUNT(Inversiones!$F$30:$F$149)=0,'Configuración'!$C$8,MIN(Inversiones!$F$30:$F$149))),MONTH(IF(COUNT(Inversiones!$F$30:$F$149)=0,'Configuración'!$C$8,MIN(Inversiones!$F$30:$F$149))),1),18))=COUNTA(Inversiones!$B$30:$B$149),SUMIFS('Cálculos'!$J$278:$J$334,'Cálculos'!$B$278:$B$334,EDATE(DATE(YEAR(IF(COUNT(Inversiones!$F$30:$F$149)=0,'Configuración'!$C$8,MIN(Inversiones!$F$30:$F$149))),MONTH(IF(COUNT(Inversiones!$F$30:$F$149)=0,'Configuración'!$C$8,MIN(Inversiones!$F$30:$F$149))),1),18)),""),IF(SUMIFS('Cálculos'!$K$278:$K$334,'Cálculos'!$B$278:$B$334,EDATE(DATE(YEAR(IF(COUNT(Inversiones!$F$30:$F$149)=0,'Configuración'!$C$8,MIN(Inversiones!$F$30:$F$149))),MONTH(IF(COUNT(Inversiones!$F$30:$F$149)=0,'Configuración'!$C$8,MIN(Inversiones!$F$30:$F$149))),1),18),'Cálculos'!$C$278:$C$334,'Cálculos'!$I$4)=1,SUMIFS('Cálculos'!$J$278:$J$334,'Cálculos'!$B$278:$B$334,EDATE(DATE(YEAR(IF(COUNT(Inversiones!$F$30:$F$149)=0,'Configuración'!$C$8,MIN(Inversiones!$F$30:$F$149))),MONTH(IF(COUNT(Inversiones!$F$30:$F$149)=0,'Configuración'!$C$8,MIN(Inversiones!$F$30:$F$149))),1),18),'Cálculos'!$C$278:$C$334,'Cálculos'!$I$4),""))) | E946: =IF(COUNT(C946,D946)<2,"",D946-C946)

Sheet Cuentas
B2: Cuentas
B8: Cuenta | C8: Saldo inicial | D8: Saldo real | E8: Fecha saldo | F8: Saldo calculado | H8: ID | I8: Acreedor | J8: Saldo inicial | K8: Saldo pendiente
F9: =IF(B9="","",C9+SUMIFS(tMovimientos[Importe],tMovimientos[Destino],B9,tMovimientos[Fecha],">="&'Configuración'!$C$6,tMovimientos[Fecha],"<="&'Configuración'!$C$7)-SUMIFS(tMovimientos[Importe],tMovimientos[Origen],B9,tMovimientos[Fecha],">="&'Configuración'!$C$6,tMovimientos[Fecha],"<="&'Configuración'!$C$7)) | K9: =IF(H9="","",J9+SUMIFS(tVinculos[Importe],tVinculos[Vinculado a],H9,tVinculos[Tipo],"Préstamo recibido",tVinculos[Fecha],">="&'Configuración'!$C$6,tVinculos[Fecha],"<="&'Configuración'!$C$7)-SUMIFS(tVinculos[Importe],tVinculos[Vinculado a],H9,tVinculos[Tipo],"Devolución deuda",tVinculos[Fecha],">="&'Configuración'!$C$6,tVinculos[Fecha],"<="&'Configuración'!$C$7))
F10: =IF(B10="","",C10+SUMIFS(tMovimientos[Importe],tMovimientos[Destino],B10,tMovimientos[Fecha],">="&'Configuración'!$C$6,tMovimientos[Fecha],"<="&'Configuración'!$C$7)-SUMIFS(tMovimientos[Importe],tMovimientos[Origen],B10,tMovimientos[Fecha],">="&'Configuración'!$C$6,tMovimientos[Fecha],"<="&'Configuración'!$C$7)) | K10: =IF(H10="","",J10+SUMIFS(tVinculos[Importe],tVinculos[Vinculado a],H10,tVinculos[Tipo],"Préstamo recibido",tVinculos[Fecha],">="&'Configuración'!$C$6,tVinculos[Fecha],"<="&'Configuración'!$C$7)-SUMIFS(tVinculos[Importe],tVinculos[Vinculado a],H10,tVinculos[Tipo],"Devolución deuda",tVinculos[Fecha],">="&'Configuración'!$C$6,tVinculos[Fecha],"<="&'Configuración'!$C$7))
F11: =IF(B11="","",C11+SUMIFS(tMovimientos[Importe],tMovimientos[Destino],B11,tMovimientos[Fecha],">="&'Configuración'!$C$6,tMovimientos[Fecha],"<="&'Configuración'!$C$7)-SUMIFS(tMovimientos[Importe],tMovimientos[Origen],B11,tMovimientos[Fecha],">="&'Configuración'!$C$6,tMovimientos[Fecha],"<="&'Configuración'!$C$7)) | K11: =IF(H11="","",J11+SUMIFS(tVinculos[Importe],tVinculos[Vinculado a],H11,tVinculos[Tipo],"Préstamo recibido",tVinculos[Fecha],">="&'Configuración'!$C$6,tVinculos[Fecha],"<="&'Configuración'!$C$7)-SUMIFS(tVinculos[Importe],tVinculos[Vinculado a],H11,tVinculos[Tipo],"Devolución deuda",tVinculos[Fecha],">="&'Configuración'!$C$6,tVinculos[Fecha],"<="&'Configuración'!$C$7))
F12: =IF(B12="","",C12+SUMIFS(tMovimientos[Importe],tMovimientos[Destino],B12,tMovimientos[Fecha],">="&'Configuración'!$C$6,tMovimientos[Fecha],"<="&'Configuración'!$C$7)-SUMIFS(tMovimientos[Importe],tMovimientos[Origen],B12,tMovimientos[Fecha],">="&'Configuración'!$C$6,tMovimientos[Fecha],"<="&'Configuración'!$C$7)) | K12: =IF(H12="","",J12+SUMIFS(tVinculos[Importe],tVinculos[Vinculado a],H12,tVinculos[Tipo],"Préstamo recibido",tVinculos[Fecha],">="&'Configuración'!$C$6,tVinculos[Fecha],"<="&'Configuración'!$C$7)-SUMIFS(tVinculos[Importe],tVinculos[Vinculado a],H12,tVinculos[Tipo],"Devolución deuda",tVinculos[Fecha],">="&'Configuración'!$C$6,tVinculos[Fecha],"<="&'Configuración'!$C$7))
F13: =IF(B13="","",C13+SUMIFS(tMovimientos[Importe],tMovimientos[Destino],B13,tMovimientos[Fecha],">="&'Configuración'!$C$6,tMovimientos[Fecha],"<="&'Configuración'!$C$7)-SUMIFS(tMovimientos[Importe],tMovimientos[Origen],B13,tMovimientos[Fecha],">="&'Configuración'!$C$6,tMovimientos[Fecha],"<="&'Configuración'!$C$7)) | K13: =IF(H13="","",J13+SUMIFS(tVinculos[Importe],tVinculos[Vinculado a],H13,tVinculos[Tipo],"Préstamo recibido",tVinculos[Fecha],">="&'Configuración'!$C$6,tVinculos[Fecha],"<="&'Configuración'!$C$7)-SUMIFS(tVinculos[Importe],tVinculos[Vinculado a],H13,tVinculos[Tipo],"Devolución deuda",tVinculos[Fecha],">="&'Configuración'!$C$6,tVinculos[Fecha],"<="&'Configuración'!$C$7))
F14: =IF(B14="","",C14+SUMIFS(tMovimientos[Importe],tMovimientos[Destino],B14,tMovimientos[Fecha],">="&'Configuración'!$C$6,tMovimientos[Fecha],"<="&'Configuración'!$C$7)-SUMIFS(tMovimientos[Importe],tMovimientos[Origen],B14,tMovimientos[Fecha],">="&'Configuración'!$C$6,tMovimientos[Fecha],"<="&'Configuración'!$C$7)) | K14: =IF(H14="","",J14+SUMIFS(tVinculos[Importe],tVinculos[Vinculado a],H14,tVinculos[Tipo],"Préstamo recibido",tVinculos[Fecha],">="&'Configuración'!$C$6,tVinculos[Fecha],"<="&'Configuración'!$C$7)-SUMIFS(tVinculos[Importe],tVinculos[Vinculado a],H14,tVinculos[Tipo],"Devolución deuda",tVinculos[Fecha],">="&'Configuración'!$C$6,tVinculos[Fecha],"<="&'Configuración'!$C$7))
F15: =IF(B15="","",C15+SUMIFS(tMovimientos[Importe],tMovimientos[Destino],B15,tMovimientos[Fecha],">="&'Configuración'!$C$6,tMovimientos[Fecha],"<="&'Configuración'!$C$7)-SUMIFS(tMovimientos[Importe],tMovimientos[Origen],B15,tMovimientos[Fecha],">="&'Configuración'!$C$6,tMovimientos[Fecha],"<="&'Configuración'!$C$7)) | K15: =IF(H15="","",J15+SUMIFS(tVinculos[Importe],tVinculos[Vinculado a],H15,tVinculos[Tipo],"Préstamo recibido",tVinculos[Fecha],">="&'Configuración'!$C$6,tVinculos[Fecha],"<="&'Configuración'!$C$7)-SUMIFS(tVinculos[Importe],tVinculos[Vinculado a],H15,tVinculos[Tipo],"Devolución deuda",tVinculos[Fecha],">="&'Configuración'!$C$6,tVinculos[Fecha],"<="&'Configuración'!$C$7))
F16: =IF(B16="","",C16+SUMIFS(tMovimientos[Importe],tMovimientos[Destino],B16,tMovimientos[Fecha],">="&'Configuración'!$C$6,tMovimientos[Fecha],"<="&'Configuración'!$C$7)-SUMIFS(tMovimientos[Importe],tMovimientos[Origen],B16,tMovimientos[Fecha],">="&'Configuración'!$C$6,tMovimientos[Fecha],"<="&'Configuración'!$C$7)) | K16: =IF(H16="","",J16+SUMIFS(tVinculos[Importe],tVinculos[Vinculado a],H16,tVinculos[Tipo],"Préstamo recibido",tVinculos[Fecha],">="&'Configuración'!$C$6,tVinculos[Fecha],"<="&'Configuración'!$C$7)-SUMIFS(tVinculos[Importe],tVinculos[Vinculado a],H16,tVinculos[Tipo],"Devolución deuda",tVinculos[Fecha],">="&'Configuración'!$C$6,tVinculos[Fecha],"<="&'Configuración'!$C$7))
F17: =IF(B17="","",C17+SUMIFS(tMovimientos[Importe],tMovimientos[Destino],B17,tMovimientos[Fecha],">="&'Configuración'!$C$6,tMovimientos[Fecha],"<="&'Configuración'!$C$7)-SUMIFS(tMovimientos[Importe],tMovimientos[Origen],B17,tMovimientos[Fecha],">="&'Configuración'!$C$6,tMovimientos[Fecha],"<="&'Configuración'!$C$7)) | K17: =IF(H17="","",J17+SUMIFS(tVinculos[Importe],tVinculos[Vinculado a],H17,tVinculos[Tipo],"Préstamo recibido",tVinculos[Fecha],">="&'Configuración'!$C$6,tVinculos[Fecha],"<="&'Configuración'!$C$7)-SUMIFS(tVinculos[Importe],tVinculos[Vinculado a],H17,tVinculos[Tipo],"Devolución deuda",tVinculos[Fecha],">="&'Configuración'!$C$6,tVinculos[Fecha],"<="&'Configuración'!$C$7))
F18: =IF(B18="","",C18+SUMIFS(tMovimientos[Importe],tMovimientos[Destino],B18,tMovimientos[Fecha],">="&'Configuración'!$C$6,tMovimientos[Fecha],"<="&'Configuración'!$C$7)-SUMIFS(tMovimientos[Importe],tMovimientos[Origen],B18,tMovimientos[Fecha],">="&'Configuración'!$C$6,tMovimientos[Fecha],"<="&'Configuración'!$C$7)) | K18: =IF(H18="","",J18+SUMIFS(tVinculos[Importe],tVinculos[Vinculado a],H18,tVinculos[Tipo],"Préstamo recibido",tVinculos[Fecha],">="&'Configuración'!$C$6,tVinculos[Fecha],"<="&'Configuración'!$C$7)-SUMIFS(tVinculos[Importe],tVinculos[Vinculado a],H18,tVinculos[Tipo],"Devolución deuda",tVinculos[Fecha],">="&'Configuración'!$C$6,tVinculos[Fecha],"<="&'Configuración'!$C$7))
F19: =IF(B19="","",C19+SUMIFS(tMovimientos[Importe],tMovimientos[Destino],B19,tMovimientos[Fecha],">="&'Configuración'!$C$6,tMovimientos[Fecha],"<="&'Configuración'!$C$7)-SUMIFS(tMovimientos[Importe],tMovimientos[Origen],B19,tMovimientos[Fecha],">="&'Configuración'!$C$6,tMovimientos[Fecha],"<="&'Configuración'!$C$7)) | K19: =IF(H19="","",J19+SUMIFS(tVinculos[Importe],tVinculos[Vinculado a],H19,tVinculos[Tipo],"Préstamo recibido",tVinculos[Fecha],">="&'Configuración'!$C$6,tVinculos[Fecha],"<="&'Configuración'!$C$7)-SUMIFS(tVinculos[Importe],tVinculos[Vinculado a],H19,tVinculos[Tipo],"Devolución deuda",tVinculos[Fecha],">="&'Configuración'!$C$6,tVinculos[Fecha],"<="&'Configuración'!$C$7))
F20: =IF(B20="","",C20+SUMIFS(tMovimientos[Importe],tMovimientos[Destino],B20,tMovimientos[Fecha],">="&'Configuración'!$C$6,tMovimientos[Fecha],"<="&'Configuración'!$C$7)-SUMIFS(tMovimientos[Importe],tMovimientos[Origen],B20,tMovimientos[Fecha],">="&'Configuración'!$C$6,tMovimientos[Fecha],"<="&'Configuración'!$C$7)) | K20: =IF(H20="","",J20+SUMIFS(tVinculos[Importe],tVinculos[Vinculado a],H20,tVinculos[Tipo],"Préstamo recibido",tVinculos[Fecha],">="&'Configuración'!$C$6,tVinculos[Fecha],"<="&'Configuración'!$C$7)-SUMIFS(tVinculos[Importe],tVinculos[Vinculado a],H20,tVinculos[Tipo],"Devolución deuda",tVinculos[Fecha],">="&'Configuración'!$C$6,tVinculos[Fecha],"<="&'Configuración'!$C$7))
... F128: =IF(B128="","",C128+SUMIFS(tMovimientos[Importe],tMovimientos[Destino],B128,tMovimientos[Fecha],">="&'Configuración'!$C$6,tMovimientos[Fecha],"<="&'Configuración'!$C$7)-SUMIFS(tMovimientos[Importe],tMovimientos[Origen],B128,tMovimientos[Fecha],">="&'Configuración'!$C$6,tMovimientos[Fecha],"<="&'Configuración'!$C$7)) | K128: =IF(H128="","",J128+SUMIFS(tVinculos[Importe],tVinculos[Vinculado a],H128,tVinculos[Tipo],"Préstamo recibido",tVinculos[Fecha],">="&'Configuración'!$C$6,tVinculos[Fecha],"<="&'Configuración'!$C$7)-SUMIFS(tVinculos[Importe],tVinculos[Vinculado a],H128,tVinculos[Tipo],"Devolución deuda",tVinculos[Fecha],">="&'Configuración'!$C$6,tVinculos[Fecha],"<="&'Configuración'!$C$7))
B132: Relaciones
B134: Movimiento | C134: Vinculado a | D134: Fecha | E134: Tipo | F134: Importe
D135: =IF(B135="","",SUMIFS(tMovimientos[Fecha],tMovimientos[ID],B135)) | E135: {=IF(B135="","",INDEX(tMovimientos[Tipo],MATCH(B135,tMovimientos[ID],0)))} | F135: =IF(B135="","",SUMIFS(tMovimientos[Importe],tMovimientos[ID],B135))
D136: =IF(B136="","",SUMIFS(tMovimientos[Fecha],tMovimientos[ID],B136)) | E136: {=IF(B136="","",INDEX(tMovimientos[Tipo],MATCH(B136,tMovimientos[ID],0)))} | F136: =IF(B136="","",SUMIFS(tMovimientos[Importe],tMovimientos[ID],B136))
D137: =IF(B137="","",SUMIFS(tMovimientos[Fecha],tMovimientos[ID],B137)) | E137: {=IF(B137="","",INDEX(tMovimientos[Tipo],MATCH(B137,tMovimientos[ID],0)))} | F137: =IF(B137="","",SUMIFS(tMovimientos[Importe],tMovimientos[ID],B137))
D138: =IF(B138="","",SUMIFS(tMovimientos[Fecha],tMovimientos[ID],B138)) | E138: {=IF(B138="","",INDEX(tMovimientos[Tipo],MATCH(B138,tMovimientos[ID],0)))} | F138: =IF(B138="","",SUMIFS(tMovimientos[Importe],tMovimientos[ID],B138))
D139: =IF(B139="","",SUMIFS(tMovimientos[Fecha],tMovimientos[ID],B139)) | E139: {=IF(B139="","",INDEX(tMovimientos[Tipo],MATCH(B139,tMovimientos[ID],0)))} | F139: =IF(B139="","",SUMIFS(tMovimientos[Importe],tMovimientos[ID],B139))
D140: =IF(B140="","",SUMIFS(tMovimientos[Fecha],tMovimientos[ID],B140)) | E140: {=IF(B140="","",INDEX(tMovimientos[Tipo],MATCH(B140,tMovimientos[ID],0)))} | F140: =IF(B140="","",SUMIFS(tMovimientos[Importe],tMovimientos[ID],B140))
D141: =IF(B141="","",SUMIFS(tMovimientos[Fecha],tMovimientos[ID],B141)) | E141: {=IF(B141="","",INDEX(tMovimientos[Tipo],MATCH(B141,tMovimientos[ID],0)))} | F141: =IF(B141="","",SUMIFS(tMovimientos[Importe],tMovimientos[ID],B141))
D142: =IF(B142="","",SUMIFS(tMovimientos[Fecha],tMovimientos[ID],B142)) | E142: {=IF(B142="","",INDEX(tMovimientos[Tipo],MATCH(B142,tMovimientos[ID],0)))} | F142: =IF(B142="","",SUMIFS(tMovimientos[Importe],tMovimientos[ID],B142))
D143: =IF(B143="","",SUMIFS(tMovimientos[Fecha],tMovimientos[ID],B143)) | E143: {=IF(B143="","",INDEX(tMovimientos[Tipo],MATCH(B143,tMovimientos[ID],0)))} | F143: =IF(B143="","",SUMIFS(tMovimientos[Importe],tMovimientos[ID],B143))
D144: =IF(B144="","",SUMIFS(tMovimientos[Fecha],tMovimientos[ID],B144)) | E144: {=IF(B144="","",INDEX(tMovimientos[Tipo],MATCH(B144,tMovimientos[ID],0)))} | F144: =IF(B144="","",SUMIFS(tMovimientos[Importe],tMovimientos[ID],B144))
D145: =IF(B145="","",SUMIFS(tMovimientos[Fecha],tMovimientos[ID],B145)) | E145: {=IF(B145="","",INDEX(tMovimientos[Tipo],MATCH(B145,tMovimientos[ID],0)))} | F145: =IF(B145="","",SUMIFS(tMovimientos[Importe],tMovimientos[ID],B145))
D146: =IF(B146="","",SUMIFS(tMovimientos[Fecha],tMovimientos[ID],B146)) | E146: {=IF(B146="","",INDEX(tMovimientos[Tipo],MATCH(B146,tMovimientos[ID],0)))} | F146: =IF(B146="","",SUMIFS(tMovimientos[Importe],tMovimientos[ID],B146))
... D254: =IF(B254="","",SUMIFS(tMovimientos[Fecha],tMovimientos[ID],B254)) | E254: {=IF(B254="","",INDEX(tMovimientos[Tipo],MATCH(B254,tMovimientos[ID],0)))} | F254: =IF(B254="","",SUMIFS(tMovimientos[Importe],tMovimientos[ID],B254))

Sheet Salario
B2: Salario
B8: Movimiento | C8: Fecha cobro | D8: Neto | E8: Bruto | F8: Cotización | G8: IRPF | H8: Otras deducciones
C9: =IF(B9="","",SUMIFS(tMovimientos[Fecha],tMovimientos[ID],B9)) | D9: =IF(B9="","",SUMIFS(tMovimientos[Importe],tMovimientos[ID],B9))
C10: =IF(B10="","",SUMIFS(tMovimientos[Fecha],tMovimientos[ID],B10)) | D10: =IF(B10="","",SUMIFS(tMovimientos[Importe],tMovimientos[ID],B10))
C11: =IF(B11="","",SUMIFS(tMovimientos[Fecha],tMovimientos[ID],B11)) | D11: =IF(B11="","",SUMIFS(tMovimientos[Importe],tMovimientos[ID],B11))
C12: =IF(B12="","",SUMIFS(tMovimientos[Fecha],tMovimientos[ID],B12)) | D12: =IF(B12="","",SUMIFS(tMovimientos[Importe],tMovimientos[ID],B12))
C13: =IF(B13="","",SUMIFS(tMovimientos[Fecha],tMovimientos[ID],B13)) | D13: =IF(B13="","",SUMIFS(tMovimientos[Importe],tMovimientos[ID],B13))
C14: =IF(B14="","",SUMIFS(tMovimientos[Fecha],tMovimientos[ID],B14)) | D14: =IF(B14="","",SUMIFS(tMovimientos[Importe],tMovimientos[ID],B14))
C15: =IF(B15="","",SUMIFS(tMovimientos[Fecha],tMovimientos[ID],B15)) | D15: =IF(B15="","",SUMIFS(tMovimientos[Importe],tMovimientos[ID],B15))
C16: =IF(B16="","",SUMIFS(tMovimientos[Fecha],tMovimientos[ID],B16)) | D16: =IF(B16="","",SUMIFS(tMovimientos[Importe],tMovimientos[ID],B16))
C17: =IF(B17="","",SUMIFS(tMovimientos[Fecha],tMovimientos[ID],B17)) | D17: =IF(B17="","",SUMIFS(tMovimientos[Importe],tMovimientos[ID],B17))
C18: =IF(B18="","",SUMIFS(tMovimientos[Fecha],tMovimientos[ID],B18)) | D18: =IF(B18="","",SUMIFS(tMovimientos[Importe],tMovimientos[ID],B18))
C19: =IF(B19="","",SUMIFS(tMovimientos[Fecha],tMovimientos[ID],B19)) | D19: =IF(B19="","",SUMIFS(tMovimientos[Importe],tMovimientos[ID],B19))
C20: =IF(B20="","",SUMIFS(tMovimientos[Fecha],tMovimientos[ID],B20)) | D20: =IF(B20="","",SUMIFS(tMovimientos[Importe],tMovimientos[ID],B20))
... C128: =IF(B128="","",SUMIFS(tMovimientos[Fecha],tMovimientos[ID],B128)) | D128: =IF(B128="","",SUMIFS(tMovimientos[Importe],tMovimientos[ID],B128))

Sheet Objetivos
B2: Objetivos
B8: ID | C8: Objetivo | D8: Meta | E8: Fecha | F8: Asignado | G8: Pendiente | H8: Avance
F9: =IF(B9="","",SUMIFS(tAsignaciones[Importe],tAsignaciones[Objetivo],B9)) | G9: =IF(B9="","",MAX(0,D9-F9)) | H9: =IF(OR(B9="",D9=0),"",F9/D9)
F10: =IF(B10="","",SUMIFS(tAsignaciones[Importe],tAsignaciones[Objetivo],B10)) | G10: =IF(B10="","",MAX(0,D10-F10)) | H10: =IF(OR(B10="",D10=0),"",F10/D10)
F11: =IF(B11="","",SUMIFS(tAsignaciones[Importe],tAsignaciones[Objetivo],B11)) | G11: =IF(B11="","",MAX(0,D11-F11)) | H11: =IF(OR(B11="",D11=0),"",F11/D11)
F12: =IF(B12="","",SUMIFS(tAsignaciones[Importe],tAsignaciones[Objetivo],B12)) | G12: =IF(B12="","",MAX(0,D12-F12)) | H12: =IF(OR(B12="",D12=0),"",F12/D12)
F13: =IF(B13="","",SUMIFS(tAsignaciones[Importe],tAsignaciones[Objetivo],B13)) | G13: =IF(B13="","",MAX(0,D13-F13)) | H13: =IF(OR(B13="",D13=0),"",F13/D13)
F14: =IF(B14="","",SUMIFS(tAsignaciones[Importe],tAsignaciones[Objetivo],B14)) | G14: =IF(B14="","",MAX(0,D14-F14)) | H14: =IF(OR(B14="",D14=0),"",F14/D14)
F15: =IF(B15="","",SUMIFS(tAsignaciones[Importe],tAsignaciones[Objetivo],B15)) | G15: =IF(B15="","",MAX(0,D15-F15)) | H15: =IF(OR(B15="",D15=0),"",F15/D15)
F16: =IF(B16="","",SUMIFS(tAsignaciones[Importe],tAsignaciones[Objetivo],B16)) | G16: =IF(B16="","",MAX(0,D16-F16)) | H16: =IF(OR(B16="",D16=0),"",F16/D16)
F17: =IF(B17="","",SUMIFS(tAsignaciones[Importe],tAsignaciones[Objetivo],B17)) | G17: =IF(B17="","",MAX(0,D17-F17)) | H17: =IF(OR(B17="",D17=0),"",F17/D17)
F18: =IF(B18="","",SUMIFS(tAsignaciones[Importe],tAsignaciones[Objetivo],B18)) | G18: =IF(B18="","",MAX(0,D18-F18)) | H18: =IF(OR(B18="",D18=0),"",F18/D18)
F19: =IF(B19="","",SUMIFS(tAsignaciones[Importe],tAsignaciones[Objetivo],B19)) | G19: =IF(B19="","",MAX(0,D19-F19)) | H19: =IF(OR(B19="",D19=0),"",F19/D19)
F20: =IF(B20="","",SUMIFS(tAsignaciones[Importe],tAsignaciones[Objetivo],B20)) | G20: =IF(B20="","",MAX(0,D20-F20)) | H20: =IF(OR(B20="",D20=0),"",F20/D20)
... F113: =IF(B113="","",SUMIFS(tAsignaciones[Importe],tAsignaciones[Objetivo],B113)) | G113: =IF(B113="","",MAX(0,D113-F113)) | H113: =IF(OR(B113="",D113=0),"",F113/D113)
B117: Asignaciones
B119: Objetivo | C119: Origen | D119: Importe

Sheet Inflación
B2: Interés compuesto
B6: Capital inicial | H6: Aportado | J6: =IF(COUNT(E6:E10)<5,"",E6+E7*E9*12)
B7: Aportación mensual | H7: Capital final | J7: =IF(COUNT(E6:E10)<5,"",IF('Cálculos'!J4=0,E6+E7*E9*12,E6*(1+'Cálculos'!J4)^(E9*12)+E7*((1+'Cálculos'!J4)^(E9*12)-1)/'Cálculos'!J4))
B8: Rentabilidad anual | H8: En euros de hoy | J8: =IF(COUNT(J7)=0,"",J7/(1+E10)^E9)
B9: Años | H9: Rendimiento | J9: =IF(COUNT(J7)=0,"",J7-J6)
B10: Inflación anual
B16: Año | C16: Aportado | D16: Capital | E16: Capital real
B17: 1 | C17: =IF(OR(COUNT($E$6:$E$10)<5,B17>$E$9),"",$E$6+$E$7*B17*12) | D17: =IF(COUNT(C17)=0,"",IF('Cálculos'!$J$4=0,C17,$E$6*(1+'Cálculos'!$J$4)^(B17*12)+$E$7*((1+'Cálculos'!$J$4)^(B17*12)-1)/'Cálculos'!$J$4)) | E17: =IF(COUNT(D17)=0,"",D17/(1+$E$10)^B17)
B18: 2 | C18: =IF(OR(COUNT($E$6:$E$10)<5,B18>$E$9),"",$E$6+$E$7*B18*12) | D18: =IF(COUNT(C18)=0,"",IF('Cálculos'!$J$4=0,C18,$E$6*(1+'Cálculos'!$J$4)^(B18*12)+$E$7*((1+'Cálculos'!$J$4)^(B18*12)-1)/'Cálculos'!$J$4)) | E18: =IF(COUNT(D18)=0,"",D18/(1+$E$10)^B18)
B19: 3 | C19: =IF(OR(COUNT($E$6:$E$10)<5,B19>$E$9),"",$E$6+$E$7*B19*12) | D19: =IF(COUNT(C19)=0,"",IF('Cálculos'!$J$4=0,C19,$E$6*(1+'Cálculos'!$J$4)^(B19*12)+$E$7*((1+'Cálculos'!$J$4)^(B19*12)-1)/'Cálculos'!$J$4)) | E19: =IF(COUNT(D19)=0,"",D19/(1+$E$10)^B19)
B20: 4 | C20: =IF(OR(COUNT($E$6:$E$10)<5,B20>$E$9),"",$E$6+$E$7*B20*12) | D20: =IF(COUNT(C20)=0,"",IF('Cálculos'!$J$4=0,C20,$E$6*(1+'Cálculos'!$J$4)^(B20*12)+$E$7*((1+'Cálculos'!$J$4)^(B20*12)-1)/'Cálculos'!$J$4)) | E20: =IF(COUNT(D20)=0,"",D20/(1+$E$10)^B20)
B21: 5 | C21: =IF(OR(COUNT($E$6:$E$10)<5,B21>$E$9),"",$E$6+$E$7*B21*12) | D21: =IF(COUNT(C21)=0,"",IF('Cálculos'!$J$4=0,C21,$E$6*(1+'Cálculos'!$J$4)^(B21*12)+$E$7*((1+'Cálculos'!$J$4)^(B21*12)-1)/'Cálculos'!$J$4)) | E21: =IF(COUNT(D21)=0,"",D21/(1+$E$10)^B21)
B22: 6 | C22: =IF(OR(COUNT($E$6:$E$10)<5,B22>$E$9),"",$E$6+$E$7*B22*12) | D22: =IF(COUNT(C22)=0,"",IF('Cálculos'!$J$4=0,C22,$E$6*(1+'Cálculos'!$J$4)^(B22*12)+$E$7*((1+'Cálculos'!$J$4)^(B22*12)-1)/'Cálculos'!$J$4)) | E22: =IF(COUNT(D22)=0,"",D22/(1+$E$10)^B22)
B23: 7 | C23: =IF(OR(COUNT($E$6:$E$10)<5,B23>$E$9),"",$E$6+$E$7*B23*12) | D23: =IF(COUNT(C23)=0,"",IF('Cálculos'!$J$4=0,C23,$E$6*(1+'Cálculos'!$J$4)^(B23*12)+$E$7*((1+'Cálculos'!$J$4)^(B23*12)-1)/'Cálculos'!$J$4)) | E23: =IF(COUNT(D23)=0,"",D23/(1+$E$10)^B23)
B24: 8 | C24: =IF(OR(COUNT($E$6:$E$10)<5,B24>$E$9),"",$E$6+$E$7*B24*12) | D24: =IF(COUNT(C24)=0,"",IF('Cálculos'!$J$4=0,C24,$E$6*(1+'Cálculos'!$J$4)^(B24*12)+$E$7*((1+'Cálculos'!$J$4)^(B24*12)-1)/'Cálculos'!$J$4)) | E24: =IF(COUNT(D24)=0,"",D24/(1+$E$10)^B24)
B25: 9 | C25: =IF(OR(COUNT($E$6:$E$10)<5,B25>$E$9),"",$E$6+$E$7*B25*12) | D25: =IF(COUNT(C25)=0,"",IF('Cálculos'!$J$4=0,C25,$E$6*(1+'Cálculos'!$J$4)^(B25*12)+$E$7*((1+'Cálculos'!$J$4)^(B25*12)-1)/'Cálculos'!$J$4)) | E25: =IF(COUNT(D25)=0,"",D25/(1+$E$10)^B25)
B26: 10 | C26: =IF(OR(COUNT($E$6:$E$10)<5,B26>$E$9),"",$E$6+$E$7*B26*12) | D26: =IF(COUNT(C26)=0,"",IF('Cálculos'!$J$4=0,C26,$E$6*(1+'Cálculos'!$J$4)^(B26*12)+$E$7*((1+'Cálculos'!$J$4)^(B26*12)-1)/'Cálculos'!$J$4)) | E26: =IF(COUNT(D26)=0,"",D26/(1+$E$10)^B26)
B27: 11 | C27: =IF(OR(COUNT($E$6:$E$10)<5,B27>$E$9),"",$E$6+$E$7*B27*12) | D27: =IF(COUNT(C27)=0,"",IF('Cálculos'!$J$4=0,C27,$E$6*(1+'Cálculos'!$J$4)^(B27*12)+$E$7*((1+'Cálculos'!$J$4)^(B27*12)-1)/'Cálculos'!$J$4)) | E27: =IF(COUNT(D27)=0,"",D27/(1+$E$10)^B27)
B28: 12 | C28: =IF(OR(COUNT($E$6:$E$10)<5,B28>$E$9),"",$E$6+$E$7*B28*12) | D28: =IF(COUNT(C28)=0,"",IF('Cálculos'!$J$4=0,C28,$E$6*(1+'Cálculos'!$J$4)^(B28*12)+$E$7*((1+'Cálculos'!$J$4)^(B28*12)-1)/'Cálculos'!$J$4)) | E28: =IF(COUNT(D28)=0,"",D28/(1+$E$10)^B28)
... B46: 30 | C46: =IF(OR(COUNT($E$6:$E$10)<5,B46>$E$9),"",$E$6+$E$7*B46*12) | D46: =IF(COUNT(C46)=0,"",IF('Cálculos'!$J$4=0,C46,$E$6*(1+'Cálculos'!$J$4)^(B46*12)+$E$7*((1+'Cálculos'!$J$4)^(B46*12)-1)/'Cálculos'!$J$4)) | E46: =IF(COUNT(D46)=0,"",D46/(1+$E$10)^B46)

Sheet Hipoteca
B2: Hipoteca
B6: Precio de vivienda | H6: Capital financiado | J6: =IF(COUNT(E6:E10)<5,"",E6-E7)
B7: Entrada | H7: Cuota mensual | J7: =IF(COUNT(J6)=0,"",IF(E9=0,J6/(E8*12),-PMT(E9/12,E8*12,J6)))
B8: Plazo en años | H8: Intereses totales | J8: =IF(COUNT(J7)=0,"",J7*E8*12-J6)
B9: TIN anual fijo | H9: Dinero inicial | J9: =IF(COUNT(J7)=0,"",E7+E10)
B10: Gastos de compra
B16: Año | C16: Capital pendiente | D16: Capital amortizado | E16: Intereses acumulados
B17: 1 | C17: =IF(OR(COUNT($J$6)=0,B17>$E$8),"",MAX(0,IF($E$9=0,$J$6-$J$7*B17*12,$J$6*(1+$E$9/12)^(B17*12)-$J$7*((1+$E$9/12)^(B17*12)-1)/($E$9/12)))) | D17: =IF(COUNT(C17)=0,"",$J$6-C17) | E17: =IF(COUNT(C17)=0,"",$J$7*B17*12-D17)
B18: 2 | C18: =IF(OR(COUNT($J$6)=0,B18>$E$8),"",MAX(0,IF($E$9=0,$J$6-$J$7*B18*12,$J$6*(1+$E$9/12)^(B18*12)-$J$7*((1+$E$9/12)^(B18*12)-1)/($E$9/12)))) | D18: =IF(COUNT(C18)=0,"",$J$6-C18) | E18: =IF(COUNT(C18)=0,"",$J$7*B18*12-D18)
B19: 3 | C19: =IF(OR(COUNT($J$6)=0,B19>$E$8),"",MAX(0,IF($E$9=0,$J$6-$J$7*B19*12,$J$6*(1+$E$9/12)^(B19*12)-$J$7*((1+$E$9/12)^(B19*12)-1)/($E$9/12)))) | D19: =IF(COUNT(C19)=0,"",$J$6-C19) | E19: =IF(COUNT(C19)=0,"",$J$7*B19*12-D19)
B20: 4 | C20: =IF(OR(COUNT($J$6)=0,B20>$E$8),"",MAX(0,IF($E$9=0,$J$6-$J$7*B20*12,$J$6*(1+$E$9/12)^(B20*12)-$J$7*((1+$E$9/12)^(B20*12)-1)/($E$9/12)))) | D20: =IF(COUNT(C20)=0,"",$J$6-C20) | E20: =IF(COUNT(C20)=0,"",$J$7*B20*12-D20)
B21: 5 | C21: =IF(OR(COUNT($J$6)=0,B21>$E$8),"",MAX(0,IF($E$9=0,$J$6-$J$7*B21*12,$J$6*(1+$E$9/12)^(B21*12)-$J$7*((1+$E$9/12)^(B21*12)-1)/($E$9/12)))) | D21: =IF(COUNT(C21)=0,"",$J$6-C21) | E21: =IF(COUNT(C21)=0,"",$J$7*B21*12-D21)
B22: 6 | C22: =IF(OR(COUNT($J$6)=0,B22>$E$8),"",MAX(0,IF($E$9=0,$J$6-$J$7*B22*12,$J$6*(1+$E$9/12)^(B22*12)-$J$7*((1+$E$9/12)^(B22*12)-1)/($E$9/12)))) | D22: =IF(COUNT(C22)=0,"",$J$6-C22) | E22: =IF(COUNT(C22)=0,"",$J$7*B22*12-D22)
B23: 7 | C23: =IF(OR(COUNT($J$6)=0,B23>$E$8),"",MAX(0,IF($E$9=0,$J$6-$J$7*B23*12,$J$6*(1+$E$9/12)^(B23*12)-$J$7*((1+$E$9/12)^(B23*12)-1)/($E$9/12)))) | D23: =IF(COUNT(C23)=0,"",$J$6-C23) | E23: =IF(COUNT(C23)=0,"",$J$7*B23*12-D23)
B24: 8 | C24: =IF(OR(COUNT($J$6)=0,B24>$E$8),"",MAX(0,IF($E$9=0,$J$6-$J$7*B24*12,$J$6*(1+$E$9/12)^(B24*12)-$J$7*((1+$E$9/12)^(B24*12)-1)/($E$9/12)))) | D24: =IF(COUNT(C24)=0,"",$J$6-C24) | E24: =IF(COUNT(C24)=0,"",$J$7*B24*12-D24)
B25: 9 | C25: =IF(OR(COUNT($J$6)=0,B25>$E$8),"",MAX(0,IF($E$9=0,$J$6-$J$7*B25*12,$J$6*(1+$E$9/12)^(B25*12)-$J$7*((1+$E$9/12)^(B25*12)-1)/($E$9/12)))) | D25: =IF(COUNT(C25)=0,"",$J$6-C25) | E25: =IF(COUNT(C25)=0,"",$J$7*B25*12-D25)
B26: 10 | C26: =IF(OR(COUNT($J$6)=0,B26>$E$8),"",MAX(0,IF($E$9=0,$J$6-$J$7*B26*12,$J$6*(1+$E$9/12)^(B26*12)-$J$7*((1+$E$9/12)^(B26*12)-1)/($E$9/12)))) | D26: =IF(COUNT(C26)=0,"",$J$6-C26) | E26: =IF(COUNT(C26)=0,"",$J$7*B26*12-D26)
B27: 11 | C27: =IF(OR(COUNT($J$6)=0,B27>$E$8),"",MAX(0,IF($E$9=0,$J$6-$J$7*B27*12,$J$6*(1+$E$9/12)^(B27*12)-$J$7*((1+$E$9/12)^(B27*12)-1)/($E$9/12)))) | D27: =IF(COUNT(C27)=0,"",$J$6-C27) | E27: =IF(COUNT(C27)=0,"",$J$7*B27*12-D27)
B28: 12 | C28: =IF(OR(COUNT($J$6)=0,B28>$E$8),"",MAX(0,IF($E$9=0,$J$6-$J$7*B28*12,$J$6*(1+$E$9/12)^(B28*12)-$J$7*((1+$E$9/12)^(B28*12)-1)/($E$9/12)))) | D28: =IF(COUNT(C28)=0,"",$J$6-C28) | E28: =IF(COUNT(C28)=0,"",$J$7*B28*12-D28)
... B46: 30 | C46: =IF(OR(COUNT($J$6)=0,B46>$E$8),"",MAX(0,IF($E$9=0,$J$6-$J$7*B46*12,$J$6*(1+$E$9/12)^(B46*12)-$J$7*((1+$E$9/12)^(B46*12)-1)/($E$9/12)))) | D46: =IF(COUNT(C46)=0,"",$J$6-C46) | E46: =IF(COUNT(C46)=0,"",$J$7*B46*12-D46)

Sheet Configuración
B2: Configuración
B5: Parámetro | C5: Valor
B6: Inicio seguimiento | C6: 46023
B7: Fecha informe | C7: 46023
B8: Valoración inversiones | C8: 46023
B9: Moneda | C9: EUR
B10: Versión modelo | C10: 3
B14: Grupo | C14: Subgrupo | D14: Categoría | E14: Subcategoría | G14: Tipos de movimiento
G15: Ingreso
G16: Gasto
G17: Transferencia
G18: Compra inversión
G19: Venta inversión
G20: Rendimiento inversión
G21: Préstamo recibido
G22: Devolución deuda
G23: Cobro compartido
G24: Devolución gasto
G28: Clases de activo
G29: Renta variable
... G134: Otros

Sheet Cálculos
B2: Cálculos
C4: {=IF('Resumen financiero'!I4="Todo el año",DATE('Resumen financiero'!E4,1,1),DATE('Resumen financiero'!E4,MATCH('Resumen financiero'!I4,{"Enero","Febrero","Marzo","Abril","Mayo","Junio","Julio","Agosto","Septiembre","Octubre","Noviembre","Diciembre"},0),1))} -> 46023 | D4: =MIN(IF('Resumen financiero'!I4="Todo el año",DATE('Resumen financiero'!E4+1,1,1),EDATE(C4,1)),'Configuración'!$C$7+1) -> 46024 | E4: =IF('Resumen financiero'!Q4="Todas",SUMIFS('Cálculos'!$K$9:$K$128,'Cálculos'!$C$9:$C$128,">="&C4,'Cálculos'!$C$9:$C$128,"<"&D4),SUMIFS('Cálculos'!$K$9:$K$128,'Cálculos'!$C$9:$C$128,">="&C4,'Cálculos'!$C$9:$C$128,"<"&D4,'Cálculos'!$N$9:$N$128,'Resumen financiero'!Q4)) -> 0 | F4: =IF('Resumen financiero'!Q4="Todas",SUMIFS('Cálculos'!$L$9:$L$128,'Cálculos'!$C$9:$C$128,">="&C4,'Cálculos'!$C$9:$C$128,"<"&D4),SUMIFS('Cálculos'!$L$9:$L$128,'Cálculos'!$C$9:$C$128,">="&C4,'Cálculos'!$C$9:$C$128,"<"&D4,'Cálculos'!$N$9:$N$128,'Resumen financiero'!Q4)) -> 0 | G4: =E4-F4 -> 0 | H4: =IF(E4=0,"",G4/E4) | I4: {=IF(Inversiones!D4="Todos","",INDEX(tProductos[ID],MATCH(Inversiones!D4,tProductos[Producto],0)))} | J4: =IF(COUNT('Inflación'!E6:E10)<5,"",(1+'Inflación'!E8)^(1/12)-1)
C5: =SUMIFS('Cálculos'!$M$9:$M$128,'Cálculos'!$C$9:$C$128,">="&'Configuración'!$C$6,'Cálculos'!$C$9:$C$128,"<="&'Configuración'!$C$7) -> 0 | D5: =IF(COUNT(tProductos[Valor])<>COUNTA(tProductos[ID]),"",SUM(tProductos[Valor])) -> 0
B8: ID | C8: Fecha | D8: Tipo | E8: Subcategoría | F8: Categoría | G8: Origen | H8: Destino | I8: Importe | J8: Recuperable | K8: Ingresos | L8: Gasto propio | M8: Recuperable pendiente | N8: Cuenta | P8: Cuentas selector | Q8: Productos selector
B9: =IF(OR(Movimientos!B9="",Movimientos!B9=""),"",Movimientos!B9) | C9: =IF(OR(Movimientos!B9="",Movimientos!C9=""),"",Movimientos!C9) | D9: =IF(OR(Movimientos!B9="",Movimientos!D9=""),"",Movimientos!D9) | E9: =IF(OR(Movimientos!B9="",Movimientos!F9=""),"",Movimientos!F9) | F9: {=IF(E9="","",INDEX('Configuración'!$D$15:$D$134,MATCH(E9,'Configuración'!$E$15:$E$134,0)))} | G9: =IF(OR(Movimientos!B9="",Movimientos!G9=""),"",Movimientos!G9) | H9: =IF(OR(Movimientos!B9="",Movimientos!H9=""),"",Movimientos!H9) | I9: =IF(OR(Movimientos!B9="",Movimientos!I9=""),"",Movimientos!I9) | J9: =IF(OR(Movimientos!B9="",Movimientos!J9=""),"",Movimientos!J9) | K9: =IF(B9="","",IF(OR(D9="Ingreso",D9="Rendimiento inversión"),I9,0)) | L9: =IF(B9="","",IF(D9="Gasto",I9-J9,IF(D9="Devolución gasto",-I9+J9,0))) | M9: =IF(B9="","",IF(D9="Gasto",J9,IF(D9="Cobro compartido",-I9,IF(D9="Devolución gasto",-J9,0)))) | N9: =IF(B9="","",IF(G9<>"",G9,H9)) | P9: Todas | Q9: Todos | T9: ="Todas" -> Todas | U9: ="Todos" -> Todos
B10: =IF(OR(Movimientos!B10="",Movimientos!B10=""),"",Movimientos!B10) | C10: =IF(OR(Movimientos!B10="",Movimientos!C10=""),"",Movimientos!C10) | D10: =IF(OR(Movimientos!B10="",Movimientos!D10=""),"",Movimientos!D10) | E10: =IF(OR(Movimientos!B10="",Movimientos!F10=""),"",Movimientos!F10) | F10: {=IF(E10="","",INDEX('Configuración'!$D$15:$D$134,MATCH(E10,'Configuración'!$E$15:$E$134,0)))} | G10: =IF(OR(Movimientos!B10="",Movimientos!G10=""),"",Movimientos!G10) | H10: =IF(OR(Movimientos!B10="",Movimientos!H10=""),"",Movimientos!H10) | I10: =IF(OR(Movimientos!B10="",Movimientos!I10=""),"",Movimientos!I10) | J10: =IF(OR(Movimientos!B10="",Movimientos!J10=""),"",Movimientos!J10) | K10: =IF(B10="","",IF(OR(D10="Ingreso",D10="Rendimiento inversión"),I10,0)) | L10: =IF(B10="","",IF(D10="Gasto",I10-J10,IF(D10="Devolución gasto",-I10+J10,0))) | M10: =IF(B10="","",IF(D10="Gasto",J10,IF(D10="Cobro compartido",-I10,IF(D10="Devolución gasto",-J10,0)))) | N10: =IF(B10="","",IF(G10<>"",G10,H10)) | T10: =IFERROR(__xludf.DUMMYFUNCTION("IFERROR(FILTER(Cuentas!$B$9:$B$128,Cuentas!$B$9:$B$128<>""""),"""")"),"") | U10: =IFERROR(__xludf.DUMMYFUNCTION("IFERROR(FILTER(Inversiones!$C$30:$C$149,Inversiones!$B$30:$B$149<>""""),"""")"),"")
B11: =IF(OR(Movimientos!B11="",Movimientos!B11=""),"",Movimientos!B11) | C11: =IF(OR(Movimientos!B11="",Movimientos!C11=""),"",Movimientos!C11) | D11: =IF(OR(Movimientos!B11="",Movimientos!D11=""),"",Movimientos!D11) | E11: =IF(OR(Movimientos!B11="",Movimientos!F11=""),"",Movimientos!F11) | F11: {=IF(E11="","",INDEX('Configuración'!$D$15:$D$134,MATCH(E11,'Configuración'!$E$15:$E$134,0)))} | G11: =IF(OR(Movimientos!B11="",Movimientos!G11=""),"",Movimientos!G11) | H11: =IF(OR(Movimientos!B11="",Movimientos!H11=""),"",Movimientos!H11) | I11: =IF(OR(Movimientos!B11="",Movimientos!I11=""),"",Movimientos!I11) | J11: =IF(OR(Movimientos!B11="",Movimientos!J11=""),"",Movimientos!J11) | K11: =IF(B11="","",IF(OR(D11="Ingreso",D11="Rendimiento inversión"),I11,0)) | L11: =IF(B11="","",IF(D11="Gasto",I11-J11,IF(D11="Devolución gasto",-I11+J11,0))) | M11: =IF(B11="","",IF(D11="Gasto",J11,IF(D11="Cobro compartido",-I11,IF(D11="Devolución gasto",-J11,0)))) | N11: =IF(B11="","",IF(G11<>"",G11,H11))
B12: =IF(OR(Movimientos!B12="",Movimientos!B12=""),"",Movimientos!B12) | C12: =IF(OR(Movimientos!B12="",Movimientos!C12=""),"",Movimientos!C12) | D12: =IF(OR(Movimientos!B12="",Movimientos!D12=""),"",Movimientos!D12) | E12: =IF(OR(Movimientos!B12="",Movimientos!F12=""),"",Movimientos!F12) | F12: {=IF(E12="","",INDEX('Configuración'!$D$15:$D$134,MATCH(E12,'Configuración'!$E$15:$E$134,0)))} | G12: =IF(OR(Movimientos!B12="",Movimientos!G12=""),"",Movimientos!G12) | H12: =IF(OR(Movimientos!B12="",Movimientos!H12=""),"",Movimientos!H12) | I12: =IF(OR(Movimientos!B12="",Movimientos!I12=""),"",Movimientos!I12) | J12: =IF(OR(Movimientos!B12="",Movimientos!J12=""),"",Movimientos!J12) | K12: =IF(B12="","",IF(OR(D12="Ingreso",D12="Rendimiento inversión"),I12,0)) | L12: =IF(B12="","",IF(D12="Gasto",I12-J12,IF(D12="Devolución gasto",-I12+J12,0))) | M12: =IF(B12="","",IF(D12="Gasto",J12,IF(D12="Cobro compartido",-I12,IF(D12="Devolución gasto",-J12,0)))) | N12: =IF(B12="","",IF(G12<>"",G12,H12))
B13: =IF(OR(Movimientos!B13="",Movimientos!B13=""),"",Movimientos!B13) | C13: =IF(OR(Movimientos!B13="",Movimientos!C13=""),"",Movimientos!C13) | D13: =IF(OR(Movimientos!B13="",Movimientos!D13=""),"",Movimientos!D13) | E13: =IF(OR(Movimientos!B13="",Movimientos!F13=""),"",Movimientos!F13) | F13: {=IF(E13="","",INDEX('Configuración'!$D$15:$D$134,MATCH(E13,'Configuración'!$E$15:$E$134,0)))} | G13: =IF(OR(Movimientos!B13="",Movimientos!G13=""),"",Movimientos!G13) | H13: =IF(OR(Movimientos!B13="",Movimientos!H13=""),"",Movimientos!H13) | I13: =IF(OR(Movimientos!B13="",Movimientos!I13=""),"",Movimientos!I13) | J13: =IF(OR(Movimientos!B13="",Movimientos!J13=""),"",Movimientos!J13) | K13: =IF(B13="","",IF(OR(D13="Ingreso",D13="Rendimiento inversión"),I13,0)) | L13: =IF(B13="","",IF(D13="Gasto",I13-J13,IF(D13="Devolución gasto",-I13+J13,0))) | M13: =IF(B13="","",IF(D13="Gasto",J13,IF(D13="Cobro compartido",-I13,IF(D13="Devolución gasto",-J13,0)))) | N13: =IF(B13="","",IF(G13<>"",G13,H13))
B14: =IF(OR(Movimientos!B14="",Movimientos!B14=""),"",Movimientos!B14) | C14: =IF(OR(Movimientos!B14="",Movimientos!C14=""),"",Movimientos!C14) | D14: =IF(OR(Movimientos!B14="",Movimientos!D14=""),"",Movimientos!D14) | E14: =IF(OR(Movimientos!B14="",Movimientos!F14=""),"",Movimientos!F14) | F14: {=IF(E14="","",INDEX('Configuración'!$D$15:$D$134,MATCH(E14,'Configuración'!$E$15:$E$134,0)))} | G14: =IF(OR(Movimientos!B14="",Movimientos!G14=""),"",Movimientos!G14) | H14: =IF(OR(Movimientos!B14="",Movimientos!H14=""),"",Movimientos!H14) | I14: =IF(OR(Movimientos!B14="",Movimientos!I14=""),"",Movimientos!I14) | J14: =IF(OR(Movimientos!B14="",Movimientos!J14=""),"",Movimientos!J14) | K14: =IF(B14="","",IF(OR(D14="Ingreso",D14="Rendimiento inversión"),I14,0)) | L14: =IF(B14="","",IF(D14="Gasto",I14-J14,IF(D14="Devolución gasto",-I14+J14,0))) | M14: =IF(B14="","",IF(D14="Gasto",J14,IF(D14="Cobro compartido",-I14,IF(D14="Devolución gasto",-J14,0)))) | N14: =IF(B14="","",IF(G14<>"",G14,H14))
B15: =IF(OR(Movimientos!B15="",Movimientos!B15=""),"",Movimientos!B15) | C15: =IF(OR(Movimientos!B15="",Movimientos!C15=""),"",Movimientos!C15) | D15: =IF(OR(Movimientos!B15="",Movimientos!D15=""),"",Movimientos!D15) | E15: =IF(OR(Movimientos!B15="",Movimientos!F15=""),"",Movimientos!F15) | F15: {=IF(E15="","",INDEX('Configuración'!$D$15:$D$134,MATCH(E15,'Configuración'!$E$15:$E$134,0)))} | G15: =IF(OR(Movimientos!B15="",Movimientos!G15=""),"",Movimientos!G15) | H15: =IF(OR(Movimientos!B15="",Movimientos!H15=""),"",Movimientos!H15) | I15: =IF(OR(Movimientos!B15="",Movimientos!I15=""),"",Movimientos!I15) | J15: =IF(OR(Movimientos!B15="",Movimientos!J15=""),"",Movimientos!J15) | K15: =IF(B15="","",IF(OR(D15="Ingreso",D15="Rendimiento inversión"),I15,0)) | L15: =IF(B15="","",IF(D15="Gasto",I15-J15,IF(D15="Devolución gasto",-I15+J15,0))) | M15: =IF(B15="","",IF(D15="Gasto",J15,IF(D15="Cobro compartido",-I15,IF(D15="Devolución gasto",-J15,0)))) | N15: =IF(B15="","",IF(G15<>"",G15,H15))
B16: =IF(OR(Movimientos!B16="",Movimientos!B16=""),"",Movimientos!B16) | C16: =IF(OR(Movimientos!B16="",Movimientos!C16=""),"",Movimientos!C16) | D16: =IF(OR(Movimientos!B16="",Movimientos!D16=""),"",Movimientos!D16) | E16: =IF(OR(Movimientos!B16="",Movimientos!F16=""),"",Movimientos!F16) | F16: {=IF(E16="","",INDEX('Configuración'!$D$15:$D$134,MATCH(E16,'Configuración'!$E$15:$E$134,0)))} | G16: =IF(OR(Movimientos!B16="",Movimientos!G16=""),"",Movimientos!G16) | H16: =IF(OR(Movimientos!B16="",Movimientos!H16=""),"",Movimientos!H16) | I16: =IF(OR(Movimientos!B16="",Movimientos!I16=""),"",Movimientos!I16) | J16: =IF(OR(Movimientos!B16="",Movimientos!J16=""),"",Movimientos!J16) | K16: =IF(B16="","",IF(OR(D16="Ingreso",D16="Rendimiento inversión"),I16,0)) | L16: =IF(B16="","",IF(D16="Gasto",I16-J16,IF(D16="Devolución gasto",-I16+J16,0))) | M16: =IF(B16="","",IF(D16="Gasto",J16,IF(D16="Cobro compartido",-I16,IF(D16="Devolución gasto",-J16,0)))) | N16: =IF(B16="","",IF(G16<>"",G16,H16)) | P16: Localización | Q16: Gasto propio
B17: =IF(OR(Movimientos!B17="",Movimientos!B17=""),"",Movimientos!B17) | C17: =IF(OR(Movimientos!B17="",Movimientos!C17=""),"",Movimientos!C17) | D17: =IF(OR(Movimientos!B17="",Movimientos!D17=""),"",Movimientos!D17) | E17: =IF(OR(Movimientos!B17="",Movimientos!F17=""),"",Movimientos!F17) | F17: {=IF(E17="","",INDEX('Configuración'!$D$15:$D$134,MATCH(E17,'Configuración'!$E$15:$E$134,0)))} | G17: =IF(OR(Movimientos!B17="",Movimientos!G17=""),"",Movimientos!G17) | H17: =IF(OR(Movimientos!B17="",Movimientos!H17=""),"",Movimientos!H17) | I17: =IF(OR(Movimientos!B17="",Movimientos!I17=""),"",Movimientos!I17) | J17: =IF(OR(Movimientos!B17="",Movimientos!J17=""),"",Movimientos!J17) | K17: =IF(B17="","",IF(OR(D17="Ingreso",D17="Rendimiento inversión"),I17,0)) | L17: =IF(B17="","",IF(D17="Gasto",I17-J17,IF(D17="Devolución gasto",-I17+J17,0))) | M17: =IF(B17="","",IF(D17="Gasto",J17,IF(D17="Cobro compartido",-I17,IF(D17="Devolución gasto",-J17,0)))) | N17: =IF(B17="","",IF(G17<>"",G17,H17)) | P17: Madrid | Q17: =IF(P17="","",IF('Resumen financiero'!$Q$4="Todas",SUMIFS('Cálculos'!$L$9:$L$128,'Cálculos'!$C$9:$C$128,">="&$C$4,'Cálculos'!$C$9:$C$128,"<"&$D$4,Movimientos!$K$9:$K$128,P17),SUMIFS('Cálculos'!$L$9:$L$128,'Cálculos'!$C$9:$C$128,">="&$C$4,'Cálculos'!$C$9:$C$128,"<"&$D$4,Movimientos!$K$9:$K$128,P17,'Cálculos'!$N$9:$N$128,'Resumen financiero'!$Q$4))) -> 0
B18: =IF(OR(Movimientos!B18="",Movimientos!B18=""),"",Movimientos!B18) | C18: =IF(OR(Movimientos!B18="",Movimientos!C18=""),"",Movimientos!C18) | D18: =IF(OR(Movimientos!B18="",Movimientos!D18=""),"",Movimientos!D18) | E18: =IF(OR(Movimientos!B18="",Movimientos!F18=""),"",Movimientos!F18) | F18: {=IF(E18="","",INDEX('Configuración'!$D$15:$D$134,MATCH(E18,'Configuración'!$E$15:$E$134,0)))} | G18: =IF(OR(Movimientos!B18="",Movimientos!G18=""),"",Movimientos!G18) | H18: =IF(OR(Movimientos!B18="",Movimientos!H18=""),"",Movimientos!H18) | I18: =IF(OR(Movimientos!B18="",Movimientos!I18=""),"",Movimientos!I18) | J18: =IF(OR(Movimientos!B18="",Movimientos!J18=""),"",Movimientos!J18) | K18: =IF(B18="","",IF(OR(D18="Ingreso",D18="Rendimiento inversión"),I18,0)) | L18: =IF(B18="","",IF(D18="Gasto",I18-J18,IF(D18="Devolución gasto",-I18+J18,0))) | M18: =IF(B18="","",IF(D18="Gasto",J18,IF(D18="Cobro compartido",-I18,IF(D18="Devolución gasto",-J18,0)))) | N18: =IF(B18="","",IF(G18<>"",G18,H18)) | P18: Alicante | Q18: =IF(P18="","",IF('Resumen financiero'!$Q$4="Todas",SUMIFS('Cálculos'!$L$9:$L$128,'Cálculos'!$C$9:$C$128,">="&$C$4,'Cálculos'!$C$9:$C$128,"<"&$D$4,Movimientos!$K$9:$K$128,P18),SUMIFS('Cálculos'!$L$9:$L$128,'Cálculos'!$C$9:$C$128,">="&$C$4,'Cálculos'!$C$9:$C$128,"<"&$D$4,Movimientos!$K$9:$K$128,P18,'Cálculos'!$N$9:$N$128,'Resumen financiero'!$Q$4))) -> 0
B19: =IF(OR(Movimientos!B19="",Movimientos!B19=""),"",Movimientos!B19) | C19: =IF(OR(Movimientos!B19="",Movimientos!C19=""),"",Movimientos!C19) | D19: =IF(OR(Movimientos!B19="",Movimientos!D19=""),"",Movimientos!D19) | E19: =IF(OR(Movimientos!B19="",Movimientos!F19=""),"",Movimientos!F19) | F19: {=IF(E19="","",INDEX('Configuración'!$D$15:$D$134,MATCH(E19,'Configuración'!$E$15:$E$134,0)))} | G19: =IF(OR(Movimientos!B19="",Movimientos!G19=""),"",Movimientos!G19) | H19: =IF(OR(Movimientos!B19="",Movimientos!H19=""),"",Movimientos!H19) | I19: =IF(OR(Movimientos!B19="",Movimientos!I19=""),"",Movimientos!I19) | J19: =IF(OR(Movimientos!B19="",Movimientos!J19=""),"",Movimientos!J19) | K19: =IF(B19="","",IF(OR(D19="Ingreso",D19="Rendimiento inversión"),I19,0)) | L19: =IF(B19="","",IF(D19="Gasto",I19-J19,IF(D19="Devolución gasto",-I19+J19,0))) | M19: =IF(B19="","",IF(D19="Gasto",J19,IF(D19="Cobro compartido",-I19,IF(D19="Devolución gasto",-J19,0)))) | N19: =IF(B19="","",IF(G19<>"",G19,H19)) | P19: La Manga | Q19: =IF(P19="","",IF('Resumen financiero'!$Q$4="Todas",SUMIFS('Cálculos'!$L$9:$L$128,'Cálculos'!$C$9:$C$128,">="&$C$4,'Cálculos'!$C$9:$C$128,"<"&$D$4,Movimientos!$K$9:$K$128,P19),SUMIFS('Cálculos'!$L$9:$L$128,'Cálculos'!$C$9:$C$128,">="&$C$4,'Cálculos'!$C$9:$C$128,"<"&$D$4,Movimientos!$K$9:$K$128,P19,'Cálculos'!$N$9:$N$128,'Resumen financiero'!$Q$4))) -> 0
B20: =IF(OR(Movimientos!B20="",Movimientos!B20=""),"",Movimientos!B20) | C20: =IF(OR(Movimientos!B20="",Movimientos!C20=""),"",Movimientos!C20) | D20: =IF(OR(Movimientos!B20="",Movimientos!D20=""),"",Movimientos!D20) | E20: =IF(OR(Movimientos!B20="",Movimientos!F20=""),"",Movimientos!F20) | F20: {=IF(E20="","",INDEX('Configuración'!$D$15:$D$134,MATCH(E20,'Configuración'!$E$15:$E$134,0)))} | G20: =IF(OR(Movimientos!B20="",Movimientos!G20=""),"",Movimientos!G20) | H20: =IF(OR(Movimientos!B20="",Movimientos!H20=""),"",Movimientos!H20) | I20: =IF(OR(Movimientos!B20="",Movimientos!I20=""),"",Movimientos!I20) | J20: =IF(OR(Movimientos!B20="",Movimientos!J20=""),"",Movimientos!J20) | K20: =IF(B20="","",IF(OR(D20="Ingreso",D20="Rendimiento inversión"),I20,0)) | L20: =IF(B20="","",IF(D20="Gasto",I20-J20,IF(D20="Devolución gasto",-I20+J20,0))) | M20: =IF(B20="","",IF(D20="Gasto",J20,IF(D20="Cobro compartido",-I20,IF(D20="Devolución gasto",-J20,0)))) | N20: =IF(B20="","",IF(G20<>"",G20,H20)) | P20: Albacete | Q20: =IF(P20="","",IF('Resumen financiero'!$Q$4="Todas",SUMIFS('Cálculos'!$L$9:$L$128,'Cálculos'!$C$9:$C$128,">="&$C$4,'Cálculos'!$C$9:$C$128,"<"&$D$4,Movimientos!$K$9:$K$128,P20),SUMIFS('Cálculos'!$L$9:$L$128,'Cálculos'!$C$9:$C$128,">="&$C$4,'Cálculos'!$C$9:$C$128,"<"&$D$4,Movimientos!$K$9:$K$128,P20,'Cálculos'!$N$9:$N$128,'Resumen financiero'!$Q$4))) -> 0
B21: =IF(OR(Movimientos!B21="",Movimientos!B21=""),"",Movimientos!B21) | C21: =IF(OR(Movimientos!B21="",Movimientos!C21=""),"",Movimientos!C21) | D21: =IF(OR(Movimientos!B21="",Movimientos!D21=""),"",Movimientos!D21) | E21: =IF(OR(Movimientos!B21="",Movimientos!F21=""),"",Movimientos!F21) | F21: {=IF(E21="","",INDEX('Configuración'!$D$15:$D$134,MATCH(E21,'Configuración'!$E$15:$E$134,0)))} | G21: =IF(OR(Movimientos!B21="",Movimientos!G21=""),"",Movimientos!G21) | H21: =IF(OR(Movimientos!B21="",Movimientos!H21=""),"",Movimientos!H21) | I21: =IF(OR(Movimientos!B21="",Movimientos!I21=""),"",Movimientos!I21) | J21: =IF(OR(Movimientos!B21="",Movimientos!J21=""),"",Movimientos!J21) | K21: =IF(B21="","",IF(OR(D21="Ingreso",D21="Rendimiento inversión"),I21,0)) | L21: =IF(B21="","",IF(D21="Gasto",I21-J21,IF(D21="Devolución gasto",-I21+J21,0))) | M21: =IF(B21="","",IF(D21="Gasto",J21,IF(D21="Cobro compartido",-I21,IF(D21="Devolución gasto",-J21,0)))) | N21: =IF(B21="","",IF(G21<>"",G21,H21)) | P21: N/A | Q21: =IF(P21="","",IF('Resumen financiero'!$Q$4="Todas",SUMIFS('Cálculos'!$L$9:$L$128,'Cálculos'!$C$9:$C$128,">="&$C$4,'Cálculos'!$C$9:$C$128,"<"&$D$4,Movimientos!$K$9:$K$128,P21),SUMIFS('Cálculos'!$L$9:$L$128,'Cálculos'!$C$9:$C$128,">="&$C$4,'Cálculos'!$C$9:$C$128,"<"&$D$4,Movimientos!$K$9:$K$128,P21,'Cálculos'!$N$9:$N$128,'Resumen financiero'!$Q$4))) -> 0
B22: =IF(OR(Movimientos!B22="",Movimientos!B22=""),"",Movimientos!B22) | C22: =IF(OR(Movimientos!B22="",Movimientos!C22=""),"",Movimientos!C22) | D22: =IF(OR(Movimientos!B22="",Movimientos!D22=""),"",Movimientos!D22) | E22: =IF(OR(Movimientos!B22="",Movimientos!F22=""),"",Movimientos!F22) | F22: {=IF(E22="","",INDEX('Configuración'!$D$15:$D$134,MATCH(E22,'Configuración'!$E$15:$E$134,0)))} | G22: =IF(OR(Movimientos!B22="",Movimientos!G22=""),"",Movimientos!G22) | H22: =IF(OR(Movimientos!B22="",Movimientos!H22=""),"",Movimientos!H22) | I22: =IF(OR(Movimientos!B22="",Movimientos!I22=""),"",Movimientos!I22) | J22: =IF(OR(Movimientos!B22="",Movimientos!J22=""),"",Movimientos!J22) | K22: =IF(B22="","",IF(OR(D22="Ingreso",D22="Rendimiento inversión"),I22,0)) | L22: =IF(B22="","",IF(D22="Gasto",I22-J22,IF(D22="Devolución gasto",-I22+J22,0))) | M22: =IF(B22="","",IF(D22="Gasto",J22,IF(D22="Cobro compartido",-I22,IF(D22="Devolución gasto",-J22,0)))) | N22: =IF(B22="","",IF(G22<>"",G22,H22))
B23: =IF(OR(Movimientos!B23="",Movimientos!B23=""),"",Movimientos!B23) | C23: =IF(OR(Movimientos!B23="",Movimientos!C23=""),"",Movimientos!C23) | D23: =IF(OR(Movimientos!B23="",Movimientos!D23=""),"",Movimientos!D23) | E23: =IF(OR(Movimientos!B23="",Movimientos!F23=""),"",Movimientos!F23) | F23: {=IF(E23="","",INDEX('Configuración'!$D$15:$D$134,MATCH(E23,'Configuración'!$E$15:$E$134,0)))} | G23: =IF(OR(Movimientos!B23="",Movimientos!G23=""),"",Movimientos!G23) | H23: =IF(OR(Movimientos!B23="",Movimientos!H23=""),"",Movimientos!H23) | I23: =IF(OR(Movimientos!B23="",Movimientos!I23=""),"",Movimientos!I23) | J23: =IF(OR(Movimientos!B23="",Movimientos!J23=""),"",Movimientos!J23) | K23: =IF(B23="","",IF(OR(D23="Ingreso",D23="Rendimiento inversión"),I23,0)) | L23: =IF(B23="","",IF(D23="Gasto",I23-J23,IF(D23="Devolución gasto",-I23+J23,0))) | M23: =IF(B23="","",IF(D23="Gasto",J23,IF(D23="Cobro compartido",-I23,IF(D23="Devolución gasto",-J23,0)))) | N23: =IF(B23="","",IF(G23<>"",G23,H23))
B24: =IF(OR(Movimientos!B24="",Movimientos!B24=""),"",Movimientos!B24) | C24: =IF(OR(Movimientos!B24="",Movimientos!C24=""),"",Movimientos!C24) | D24: =IF(OR(Movimientos!B24="",Movimientos!D24=""),"",Movimientos!D24) | E24: =IF(OR(Movimientos!B24="",Movimientos!F24=""),"",Movimientos!F24) | F24: {=IF(E24="","",INDEX('Configuración'!$D$15:$D$134,MATCH(E24,'Configuración'!$E$15:$E$134,0)))} | G24: =IF(OR(Movimientos!B24="",Movimientos!G24=""),"",Movimientos!G24) | H24: =IF(OR(Movimientos!B24="",Movimientos!H24=""),"",Movimientos!H24) | I24: =IF(OR(Movimientos!B24="",Movimientos!I24=""),"",Movimientos!I24) | J24: =IF(OR(Movimientos!B24="",Movimientos!J24=""),"",Movimientos!J24) | K24: =IF(B24="","",IF(OR(D24="Ingreso",D24="Rendimiento inversión"),I24,0)) | L24: =IF(B24="","",IF(D24="Gasto",I24-J24,IF(D24="Devolución gasto",-I24+J24,0))) | M24: =IF(B24="","",IF(D24="Gasto",J24,IF(D24="Cobro compartido",-I24,IF(D24="Devolución gasto",-J24,0)))) | N24: =IF(B24="","",IF(G24<>"",G24,H24))
B25: =IF(OR(Movimientos!B25="",Movimientos!B25=""),"",Movimientos!B25) | C25: =IF(OR(Movimientos!B25="",Movimientos!C25=""),"",Movimientos!C25) | D25: =IF(OR(Movimientos!B25="",Movimientos!D25=""),"",Movimientos!D25) | E25: =IF(OR(Movimientos!B25="",Movimientos!F25=""),"",Movimientos!F25) | F25: {=IF(E25="","",INDEX('Configuración'!$D$15:$D$134,MATCH(E25,'Configuración'!$E$15:$E$134,0)))} | G25: =IF(OR(Movimientos!B25="",Movimientos!G25=""),"",Movimientos!G25) | H25: =IF(OR(Movimientos!B25="",Movimientos!H25=""),"",Movimientos!H25) | I25: =IF(OR(Movimientos!B25="",Movimientos!I25=""),"",Movimientos!I25) | J25: =IF(OR(Movimientos!B25="",Movimientos!J25=""),"",Movimientos!J25) | K25: =IF(B25="","",IF(OR(D25="Ingreso",D25="Rendimiento inversión"),I25,0)) | L25: =IF(B25="","",IF(D25="Gasto",I25-J25,IF(D25="Devolución gasto",-I25+J25,0))) | M25: =IF(B25="","",IF(D25="Gasto",J25,IF(D25="Cobro compartido",-I25,IF(D25="Devolución gasto",-J25,0)))) | N25: =IF(B25="","",IF(G25<>"",G25,H25))
B26: =IF(OR(Movimientos!B26="",Movimientos!B26=""),"",Movimientos!B26) | C26: =IF(OR(Movimientos!B26="",Movimientos!C26=""),"",Movimientos!C26) | D26: =IF(OR(Movimientos!B26="",Movimientos!D26=""),"",Movimientos!D26) | E26: =IF(OR(Movimientos!B26="",Movimientos!F26=""),"",Movimientos!F26) | F26: {=IF(E26="","",INDEX('Configuración'!$D$15:$D$134,MATCH(E26,'Configuración'!$E$15:$E$134,0)))} | G26: =IF(OR(Movimientos!B26="",Movimientos!G26=""),"",Movimientos!G26) | H26: =IF(OR(Movimientos!B26="",Movimientos!H26=""),"",Movimientos!H26) | I26: =IF(OR(Movimientos!B26="",Movimientos!I26=""),"",Movimientos!I26) | J26: =IF(OR(Movimientos!B26="",Movimientos!J26=""),"",Movimientos!J26) | K26: =IF(B26="","",IF(OR(D26="Ingreso",D26="Rendimiento inversión"),I26,0)) | L26: =IF(B26="","",IF(D26="Gasto",I26-J26,IF(D26="Devolución gasto",-I26+J26,0))) | M26: =IF(B26="","",IF(D26="Gasto",J26,IF(D26="Cobro compartido",-I26,IF(D26="Devolución gasto",-J26,0)))) | N26: =IF(B26="","",IF(G26<>"",G26,H26))
B27: =IF(OR(Movimientos!B27="",Movimientos!B27=""),"",Movimientos!B27) | C27: =IF(OR(Movimientos!B27="",Movimientos!C27=""),"",Movimientos!C27) | D27: =IF(OR(Movimientos!B27="",Movimientos!D27=""),"",Movimientos!D27) | E27: =IF(OR(Movimientos!B27="",Movimientos!F27=""),"",Movimientos!F27) | F27: {=IF(E27="","",INDEX('Configuración'!$D$15:$D$134,MATCH(E27,'Configuración'!$E$15:$E$134,0)))} | G27: =IF(OR(Movimientos!B27="",Movimientos!G27=""),"",Movimientos!G27) | H27: =IF(OR(Movimientos!B27="",Movimientos!H27=""),"",Movimientos!H27) | I27: =IF(OR(Movimientos!B27="",Movimientos!I27=""),"",Movimientos!I27) | J27: =IF(OR(Movimientos!B27="",Movimientos!J27=""),"",Movimientos!J27) | K27: =IF(B27="","",IF(OR(D27="Ingreso",D27="Rendimiento inversión"),I27,0)) | L27: =IF(B27="","",IF(D27="Gasto",I27-J27,IF(D27="Devolución gasto",-I27+J27,0))) | M27: =IF(B27="","",IF(D27="Gasto",J27,IF(D27="Cobro compartido",-I27,IF(D27="Devolución gasto",-J27,0)))) | N27: =IF(B27="","",IF(G27<>"",G27,H27))
B28: =IF(OR(Movimientos!B28="",Movimientos!B28=""),"",Movimientos!B28) | C28: =IF(OR(Movimientos!B28="",Movimientos!C28=""),"",Movimientos!C28) | D28: =IF(OR(Movimientos!B28="",Movimientos!D28=""),"",Movimientos!D28) | E28: =IF(OR(Movimientos!B28="",Movimientos!F28=""),"",Movimientos!F28) | F28: {=IF(E28="","",INDEX('Configuración'!$D$15:$D$134,MATCH(E28,'Configuración'!$E$15:$E$134,0)))} | G28: =IF(OR(Movimientos!B28="",Movimientos!G28=""),"",Movimientos!G28) | H28: =IF(OR(Movimientos!B28="",Movimientos!H28=""),"",Movimientos!H28) | I28: =IF(OR(Movimientos!B28="",Movimientos!I28=""),"",Movimientos!I28) | J28: =IF(OR(Movimientos!B28="",Movimientos!J28=""),"",Movimientos!J28) | K28: =IF(B28="","",IF(OR(D28="Ingreso",D28="Rendimiento inversión"),I28,0)) | L28: =IF(B28="","",IF(D28="Gasto",I28-J28,IF(D28="Devolución gasto",-I28+J28,0))) | M28: =IF(B28="","",IF(D28="Gasto",J28,IF(D28="Cobro compartido",-I28,IF(D28="Devolución gasto",-J28,0)))) | N28: =IF(B28="","",IF(G28<>"",G28,H28))
B29: =IF(OR(Movimientos!B29="",Movimientos!B29=""),"",Movimientos!B29) | C29: =IF(OR(Movimientos!B29="",Movimientos!C29=""),"",Movimientos!C29) | D29: =IF(OR(Movimientos!B29="",Movimientos!D29=""),"",Movimientos!D29) | E29: =IF(OR(Movimientos!B29="",Movimientos!F29=""),"",Movimientos!F29) | F29: {=IF(E29="","",INDEX('Configuración'!$D$15:$D$134,MATCH(E29,'Configuración'!$E$15:$E$134,0)))} | G29: =IF(OR(Movimientos!B29="",Movimientos!G29=""),"",Movimientos!G29) | H29: =IF(OR(Movimientos!B29="",Movimientos!H29=""),"",Movimientos!H29) | I29: =IF(OR(Movimientos!B29="",Movimientos!I29=""),"",Movimientos!I29) | J29: =IF(OR(Movimientos!B29="",Movimientos!J29=""),"",Movimientos!J29) | K29: =IF(B29="","",IF(OR(D29="Ingreso",D29="Rendimiento inversión"),I29,0)) | L29: =IF(B29="","",IF(D29="Gasto",I29-J29,IF(D29="Devolución gasto",-I29+J29,0))) | M29: =IF(B29="","",IF(D29="Gasto",J29,IF(D29="Cobro compartido",-I29,IF(D29="Devolución gasto",-J29,0)))) | N29: =IF(B29="","",IF(G29<>"",G29,H29))
B30: =IF(OR(Movimientos!B30="",Movimientos!B30=""),"",Movimientos!B30) | C30: =IF(OR(Movimientos!B30="",Movimientos!C30=""),"",Movimientos!C30) | D30: =IF(OR(Movimientos!B30="",Movimientos!D30=""),"",Movimientos!D30) | E30: =IF(OR(Movimientos!B30="",Movimientos!F30=""),"",Movimientos!F30) | F30: {=IF(E30="","",INDEX('Configuración'!$D$15:$D$134,MATCH(E30,'Configuración'!$E$15:$E$134,0)))} | G30: =IF(OR(Movimientos!B30="",Movimientos!G30=""),"",Movimientos!G30) | H30: =IF(OR(Movimientos!B30="",Movimientos!H30=""),"",Movimientos!H30) | I30: =IF(OR(Movimientos!B30="",Movimientos!I30=""),"",Movimientos!I30) | J30: =IF(OR(Movimientos!B30="",Movimientos!J30=""),"",Movimientos!J30) | K30: =IF(B30="","",IF(OR(D30="Ingreso",D30="Rendimiento inversión"),I30,0)) | L30: =IF(B30="","",IF(D30="Gasto",I30-J30,IF(D30="Devolución gasto",-I30+J30,0))) | M30: =IF(B30="","",IF(D30="Gasto",J30,IF(D30="Cobro compartido",-I30,IF(D30="Devolución gasto",-J30,0)))) | N30: =IF(B30="","",IF(G30<>"",G30,H30))
B31: =IF(OR(Movimientos!B31="",Movimientos!B31=""),"",Movimientos!B31) | C31: =IF(OR(Movimientos!B31="",Movimientos!C31=""),"",Movimientos!C31) | D31: =IF(OR(Movimientos!B31="",Movimientos!D31=""),"",Movimientos!D31) | E31: =IF(OR(Movimientos!B31="",Movimientos!F31=""),"",Movimientos!F31) | F31: {=IF(E31="","",INDEX('Configuración'!$D$15:$D$134,MATCH(E31,'Configuración'!$E$15:$E$134,0)))} | G31: =IF(OR(Movimientos!B31="",Movimientos!G31=""),"",Movimientos!G31) | H31: =IF(OR(Movimientos!B31="",Movimientos!H31=""),"",Movimientos!H31) | I31: =IF(OR(Movimientos!B31="",Movimientos!I31=""),"",Movimientos!I31) | J31: =IF(OR(Movimientos!B31="",Movimientos!J31=""),"",Movimientos!J31) | K31: =IF(B31="","",IF(OR(D31="Ingreso",D31="Rendimiento inversión"),I31,0)) | L31: =IF(B31="","",IF(D31="Gasto",I31-J31,IF(D31="Devolución gasto",-I31+J31,0))) | M31: =IF(B31="","",IF(D31="Gasto",J31,IF(D31="Cobro compartido",-I31,IF(D31="Devolución gasto",-J31,0)))) | N31: =IF(B31="","",IF(G31<>"",G31,H31))
B32: =IF(OR(Movimientos!B32="",Movimientos!B32=""),"",Movimientos!B32) | C32: =IF(OR(Movimientos!B32="",Movimientos!C32=""),"",Movimientos!C32) | D32: =IF(OR(Movimientos!B32="",Movimientos!D32=""),"",Movimientos!D32) | E32: =IF(OR(Movimientos!B32="",Movimientos!F32=""),"",Movimientos!F32) | F32: {=IF(E32="","",INDEX('Configuración'!$D$15:$D$134,MATCH(E32,'Configuración'!$E$15:$E$134,0)))} | G32: =IF(OR(Movimientos!B32="",Movimientos!G32=""),"",Movimientos!G32) | H32: =IF(OR(Movimientos!B32="",Movimientos!H32=""),"",Movimientos!H32) | I32: =IF(OR(Movimientos!B32="",Movimientos!I32=""),"",Movimientos!I32) | J32: =IF(OR(Movimientos!B32="",Movimientos!J32=""),"",Movimientos!J32) | K32: =IF(B32="","",IF(OR(D32="Ingreso",D32="Rendimiento inversión"),I32,0)) | L32: =IF(B32="","",IF(D32="Gasto",I32-J32,IF(D32="Devolución gasto",-I32+J32,0))) | M32: =IF(B32="","",IF(D32="Gasto",J32,IF(D32="Cobro compartido",-I32,IF(D32="Devolución gasto",-J32,0)))) | N32: =IF(B32="","",IF(G32<>"",G32,H32))
B33: =IF(OR(Movimientos!B33="",Movimientos!B33=""),"",Movimientos!B33) | C33: =IF(OR(Movimientos!B33="",Movimientos!C33=""),"",Movimientos!C33) | D33: =IF(OR(Movimientos!B33="",Movimientos!D33=""),"",Movimientos!D33) | E33: =IF(OR(Movimientos!B33="",Movimientos!F33=""),"",Movimientos!F33) | F33: {=IF(E33="","",INDEX('Configuración'!$D$15:$D$134,MATCH(E33,'Configuración'!$E$15:$E$134,0)))} | G33: =IF(OR(Movimientos!B33="",Movimientos!G33=""),"",Movimientos!G33) | H33: =IF(OR(Movimientos!B33="",Movimientos!H33=""),"",Movimientos!H33) | I33: =IF(OR(Movimientos!B33="",Movimientos!I33=""),"",Movimientos!I33) | J33: =IF(OR(Movimientos!B33="",Movimientos!J33=""),"",Movimientos!J33) | K33: =IF(B33="","",IF(OR(D33="Ingreso",D33="Rendimiento inversión"),I33,0)) | L33: =IF(B33="","",IF(D33="Gasto",I33-J33,IF(D33="Devolución gasto",-I33+J33,0))) | M33: =IF(B33="","",IF(D33="Gasto",J33,IF(D33="Cobro compartido",-I33,IF(D33="Devolución gasto",-J33,0)))) | N33: =IF(B33="","",IF(G33<>"",G33,H33))
... B128: =IF(OR(Movimientos!B128="",Movimientos!B128=""),"",Movimientos!B128) | C128: =IF(OR(Movimientos!B128="",Movimientos!C128=""),"",Movimientos!C128) | D128: =IF(OR(Movimientos!B128="",Movimientos!D128=""),"",Movimientos!D128) | E128: =IF(OR(Movimientos!B128="",Movimientos!F128=""),"",Movimientos!F128) | F128: {=IF(E128="","",INDEX('Configuración'!$D$15:$D$134,MATCH(E128,'Configuración'!$E$15:$E$134,0)))} | G128: =IF(OR(Movimientos!B128="",Movimientos!G128=""),"",Movimientos!G128) | H128: =IF(OR(Movimientos!B128="",Movimientos!H128=""),"",Movimientos!H128) | I128: =IF(OR(Movimientos!B128="",Movimientos!I128=""),"",Movimientos!I128) | J128: =IF(OR(Movimientos!B128="",Movimientos!J128=""),"",Movimientos!J128) | K128: =IF(B128="","",IF(OR(D128="Ingreso",D128="Rendimiento inversión"),I128,0)) | L128: =IF(B128="","",IF(D128="Gasto",I128-J128,IF(D128="Devolución gasto",-I128+J128,0))) | M128: =IF(B128="","",IF(D128="Gasto",J128,IF(D128="Cobro compartido",-I128,IF(D128="Devolución gasto",-J128,0)))) | N128: =IF(B128="","",IF(G128<>"",G128,H128))
B134: Mes | C134: Ingresos | D134: Gastos | E134: Ahorro | F134: Efectivo | G134: Etiqueta
B135: =DATE('Resumen financiero'!$E$4,1,1) -> 46023 | C135: =IF(AND(EDATE(B135,1)>'Configuración'!$C$6,B135<='Configuración'!$C$7),IF('Resumen financiero'!$Q$4="Todas",SUMIFS('Cálculos'!$K$9:$K$128,'Cálculos'!$C$9:$C$128,">="&B135,'Cálculos'!$C$9:$C$128,"<"&MIN(EDATE(B135,1),'Configuración'!$C$7+1)),SUMIFS('Cálculos'!$K$9:$K$128,'Cálculos'!$C$9:$C$128,">="&B135,'Cálculos'!$C$9:$C$128,"<"&MIN(EDATE(B135,1),'Configuración'!$C$7+1),'Cálculos'!$N$9:$N$128,'Resumen financiero'!$Q$4)),"") -> 0 | D135: =IF(AND(EDATE(B135,1)>'Configuración'!$C$6,B135<='Configuración'!$C$7),IF('Resumen financiero'!$Q$4="Todas",SUMIFS('Cálculos'!$L$9:$L$128,'Cálculos'!$C$9:$C$128,">="&B135,'Cálculos'!$C$9:$C$128,"<"&MIN(EDATE(B135,1),'Configuración'!$C$7+1)),SUMIFS('Cálculos'!$L$9:$L$128,'Cálculos'!$C$9:$C$128,">="&B135,'Cálculos'!$C$9:$C$128,"<"&MIN(EDATE(B135,1),'Configuración'!$C$7+1),'Cálculos'!$N$9:$N$128,'Resumen financiero'!$Q$4)),"") -> 0 | E135: =IF(COUNT(C135,D135)<2,"",C135-D135) -> 0 | F135: =IF(AND(EDATE(B135,1)>'Configuración'!$C$6,B135<='Configuración'!$C$7),IF('Resumen financiero'!$Q$4="Todas",SUM(tCuentas[Saldo inicial])+SUMIFS(tMovimientos[Importe],tMovimientos[Destino],"<>",tMovimientos[Fecha],">="&'Configuración'!$C$6,tMovimientos[Fecha],"<"&MIN(EDATE(B135,1),'Configuración'!$C$7+1))-SUMIFS(tMovimientos[Importe],tMovimientos[Origen],"<>",tMovimientos[Fecha],">="&'Configuración'!$C$6,tMovimientos[Fecha],"<"&MIN(EDATE(B135,1),'Configuración'!$C$7+1)),SUMIFS(tCuentas[Saldo inicial],tCuentas[Cuenta],'Resumen financiero'!$Q$4)+SUMIFS(tMovimientos[Importe],tMovimientos[Destino],'Resumen financiero'!$Q$4,tMovimientos[Fecha],">="&'Configuración'!$C$6,tMovimientos[Fecha],"<"&MIN(EDATE(B135,1),'Configuración'!$C$7+1))-SUMIFS(tMovimientos[Importe],tMovimientos[Origen],'Resumen financiero'!$Q$4,tMovimientos[Fecha],">="&'Configuración'!$C$6,tMovimientos[Fecha],"<"&MIN(EDATE(B135,1),'Configuración'!$C$7+1))),"") -> 0 | G135: =IF(COUNT(C135)=0,"",CHOOSE(MONTH(B135),"ene","feb","mar","abr","may","jun","jul","ago","sep","oct","nov","dic")&" "&YEAR(B135)) -> ene 2026
B136: =DATE('Resumen financiero'!$E$4,2,1) -> 46054 | C136: =IF(AND(EDATE(B136,1)>'Configuración'!$C$6,B136<='Configuración'!$C$7),IF('Resumen financiero'!$Q$4="Todas",SUMIFS('Cálculos'!$K$9:$K$128,'Cálculos'!$C$9:$C$128,">="&B136,'Cálculos'!$C$9:$C$128,"<"&MIN(EDATE(B136,1),'Configuración'!$C$7+1)),SUMIFS('Cálculos'!$K$9:$K$128,'Cálculos'!$C$9:$C$128,">="&B136,'Cálculos'!$C$9:$C$128,"<"&MIN(EDATE(B136,1),'Configuración'!$C$7+1),'Cálculos'!$N$9:$N$128,'Resumen financiero'!$Q$4)),"") | D136: =IF(AND(EDATE(B136,1)>'Configuración'!$C$6,B136<='Configuración'!$C$7),IF('Resumen financiero'!$Q$4="Todas",SUMIFS('Cálculos'!$L$9:$L$128,'Cálculos'!$C$9:$C$128,">="&B136,'Cálculos'!$C$9:$C$128,"<"&MIN(EDATE(B136,1),'Configuración'!$C$7+1)),SUMIFS('Cálculos'!$L$9:$L$128,'Cálculos'!$C$9:$C$128,">="&B136,'Cálculos'!$C$9:$C$128,"<"&MIN(EDATE(B136,1),'Configuración'!$C$7+1),'Cálculos'!$N$9:$N$128,'Resumen financiero'!$Q$4)),"") | E136: =IF(COUNT(C136,D136)<2,"",C136-D136) | F136: =IF(AND(EDATE(B136,1)>'Configuración'!$C$6,B136<='Configuración'!$C$7),IF('Resumen financiero'!$Q$4="Todas",SUM(tCuentas[Saldo inicial])+SUMIFS(tMovimientos[Importe],tMovimientos[Destino],"<>",tMovimientos[Fecha],">="&'Configuración'!$C$6,tMovimientos[Fecha],"<"&MIN(EDATE(B136,1),'Configuración'!$C$7+1))-SUMIFS(tMovimientos[Importe],tMovimientos[Origen],"<>",tMovimientos[Fecha],">="&'Configuración'!$C$6,tMovimientos[Fecha],"<"&MIN(EDATE(B136,1),'Configuración'!$C$7+1)),SUMIFS(tCuentas[Saldo inicial],tCuentas[Cuenta],'Resumen financiero'!$Q$4)+SUMIFS(tMovimientos[Importe],tMovimientos[Destino],'Resumen financiero'!$Q$4,tMovimientos[Fecha],">="&'Configuración'!$C$6,tMovimientos[Fecha],"<"&MIN(EDATE(B136,1),'Configuración'!$C$7+1))-SUMIFS(tMovimientos[Importe],tMovimientos[Origen],'Resumen financiero'!$Q$4,tMovimientos[Fecha],">="&'Configuración'!$C$6,tMovimientos[Fecha],"<"&MIN(EDATE(B136,1),'Configuración'!$C$7+1))),"") | G136: =IF(COUNT(C136)=0,"",CHOOSE(MONTH(B136),"ene","feb","mar","abr","may","jun","jul","ago","sep","oct","nov","dic")&" "&YEAR(B136))
B137: =DATE('Resumen financiero'!$E$4,3,1) -> 46082 | C137: =IF(AND(EDATE(B137,1)>'Configuración'!$C$6,B137<='Configuración'!$C$7),IF('Resumen financiero'!$Q$4="Todas",SUMIFS('Cálculos'!$K$9:$K$128,'Cálculos'!$C$9:$C$128,">="&B137,'Cálculos'!$C$9:$C$128,"<"&MIN(EDATE(B137,1),'Configuración'!$C$7+1)),SUMIFS('Cálculos'!$K$9:$K$128,'Cálculos'!$C$9:$C$128,">="&B137,'Cálculos'!$C$9:$C$128,"<"&MIN(EDATE(B137,1),'Configuración'!$C$7+1),'Cálculos'!$N$9:$N$128,'Resumen financiero'!$Q$4)),"") | D137: =IF(AND(EDATE(B137,1)>'Configuración'!$C$6,B137<='Configuración'!$C$7),IF('Resumen financiero'!$Q$4="Todas",SUMIFS('Cálculos'!$L$9:$L$128,'Cálculos'!$C$9:$C$128,">="&B137,'Cálculos'!$C$9:$C$128,"<"&MIN(EDATE(B137,1),'Configuración'!$C$7+1)),SUMIFS('Cálculos'!$L$9:$L$128,'Cálculos'!$C$9:$C$128,">="&B137,'Cálculos'!$C$9:$C$128,"<"&MIN(EDATE(B137,1),'Configuración'!$C$7+1),'Cálculos'!$N$9:$N$128,'Resumen financiero'!$Q$4)),"") | E137: =IF(COUNT(C137,D137)<2,"",C137-D137) | F137: =IF(AND(EDATE(B137,1)>'Configuración'!$C$6,B137<='Configuración'!$C$7),IF('Resumen financiero'!$Q$4="Todas",SUM(tCuentas[Saldo inicial])+SUMIFS(tMovimientos[Importe],tMovimientos[Destino],"<>",tMovimientos[Fecha],">="&'Configuración'!$C$6,tMovimientos[Fecha],"<"&MIN(EDATE(B137,1),'Configuración'!$C$7+1))-SUMIFS(tMovimientos[Importe],tMovimientos[Origen],"<>",tMovimientos[Fecha],">="&'Configuración'!$C$6,tMovimientos[Fecha],"<"&MIN(EDATE(B137,1),'Configuración'!$C$7+1)),SUMIFS(tCuentas[Saldo inicial],tCuentas[Cuenta],'Resumen financiero'!$Q$4)+SUMIFS(tMovimientos[Importe],tMovimientos[Destino],'Resumen financiero'!$Q$4,tMovimientos[Fecha],">="&'Configuración'!$C$6,tMovimientos[Fecha],"<"&MIN(EDATE(B137,1),'Configuración'!$C$7+1))-SUMIFS(tMovimientos[Importe],tMovimientos[Origen],'Resumen financiero'!$Q$4,tMovimientos[Fecha],">="&'Configuración'!$C$6,tMovimientos[Fecha],"<"&MIN(EDATE(B137,1),'Configuración'!$C$7+1))),"") | G137: =IF(COUNT(C137)=0,"",CHOOSE(MONTH(B137),"ene","feb","mar","abr","may","jun","jul","ago","sep","oct","nov","dic")&" "&YEAR(B137))
B138: =DATE('Resumen financiero'!$E$4,4,1) -> 46113 | C138: =IF(AND(EDATE(B138,1)>'Configuración'!$C$6,B138<='Configuración'!$C$7),IF('Resumen financiero'!$Q$4="Todas",SUMIFS('Cálculos'!$K$9:$K$128,'Cálculos'!$C$9:$C$128,">="&B138,'Cálculos'!$C$9:$C$128,"<"&MIN(EDATE(B138,1),'Configuración'!$C$7+1)),SUMIFS('Cálculos'!$K$9:$K$128,'Cálculos'!$C$9:$C$128,">="&B138,'Cálculos'!$C$9:$C$128,"<"&MIN(EDATE(B138,1),'Configuración'!$C$7+1),'Cálculos'!$N$9:$N$128,'Resumen financiero'!$Q$4)),"") | D138: =IF(AND(EDATE(B138,1)>'Configuración'!$C$6,B138<='Configuración'!$C$7),IF('Resumen financiero'!$Q$4="Todas",SUMIFS('Cálculos'!$L$9:$L$128,'Cálculos'!$C$9:$C$128,">="&B138,'Cálculos'!$C$9:$C$128,"<"&MIN(EDATE(B138,1),'Configuración'!$C$7+1)),SUMIFS('Cálculos'!$L$9:$L$128,'Cálculos'!$C$9:$C$128,">="&B138,'Cálculos'!$C$9:$C$128,"<"&MIN(EDATE(B138,1),'Configuración'!$C$7+1),'Cálculos'!$N$9:$N$128,'Resumen financiero'!$Q$4)),"") | E138: =IF(COUNT(C138,D138)<2,"",C138-D138) | F138: =IF(AND(EDATE(B138,1)>'Configuración'!$C$6,B138<='Configuración'!$C$7),IF('Resumen financiero'!$Q$4="Todas",SUM(tCuentas[Saldo inicial])+SUMIFS(tMovimientos[Importe],tMovimientos[Destino],"<>",tMovimientos[Fecha],">="&'Configuración'!$C$6,tMovimientos[Fecha],"<"&MIN(EDATE(B138,1),'Configuración'!$C$7+1))-SUMIFS(tMovimientos[Importe],tMovimientos[Origen],"<>",tMovimientos[Fecha],">="&'Configuración'!$C$6,tMovimientos[Fecha],"<"&MIN(EDATE(B138,1),'Configuración'!$C$7+1)),SUMIFS(tCuentas[Saldo inicial],tCuentas[Cuenta],'Resumen financiero'!$Q$4)+SUMIFS(tMovimientos[Importe],tMovimientos[Destino],'Resumen financiero'!$Q$4,tMovimientos[Fecha],">="&'Configuración'!$C$6,tMovimientos[Fecha],"<"&MIN(EDATE(B138,1),'Configuración'!$C$7+1))-SUMIFS(tMovimientos[Importe],tMovimientos[Origen],'Resumen financiero'!$Q$4,tMovimientos[Fecha],">="&'Configuración'!$C$6,tMovimientos[Fecha],"<"&MIN(EDATE(B138,1),'Configuración'!$C$7+1))),"") | G138: =IF(COUNT(C138)=0,"",CHOOSE(MONTH(B138),"ene","feb","mar","abr","may","jun","jul","ago","sep","oct","nov","dic")&" "&YEAR(B138))
B139: =DATE('Resumen financiero'!$E$4,5,1) -> 46143 | C139: =IF(AND(EDATE(B139,1)>'Configuración'!$C$6,B139<='Configuración'!$C$7),IF('Resumen financiero'!$Q$4="Todas",SUMIFS('Cálculos'!$K$9:$K$128,'Cálculos'!$C$9:$C$128,">="&B139,'Cálculos'!$C$9:$C$128,"<"&MIN(EDATE(B139,1),'Configuración'!$C$7+1)),SUMIFS('Cálculos'!$K$9:$K$128,'Cálculos'!$C$9:$C$128,">="&B139,'Cálculos'!$C$9:$C$128,"<"&MIN(EDATE(B139,1),'Configuración'!$C$7+1),'Cálculos'!$N$9:$N$128,'Resumen financiero'!$Q$4)),"") | D139: =IF(AND(EDATE(B139,1)>'Configuración'!$C$6,B139<='Configuración'!$C$7),IF('Resumen financiero'!$Q$4="Todas",SUMIFS('Cálculos'!$L$9:$L$128,'Cálculos'!$C$9:$C$128,">="&B139,'Cálculos'!$C$9:$C$128,"<"&MIN(EDATE(B139,1),'Configuración'!$C$7+1)),SUMIFS('Cálculos'!$L$9:$L$128,'Cálculos'!$C$9:$C$128,">="&B139,'Cálculos'!$C$9:$C$128,"<"&MIN(EDATE(B139,1),'Configuración'!$C$7+1),'Cálculos'!$N$9:$N$128,'Resumen financiero'!$Q$4)),"") | E139: =IF(COUNT(C139,D139)<2,"",C139-D139) | F139: =IF(AND(EDATE(B139,1)>'Configuración'!$C$6,B139<='Configuración'!$C$7),IF('Resumen financiero'!$Q$4="Todas",SUM(tCuentas[Saldo inicial])+SUMIFS(tMovimientos[Importe],tMovimientos[Destino],"<>",tMovimientos[Fecha],">="&'Configuración'!$C$6,tMovimientos[Fecha],"<"&MIN(EDATE(B139,1),'Configuración'!$C$7+1))-SUMIFS(tMovimientos[Importe],tMovimientos[Origen],"<>",tMovimientos[Fecha],">="&'Configuración'!$C$6,tMovimientos[Fecha],"<"&MIN(EDATE(B139,1),'Configuración'!$C$7+1)),SUMIFS(tCuentas[Saldo inicial],tCuentas[Cuenta],'Resumen financiero'!$Q$4)+SUMIFS(tMovimientos[Importe],tMovimientos[Destino],'Resumen financiero'!$Q$4,tMovimientos[Fecha],">="&'Configuración'!$C$6,tMovimientos[Fecha],"<"&MIN(EDATE(B139,1),'Configuración'!$C$7+1))-SUMIFS(tMovimientos[Importe],tMovimientos[Origen],'Resumen financiero'!$Q$4,tMovimientos[Fecha],">="&'Configuración'!$C$6,tMovimientos[Fecha],"<"&MIN(EDATE(B139,1),'Configuración'!$C$7+1))),"") | G139: =IF(COUNT(C139)=0,"",CHOOSE(MONTH(B139),"ene","feb","mar","abr","may","jun","jul","ago","sep","oct","nov","dic")&" "&YEAR(B139))
B140: =DATE('Resumen financiero'!$E$4,6,1) -> 46174 | C140: =IF(AND(EDATE(B140,1)>'Configuración'!$C$6,B140<='Configuración'!$C$7),IF('Resumen financiero'!$Q$4="Todas",SUMIFS('Cálculos'!$K$9:$K$128,'Cálculos'!$C$9:$C$128,">="&B140,'Cálculos'!$C$9:$C$128,"<"&MIN(EDATE(B140,1),'Configuración'!$C$7+1)),SUMIFS('Cálculos'!$K$9:$K$128,'Cálculos'!$C$9:$C$128,">="&B140,'Cálculos'!$C$9:$C$128,"<"&MIN(EDATE(B140,1),'Configuración'!$C$7+1),'Cálculos'!$N$9:$N$128,'Resumen financiero'!$Q$4)),"") | D140: =IF(AND(EDATE(B140,1)>'Configuración'!$C$6,B140<='Configuración'!$C$7),IF('Resumen financiero'!$Q$4="Todas",SUMIFS('Cálculos'!$L$9:$L$128,'Cálculos'!$C$9:$C$128,">="&B140,'Cálculos'!$C$9:$C$128,"<"&MIN(EDATE(B140,1),'Configuración'!$C$7+1)),SUMIFS('Cálculos'!$L$9:$L$128,'Cálculos'!$C$9:$C$128,">="&B140,'Cálculos'!$C$9:$C$128,"<"&MIN(EDATE(B140,1),'Configuración'!$C$7+1),'Cálculos'!$N$9:$N$128,'Resumen financiero'!$Q$4)),"") | E140: =IF(COUNT(C140,D140)<2,"",C140-D140) | F140: =IF(AND(EDATE(B140,1)>'Configuración'!$C$6,B140<='Configuración'!$C$7),IF('Resumen financiero'!$Q$4="Todas",SUM(tCuentas[Saldo inicial])+SUMIFS(tMovimientos[Importe],tMovimientos[Destino],"<>",tMovimientos[Fecha],">="&'Configuración'!$C$6,tMovimientos[Fecha],"<"&MIN(EDATE(B140,1),'Configuración'!$C$7+1))-SUMIFS(tMovimientos[Importe],tMovimientos[Origen],"<>",tMovimientos[Fecha],">="&'Configuración'!$C$6,tMovimientos[Fecha],"<"&MIN(EDATE(B140,1),'Configuración'!$C$7+1)),SUMIFS(tCuentas[Saldo inicial],tCuentas[Cuenta],'Resumen financiero'!$Q$4)+SUMIFS(tMovimientos[Importe],tMovimientos[Destino],'Resumen financiero'!$Q$4,tMovimientos[Fecha],">="&'Configuración'!$C$6,tMovimientos[Fecha],"<"&MIN(EDATE(B140,1),'Configuración'!$C$7+1))-SUMIFS(tMovimientos[Importe],tMovimientos[Origen],'Resumen financiero'!$Q$4,tMovimientos[Fecha],">="&'Configuración'!$C$6,tMovimientos[Fecha],"<"&MIN(EDATE(B140,1),'Configuración'!$C$7+1))),"") | G140: =IF(COUNT(C140)=0,"",CHOOSE(MONTH(B140),"ene","feb","mar","abr","may","jun","jul","ago","sep","oct","nov","dic")&" "&YEAR(B140))
B141: =DATE('Resumen financiero'!$E$4,7,1) -> 46204 | C141: =IF(AND(EDATE(B141,1)>'Configuración'!$C$6,B141<='Configuración'!$C$7),IF('Resumen financiero'!$Q$4="Todas",SUMIFS('Cálculos'!$K$9:$K$128,'Cálculos'!$C$9:$C$128,">="&B141,'Cálculos'!$C$9:$C$128,"<"&MIN(EDATE(B141,1),'Configuración'!$C$7+1)),SUMIFS('Cálculos'!$K$9:$K$128,'Cálculos'!$C$9:$C$128,">="&B141,'Cálculos'!$C$9:$C$128,"<"&MIN(EDATE(B141,1),'Configuración'!$C$7+1),'Cálculos'!$N$9:$N$128,'Resumen financiero'!$Q$4)),"") | D141: =IF(AND(EDATE(B141,1)>'Configuración'!$C$6,B141<='Configuración'!$C$7),IF('Resumen financiero'!$Q$4="Todas",SUMIFS('Cálculos'!$L$9:$L$128,'Cálculos'!$C$9:$C$128,">="&B141,'Cálculos'!$C$9:$C$128,"<"&MIN(EDATE(B141,1),'Configuración'!$C$7+1)),SUMIFS('Cálculos'!$L$9:$L$128,'Cálculos'!$C$9:$C$128,">="&B141,'Cálculos'!$C$9:$C$128,"<"&MIN(EDATE(B141,1),'Configuración'!$C$7+1),'Cálculos'!$N$9:$N$128,'Resumen financiero'!$Q$4)),"") | E141: =IF(COUNT(C141,D141)<2,"",C141-D141) | F141: =IF(AND(EDATE(B141,1)>'Configuración'!$C$6,B141<='Configuración'!$C$7),IF('Resumen financiero'!$Q$4="Todas",SUM(tCuentas[Saldo inicial])+SUMIFS(tMovimientos[Importe],tMovimientos[Destino],"<>",tMovimientos[Fecha],">="&'Configuración'!$C$6,tMovimientos[Fecha],"<"&MIN(EDATE(B141,1),'Configuración'!$C$7+1))-SUMIFS(tMovimientos[Importe],tMovimientos[Origen],"<>",tMovimientos[Fecha],">="&'Configuración'!$C$6,tMovimientos[Fecha],"<"&MIN(EDATE(B141,1),'Configuración'!$C$7+1)),SUMIFS(tCuentas[Saldo inicial],tCuentas[Cuenta],'Resumen financiero'!$Q$4)+SUMIFS(tMovimientos[Importe],tMovimientos[Destino],'Resumen financiero'!$Q$4,tMovimientos[Fecha],">="&'Configuración'!$C$6,tMovimientos[Fecha],"<"&MIN(EDATE(B141,1),'Configuración'!$C$7+1))-SUMIFS(tMovimientos[Importe],tMovimientos[Origen],'Resumen financiero'!$Q$4,tMovimientos[Fecha],">="&'Configuración'!$C$6,tMovimientos[Fecha],"<"&MIN(EDATE(B141,1),'Configuración'!$C$7+1))),"") | G141: =IF(COUNT(C141)=0,"",CHOOSE(MONTH(B141),"ene","feb","mar","abr","may","jun","jul","ago","sep","oct","nov","dic")&" "&YEAR(B141))
B142: =DATE('Resumen financiero'!$E$4,8,1) -> 46235 | C142: =IF(AND(EDATE(B142,1)>'Configuración'!$C$6,B142<='Configuración'!$C$7),IF('Resumen financiero'!$Q$4="Todas",SUMIFS('Cálculos'!$K$9:$K$128,'Cálculos'!$C$9:$C$128,">="&B142,'Cálculos'!$C$9:$C$128,"<"&MIN(EDATE(B142,1),'Configuración'!$C$7+1)),SUMIFS('Cálculos'!$K$9:$K$128,'Cálculos'!$C$9:$C$128,">="&B142,'Cálculos'!$C$9:$C$128,"<"&MIN(EDATE(B142,1),'Configuración'!$C$7+1),'Cálculos'!$N$9:$N$128,'Resumen financiero'!$Q$4)),"") | D142: =IF(AND(EDATE(B142,1)>'Configuración'!$C$6,B142<='Configuración'!$C$7),IF('Resumen financiero'!$Q$4="Todas",SUMIFS('Cálculos'!$L$9:$L$128,'Cálculos'!$C$9:$C$128,">="&B142,'Cálculos'!$C$9:$C$128,"<"&MIN(EDATE(B142,1),'Configuración'!$C$7+1)),SUMIFS('Cálculos'!$L$9:$L$128,'Cálculos'!$C$9:$C$128,">="&B142,'Cálculos'!$C$9:$C$128,"<"&MIN(EDATE(B142,1),'Configuración'!$C$7+1),'Cálculos'!$N$9:$N$128,'Resumen financiero'!$Q$4)),"") | E142: =IF(COUNT(C142,D142)<2,"",C142-D142) | F142: =IF(AND(EDATE(B142,1)>'Configuración'!$C$6,B142<='Configuración'!$C$7),IF('Resumen financiero'!$Q$4="Todas",SUM(tCuentas[Saldo inicial])+SUMIFS(tMovimientos[Importe],tMovimientos[Destino],"<>",tMovimientos[Fecha],">="&'Configuración'!$C$6,tMovimientos[Fecha],"<"&MIN(EDATE(B142,1),'Configuración'!$C$7+1))-SUMIFS(tMovimientos[Importe],tMovimientos[Origen],"<>",tMovimientos[Fecha],">="&'Configuración'!$C$6,tMovimientos[Fecha],"<"&MIN(EDATE(B142,1),'Configuración'!$C$7+1)),SUMIFS(tCuentas[Saldo inicial],tCuentas[Cuenta],'Resumen financiero'!$Q$4)+SUMIFS(tMovimientos[Importe],tMovimientos[Destino],'Resumen financiero'!$Q$4,tMovimientos[Fecha],">="&'Configuración'!$C$6,tMovimientos[Fecha],"<"&MIN(EDATE(B142,1),'Configuración'!$C$7+1))-SUMIFS(tMovimientos[Importe],tMovimientos[Origen],'Resumen financiero'!$Q$4,tMovimientos[Fecha],">="&'Configuración'!$C$6,tMovimientos[Fecha],"<"&MIN(EDATE(B142,1),'Configuración'!$C$7+1))),"") | G142: =IF(COUNT(C142)=0,"",CHOOSE(MONTH(B142),"ene","feb","mar","abr","may","jun","jul","ago","sep","oct","nov","dic")&" "&YEAR(B142))
B143: =DATE('Resumen financiero'!$E$4,9,1) -> 46266 | C143: =IF(AND(EDATE(B143,1)>'Configuración'!$C$6,B143<='Configuración'!$C$7),IF('Resumen financiero'!$Q$4="Todas",SUMIFS('Cálculos'!$K$9:$K$128,'Cálculos'!$C$9:$C$128,">="&B143,'Cálculos'!$C$9:$C$128,"<"&MIN(EDATE(B143,1),'Configuración'!$C$7+1)),SUMIFS('Cálculos'!$K$9:$K$128,'Cálculos'!$C$9:$C$128,">="&B143,'Cálculos'!$C$9:$C$128,"<"&MIN(EDATE(B143,1),'Configuración'!$C$7+1),'Cálculos'!$N$9:$N$128,'Resumen financiero'!$Q$4)),"") | D143: =IF(AND(EDATE(B143,1)>'Configuración'!$C$6,B143<='Configuración'!$C$7),IF('Resumen financiero'!$Q$4="Todas",SUMIFS('Cálculos'!$L$9:$L$128,'Cálculos'!$C$9:$C$128,">="&B143,'Cálculos'!$C$9:$C$128,"<"&MIN(EDATE(B143,1),'Configuración'!$C$7+1)),SUMIFS('Cálculos'!$L$9:$L$128,'Cálculos'!$C$9:$C$128,">="&B143,'Cálculos'!$C$9:$C$128,"<"&MIN(EDATE(B143,1),'Configuración'!$C$7+1),'Cálculos'!$N$9:$N$128,'Resumen financiero'!$Q$4)),"") | E143: =IF(COUNT(C143,D143)<2,"",C143-D143) | F143: =IF(AND(EDATE(B143,1)>'Configuración'!$C$6,B143<='Configuración'!$C$7),IF('Resumen financiero'!$Q$4="Todas",SUM(tCuentas[Saldo inicial])+SUMIFS(tMovimientos[Importe],tMovimientos[Destino],"<>",tMovimientos[Fecha],">="&'Configuración'!$C$6,tMovimientos[Fecha],"<"&MIN(EDATE(B143,1),'Configuración'!$C$7+1))-SUMIFS(tMovimientos[Importe],tMovimientos[Origen],"<>",tMovimientos[Fecha],">="&'Configuración'!$C$6,tMovimientos[Fecha],"<"&MIN(EDATE(B143,1),'Configuración'!$C$7+1)),SUMIFS(tCuentas[Saldo inicial],tCuentas[Cuenta],'Resumen financiero'!$Q$4)+SUMIFS(tMovimientos[Importe],tMovimientos[Destino],'Resumen financiero'!$Q$4,tMovimientos[Fecha],">="&'Configuración'!$C$6,tMovimientos[Fecha],"<"&MIN(EDATE(B143,1),'Configuración'!$C$7+1))-SUMIFS(tMovimientos[Importe],tMovimientos[Origen],'Resumen financiero'!$Q$4,tMovimientos[Fecha],">="&'Configuración'!$C$6,tMovimientos[Fecha],"<"&MIN(EDATE(B143,1),'Configuración'!$C$7+1))),"") | G143: =IF(COUNT(C143)=0,"",CHOOSE(MONTH(B143),"ene","feb","mar","abr","may","jun","jul","ago","sep","oct","nov","dic")&" "&YEAR(B143))
B144: =DATE('Resumen financiero'!$E$4,10,1) -> 46296 | C144: =IF(AND(EDATE(B144,1)>'Configuración'!$C$6,B144<='Configuración'!$C$7),IF('Resumen financiero'!$Q$4="Todas",SUMIFS('Cálculos'!$K$9:$K$128,'Cálculos'!$C$9:$C$128,">="&B144,'Cálculos'!$C$9:$C$128,"<"&MIN(EDATE(B144,1),'Configuración'!$C$7+1)),SUMIFS('Cálculos'!$K$9:$K$128,'Cálculos'!$C$9:$C$128,">="&B144,'Cálculos'!$C$9:$C$128,"<"&MIN(EDATE(B144,1),'Configuración'!$C$7+1),'Cálculos'!$N$9:$N$128,'Resumen financiero'!$Q$4)),"") | D144: =IF(AND(EDATE(B144,1)>'Configuración'!$C$6,B144<='Configuración'!$C$7),IF('Resumen financiero'!$Q$4="Todas",SUMIFS('Cálculos'!$L$9:$L$128,'Cálculos'!$C$9:$C$128,">="&B144,'Cálculos'!$C$9:$C$128,"<"&MIN(EDATE(B144,1),'Configuración'!$C$7+1)),SUMIFS('Cálculos'!$L$9:$L$128,'Cálculos'!$C$9:$C$128,">="&B144,'Cálculos'!$C$9:$C$128,"<"&MIN(EDATE(B144,1),'Configuración'!$C$7+1),'Cálculos'!$N$9:$N$128,'Resumen financiero'!$Q$4)),"") | E144: =IF(COUNT(C144,D144)<2,"",C144-D144) | F144: =IF(AND(EDATE(B144,1)>'Configuración'!$C$6,B144<='Configuración'!$C$7),IF('Resumen financiero'!$Q$4="Todas",SUM(tCuentas[Saldo inicial])+SUMIFS(tMovimientos[Importe],tMovimientos[Destino],"<>",tMovimientos[Fecha],">="&'Configuración'!$C$6,tMovimientos[Fecha],"<"&MIN(EDATE(B144,1),'Configuración'!$C$7+1))-SUMIFS(tMovimientos[Importe],tMovimientos[Origen],"<>",tMovimientos[Fecha],">="&'Configuración'!$C$6,tMovimientos[Fecha],"<"&MIN(EDATE(B144,1),'Configuración'!$C$7+1)),SUMIFS(tCuentas[Saldo inicial],tCuentas[Cuenta],'Resumen financiero'!$Q$4)+SUMIFS(tMovimientos[Importe],tMovimientos[Destino],'Resumen financiero'!$Q$4,tMovimientos[Fecha],">="&'Configuración'!$C$6,tMovimientos[Fecha],"<"&MIN(EDATE(B144,1),'Configuración'!$C$7+1))-SUMIFS(tMovimientos[Importe],tMovimientos[Origen],'Resumen financiero'!$Q$4,tMovimientos[Fecha],">="&'Configuración'!$C$6,tMovimientos[Fecha],"<"&MIN(EDATE(B144,1),'Configuración'!$C$7+1))),"") | G144: =IF(COUNT(C144)=0,"",CHOOSE(MONTH(B144),"ene","feb","mar","abr","may","jun","jul","ago","sep","oct","nov","dic")&" "&YEAR(B144))
B145: =DATE('Resumen financiero'!$E$4,11,1) -> 46327 | C145: =IF(AND(EDATE(B145,1)>'Configuración'!$C$6,B145<='Configuración'!$C$7),IF('Resumen financiero'!$Q$4="Todas",SUMIFS('Cálculos'!$K$9:$K$128,'Cálculos'!$C$9:$C$128,">="&B145,'Cálculos'!$C$9:$C$128,"<"&MIN(EDATE(B145,1),'Configuración'!$C$7+1)),SUMIFS('Cálculos'!$K$9:$K$128,'Cálculos'!$C$9:$C$128,">="&B145,'Cálculos'!$C$9:$C$128,"<"&MIN(EDATE(B145,1),'Configuración'!$C$7+1),'Cálculos'!$N$9:$N$128,'Resumen financiero'!$Q$4)),"") | D145: =IF(AND(EDATE(B145,1)>'Configuración'!$C$6,B145<='Configuración'!$C$7),IF('Resumen financiero'!$Q$4="Todas",SUMIFS('Cálculos'!$L$9:$L$128,'Cálculos'!$C$9:$C$128,">="&B145,'Cálculos'!$C$9:$C$128,"<"&MIN(EDATE(B145,1),'Configuración'!$C$7+1)),SUMIFS('Cálculos'!$L$9:$L$128,'Cálculos'!$C$9:$C$128,">="&B145,'Cálculos'!$C$9:$C$128,"<"&MIN(EDATE(B145,1),'Configuración'!$C$7+1),'Cálculos'!$N$9:$N$128,'Resumen financiero'!$Q$4)),"") | E145: =IF(COUNT(C145,D145)<2,"",C145-D145) | F145: =IF(AND(EDATE(B145,1)>'Configuración'!$C$6,B145<='Configuración'!$C$7),IF('Resumen financiero'!$Q$4="Todas",SUM(tCuentas[Saldo inicial])+SUMIFS(tMovimientos[Importe],tMovimientos[Destino],"<>",tMovimientos[Fecha],">="&'Configuración'!$C$6,tMovimientos[Fecha],"<"&MIN(EDATE(B145,1),'Configuración'!$C$7+1))-SUMIFS(tMovimientos[Importe],tMovimientos[Origen],"<>",tMovimientos[Fecha],">="&'Configuración'!$C$6,tMovimientos[Fecha],"<"&MIN(EDATE(B145,1),'Configuración'!$C$7+1)),SUMIFS(tCuentas[Saldo inicial],tCuentas[Cuenta],'Resumen financiero'!$Q$4)+SUMIFS(tMovimientos[Importe],tMovimientos[Destino],'Resumen financiero'!$Q$4,tMovimientos[Fecha],">="&'Configuración'!$C$6,tMovimientos[Fecha],"<"&MIN(EDATE(B145,1),'Configuración'!$C$7+1))-SUMIFS(tMovimientos[Importe],tMovimientos[Origen],'Resumen financiero'!$Q$4,tMovimientos[Fecha],">="&'Configuración'!$C$6,tMovimientos[Fecha],"<"&MIN(EDATE(B145,1),'Configuración'!$C$7+1))),"") | G145: =IF(COUNT(C145)=0,"",CHOOSE(MONTH(B145),"ene","feb","mar","abr","may","jun","jul","ago","sep","oct","nov","dic")&" "&YEAR(B145))
B146: =DATE('Resumen financiero'!$E$4,12,1) -> 46357 | C146: =IF(AND(EDATE(B146,1)>'Configuración'!$C$6,B146<='Configuración'!$C$7),IF('Resumen financiero'!$Q$4="Todas",SUMIFS('Cálculos'!$K$9:$K$128,'Cálculos'!$C$9:$C$128,">="&B146,'Cálculos'!$C$9:$C$128,"<"&MIN(EDATE(B146,1),'Configuración'!$C$7+1)),SUMIFS('Cálculos'!$K$9:$K$128,'Cálculos'!$C$9:$C$128,">="&B146,'Cálculos'!$C$9:$C$128,"<"&MIN(EDATE(B146,1),'Configuración'!$C$7+1),'Cálculos'!$N$9:$N$128,'Resumen financiero'!$Q$4)),"") | D146: =IF(AND(EDATE(B146,1)>'Configuración'!$C$6,B146<='Configuración'!$C$7),IF('Resumen financiero'!$Q$4="Todas",SUMIFS('Cálculos'!$L$9:$L$128,'Cálculos'!$C$9:$C$128,">="&B146,'Cálculos'!$C$9:$C$128,"<"&MIN(EDATE(B146,1),'Configuración'!$C$7+1)),SUMIFS('Cálculos'!$L$9:$L$128,'Cálculos'!$C$9:$C$128,">="&B146,'Cálculos'!$C$9:$C$128,"<"&MIN(EDATE(B146,1),'Configuración'!$C$7+1),'Cálculos'!$N$9:$N$128,'Resumen financiero'!$Q$4)),"") | E146: =IF(COUNT(C146,D146)<2,"",C146-D146) | F146: =IF(AND(EDATE(B146,1)>'Configuración'!$C$6,B146<='Configuración'!$C$7),IF('Resumen financiero'!$Q$4="Todas",SUM(tCuentas[Saldo inicial])+SUMIFS(tMovimientos[Importe],tMovimientos[Destino],"<>",tMovimientos[Fecha],">="&'Configuración'!$C$6,tMovimientos[Fecha],"<"&MIN(EDATE(B146,1),'Configuración'!$C$7+1))-SUMIFS(tMovimientos[Importe],tMovimientos[Origen],"<>",tMovimientos[Fecha],">="&'Configuración'!$C$6,tMovimientos[Fecha],"<"&MIN(EDATE(B146,1),'Configuración'!$C$7+1)),SUMIFS(tCuentas[Saldo inicial],tCuentas[Cuenta],'Resumen financiero'!$Q$4)+SUMIFS(tMovimientos[Importe],tMovimientos[Destino],'Resumen financiero'!$Q$4,tMovimientos[Fecha],">="&'Configuración'!$C$6,tMovimientos[Fecha],"<"&MIN(EDATE(B146,1),'Configuración'!$C$7+1))-SUMIFS(tMovimientos[Importe],tMovimientos[Origen],'Resumen financiero'!$Q$4,tMovimientos[Fecha],">="&'Configuración'!$C$6,tMovimientos[Fecha],"<"&MIN(EDATE(B146,1),'Configuración'!$C$7+1))),"") | G146: =IF(COUNT(C146)=0,"",CHOOSE(MONTH(B146),"ene","feb","mar","abr","may","jun","jul","ago","sep","oct","nov","dic")&" "&YEAR(B146))
B150: Categoría | C150: Gasto propio | E150: Categoría | F150: Gasto positivo
B151: =IFERROR(__xludf.DUMMYFUNCTION("IFERROR(INDEX(UNIQUE(FILTER('Configuración'!$D$15:$D$134,'Configuración'!$B$15:$B$134=""Gastos"")),1),"""")"),"") | C151: =IF(B151="","",IF('Resumen financiero'!$Q$4="Todas",SUMIFS('Cálculos'!$L$9:$L$128,'Cálculos'!$F$9:$F$128,B151,'Cálculos'!$C$9:$C$128,">="&$C$4,'Cálculos'!$C$9:$C$128,"<"&$D$4),SUMIFS('Cálculos'!$L$9:$L$128,'Cálculos'!$F$9:$F$128,B151,'Cálculos'!$C$9:$C$128,">="&$C$4,'Cálculos'!$C$9:$C$128,"<"&$D$4,'Cálculos'!$N$9:$N$128,'Resumen financiero'!$Q$4))) | D151: ="" | E151: =IFERROR(__xludf.DUMMYFUNCTION("IFERROR(INDEX(UNIQUE(FILTER('Configuración'!$D$15:$D$134,'Configuración'!$B$15:$B$134=""Gastos"")),1),"""")"),"") | F151: =IF(COUNT(C151)=0,"",MAX(0,C151))
B152: =IFERROR(__xludf.DUMMYFUNCTION("IFERROR(INDEX(UNIQUE(FILTER('Configuración'!$D$15:$D$134,'Configuración'!$B$15:$B$134=""Gastos"")),2),"""")"),"") | C152: =IF(B152="","",IF('Resumen financiero'!$Q$4="Todas",SUMIFS('Cálculos'!$L$9:$L$128,'Cálculos'!$F$9:$F$128,B152,'Cálculos'!$C$9:$C$128,">="&$C$4,'Cálculos'!$C$9:$C$128,"<"&$D$4),SUMIFS('Cálculos'!$L$9:$L$128,'Cálculos'!$F$9:$F$128,B152,'Cálculos'!$C$9:$C$128,">="&$C$4,'Cálculos'!$C$9:$C$128,"<"&$D$4,'Cálculos'!$N$9:$N$128,'Resumen financiero'!$Q$4))) | D152: ="" | E152: =IFERROR(__xludf.DUMMYFUNCTION("IFERROR(INDEX(UNIQUE(FILTER('Configuración'!$D$15:$D$134,'Configuración'!$B$15:$B$134=""Gastos"")),2),"""")"),"") | F152: =IF(COUNT(C152)=0,"",MAX(0,C152))
B153: =IFERROR(__xludf.DUMMYFUNCTION("IFERROR(INDEX(UNIQUE(FILTER('Configuración'!$D$15:$D$134,'Configuración'!$B$15:$B$134=""Gastos"")),3),"""")"),"") | C153: =IF(B153="","",IF('Resumen financiero'!$Q$4="Todas",SUMIFS('Cálculos'!$L$9:$L$128,'Cálculos'!$F$9:$F$128,B153,'Cálculos'!$C$9:$C$128,">="&$C$4,'Cálculos'!$C$9:$C$128,"<"&$D$4),SUMIFS('Cálculos'!$L$9:$L$128,'Cálculos'!$F$9:$F$128,B153,'Cálculos'!$C$9:$C$128,">="&$C$4,'Cálculos'!$C$9:$C$128,"<"&$D$4,'Cálculos'!$N$9:$N$128,'Resumen financiero'!$Q$4))) | D153: ="" | E153: =IFERROR(__xludf.DUMMYFUNCTION("IFERROR(INDEX(UNIQUE(FILTER('Configuración'!$D$15:$D$134,'Configuración'!$B$15:$B$134=""Gastos"")),3),"""")"),"") | F153: =IF(COUNT(C153)=0,"",MAX(0,C153))
B154: =IFERROR(__xludf.DUMMYFUNCTION("IFERROR(INDEX(UNIQUE(FILTER('Configuración'!$D$15:$D$134,'Configuración'!$B$15:$B$134=""Gastos"")),4),"""")"),"") | C154: =IF(B154="","",IF('Resumen financiero'!$Q$4="Todas",SUMIFS('Cálculos'!$L$9:$L$128,'Cálculos'!$F$9:$F$128,B154,'Cálculos'!$C$9:$C$128,">="&$C$4,'Cálculos'!$C$9:$C$128,"<"&$D$4),SUMIFS('Cálculos'!$L$9:$L$128,'Cálculos'!$F$9:$F$128,B154,'Cálculos'!$C$9:$C$128,">="&$C$4,'Cálculos'!$C$9:$C$128,"<"&$D$4,'Cálculos'!$N$9:$N$128,'Resumen financiero'!$Q$4))) | D154: ="" | E154: =IFERROR(__xludf.DUMMYFUNCTION("IFERROR(INDEX(UNIQUE(FILTER('Configuración'!$D$15:$D$134,'Configuración'!$B$15:$B$134=""Gastos"")),4),"""")"),"") | F154: =IF(COUNT(C154)=0,"",MAX(0,C154))
B155: =IFERROR(__xludf.DUMMYFUNCTION("IFERROR(INDEX(UNIQUE(FILTER('Configuración'!$D$15:$D$134,'Configuración'!$B$15:$B$134=""Gastos"")),5),"""")"),"") | C155: =IF(B155="","",IF('Resumen financiero'!$Q$4="Todas",SUMIFS('Cálculos'!$L$9:$L$128,'Cálculos'!$F$9:$F$128,B155,'Cálculos'!$C$9:$C$128,">="&$C$4,'Cálculos'!$C$9:$C$128,"<"&$D$4),SUMIFS('Cálculos'!$L$9:$L$128,'Cálculos'!$F$9:$F$128,B155,'Cálculos'!$C$9:$C$128,">="&$C$4,'Cálculos'!$C$9:$C$128,"<"&$D$4,'Cálculos'!$N$9:$N$128,'Resumen financiero'!$Q$4))) | D155: ="" | E155: =IFERROR(__xludf.DUMMYFUNCTION("IFERROR(INDEX(UNIQUE(FILTER('Configuración'!$D$15:$D$134,'Configuración'!$B$15:$B$134=""Gastos"")),5),"""")"),"") | F155: =IF(COUNT(C155)=0,"",MAX(0,C155))
B156: =IFERROR(__xludf.DUMMYFUNCTION("IFERROR(INDEX(UNIQUE(FILTER('Configuración'!$D$15:$D$134,'Configuración'!$B$15:$B$134=""Gastos"")),6),"""")"),"") | C156: =IF(B156="","",IF('Resumen financiero'!$Q$4="Todas",SUMIFS('Cálculos'!$L$9:$L$128,'Cálculos'!$F$9:$F$128,B156,'Cálculos'!$C$9:$C$128,">="&$C$4,'Cálculos'!$C$9:$C$128,"<"&$D$4),SUMIFS('Cálculos'!$L$9:$L$128,'Cálculos'!$F$9:$F$128,B156,'Cálculos'!$C$9:$C$128,">="&$C$4,'Cálculos'!$C$9:$C$128,"<"&$D$4,'Cálculos'!$N$9:$N$128,'Resumen financiero'!$Q$4))) | D156: ="" | E156: =IFERROR(__xludf.DUMMYFUNCTION("IFERROR(INDEX(UNIQUE(FILTER('Configuración'!$D$15:$D$134,'Configuración'!$B$15:$B$134=""Gastos"")),6),"""")"),"") | F156: =IF(COUNT(C156)=0,"",MAX(0,C156))
B157: =IFERROR(__xludf.DUMMYFUNCTION("IFERROR(INDEX(UNIQUE(FILTER('Configuración'!$D$15:$D$134,'Configuración'!$B$15:$B$134=""Gastos"")),7),"""")"),"") | C157: =IF(B157="","",IF('Resumen financiero'!$Q$4="Todas",SUMIFS('Cálculos'!$L$9:$L$128,'Cálculos'!$F$9:$F$128,B157,'Cálculos'!$C$9:$C$128,">="&$C$4,'Cálculos'!$C$9:$C$128,"<"&$D$4),SUMIFS('Cálculos'!$L$9:$L$128,'Cálculos'!$F$9:$F$128,B157,'Cálculos'!$C$9:$C$128,">="&$C$4,'Cálculos'!$C$9:$C$128,"<"&$D$4,'Cálculos'!$N$9:$N$128,'Resumen financiero'!$Q$4))) | D157: ="" | E157: =IFERROR(__xludf.DUMMYFUNCTION("IFERROR(INDEX(UNIQUE(FILTER('Configuración'!$D$15:$D$134,'Configuración'!$B$15:$B$134=""Gastos"")),7),"""")"),"") | F157: =IF(COUNT(C157)=0,"",MAX(0,C157))
B158: =IFERROR(__xludf.DUMMYFUNCTION("IFERROR(INDEX(UNIQUE(FILTER('Configuración'!$D$15:$D$134,'Configuración'!$B$15:$B$134=""Gastos"")),8),"""")"),"") | C158: =IF(B158="","",IF('Resumen financiero'!$Q$4="Todas",SUMIFS('Cálculos'!$L$9:$L$128,'Cálculos'!$F$9:$F$128,B158,'Cálculos'!$C$9:$C$128,">="&$C$4,'Cálculos'!$C$9:$C$128,"<"&$D$4),SUMIFS('Cálculos'!$L$9:$L$128,'Cálculos'!$F$9:$F$128,B158,'Cálculos'!$C$9:$C$128,">="&$C$4,'Cálculos'!$C$9:$C$128,"<"&$D$4,'Cálculos'!$N$9:$N$128,'Resumen financiero'!$Q$4))) | D158: ="" | E158: =IFERROR(__xludf.DUMMYFUNCTION("IFERROR(INDEX(UNIQUE(FILTER('Configuración'!$D$15:$D$134,'Configuración'!$B$15:$B$134=""Gastos"")),8),"""")"),"") | F158: =IF(COUNT(C158)=0,"",MAX(0,C158))
B159: =IFERROR(__xludf.DUMMYFUNCTION("IFERROR(INDEX(UNIQUE(FILTER('Configuración'!$D$15:$D$134,'Configuración'!$B$15:$B$134=""Gastos"")),9),"""")"),"") | C159: =IF(B159="","",IF('Resumen financiero'!$Q$4="Todas",SUMIFS('Cálculos'!$L$9:$L$128,'Cálculos'!$F$9:$F$128,B159,'Cálculos'!$C$9:$C$128,">="&$C$4,'Cálculos'!$C$9:$C$128,"<"&$D$4),SUMIFS('Cálculos'!$L$9:$L$128,'Cálculos'!$F$9:$F$128,B159,'Cálculos'!$C$9:$C$128,">="&$C$4,'Cálculos'!$C$9:$C$128,"<"&$D$4,'Cálculos'!$N$9:$N$128,'Resumen financiero'!$Q$4))) | D159: ="" | E159: =IFERROR(__xludf.DUMMYFUNCTION("IFERROR(INDEX(UNIQUE(FILTER('Configuración'!$D$15:$D$134,'Configuración'!$B$15:$B$134=""Gastos"")),9),"""")"),"") | F159: =IF(COUNT(C159)=0,"",MAX(0,C159))
B160: =IFERROR(__xludf.DUMMYFUNCTION("IFERROR(INDEX(UNIQUE(FILTER('Configuración'!$D$15:$D$134,'Configuración'!$B$15:$B$134=""Gastos"")),10),"""")"),"") | C160: =IF(B160="","",IF('Resumen financiero'!$Q$4="Todas",SUMIFS('Cálculos'!$L$9:$L$128,'Cálculos'!$F$9:$F$128,B160,'Cálculos'!$C$9:$C$128,">="&$C$4,'Cálculos'!$C$9:$C$128,"<"&$D$4),SUMIFS('Cálculos'!$L$9:$L$128,'Cálculos'!$F$9:$F$128,B160,'Cálculos'!$C$9:$C$128,">="&$C$4,'Cálculos'!$C$9:$C$128,"<"&$D$4,'Cálculos'!$N$9:$N$128,'Resumen financiero'!$Q$4))) | D160: ="" | E160: =IFERROR(__xludf.DUMMYFUNCTION("IFERROR(INDEX(UNIQUE(FILTER('Configuración'!$D$15:$D$134,'Configuración'!$B$15:$B$134=""Gastos"")),10),"""")"),"") | F160: =IF(COUNT(C160)=0,"",MAX(0,C160))
B161: =IFERROR(__xludf.DUMMYFUNCTION("IFERROR(INDEX(UNIQUE(FILTER('Configuración'!$D$15:$D$134,'Configuración'!$B$15:$B$134=""Gastos"")),11),"""")"),"") | C161: =IF(B161="","",IF('Resumen financiero'!$Q$4="Todas",SUMIFS('Cálculos'!$L$9:$L$128,'Cálculos'!$F$9:$F$128,B161,'Cálculos'!$C$9:$C$128,">="&$C$4,'Cálculos'!$C$9:$C$128,"<"&$D$4),SUMIFS('Cálculos'!$L$9:$L$128,'Cálculos'!$F$9:$F$128,B161,'Cálculos'!$C$9:$C$128,">="&$C$4,'Cálculos'!$C$9:$C$128,"<"&$D$4,'Cálculos'!$N$9:$N$128,'Resumen financiero'!$Q$4))) | D161: ="" | E161: =IFERROR(__xludf.DUMMYFUNCTION("IFERROR(INDEX(UNIQUE(FILTER('Configuración'!$D$15:$D$134,'Configuración'!$B$15:$B$134=""Gastos"")),11),"""")"),"") | F161: =IF(COUNT(C161)=0,"",MAX(0,C161))
B162: =IFERROR(__xludf.DUMMYFUNCTION("IFERROR(INDEX(UNIQUE(FILTER('Configuración'!$D$15:$D$134,'Configuración'!$B$15:$B$134=""Gastos"")),12),"""")"),"") | C162: =IF(B162="","",IF('Resumen financiero'!$Q$4="Todas",SUMIFS('Cálculos'!$L$9:$L$128,'Cálculos'!$F$9:$F$128,B162,'Cálculos'!$C$9:$C$128,">="&$C$4,'Cálculos'!$C$9:$C$128,"<"&$D$4),SUMIFS('Cálculos'!$L$9:$L$128,'Cálculos'!$F$9:$F$128,B162,'Cálculos'!$C$9:$C$128,">="&$C$4,'Cálculos'!$C$9:$C$128,"<"&$D$4,'Cálculos'!$N$9:$N$128,'Resumen financiero'!$Q$4))) | D162: ="" | E162: =IFERROR(__xludf.DUMMYFUNCTION("IFERROR(INDEX(UNIQUE(FILTER('Configuración'!$D$15:$D$134,'Configuración'!$B$15:$B$134=""Gastos"")),12),"""")"),"") | F162: =IF(COUNT(C162)=0,"",MAX(0,C162))
B163: =IFERROR(__xludf.DUMMYFUNCTION("IFERROR(INDEX(UNIQUE(FILTER('Configuración'!$D$15:$D$134,'Configuración'!$B$15:$B$134=""Gastos"")),13),"""")"),"") | C163: =IF(B163="","",IF('Resumen financiero'!$Q$4="Todas",SUMIFS('Cálculos'!$L$9:$L$128,'Cálculos'!$F$9:$F$128,B163,'Cálculos'!$C$9:$C$128,">="&$C$4,'Cálculos'!$C$9:$C$128,"<"&$D$4),SUMIFS('Cálculos'!$L$9:$L$128,'Cálculos'!$F$9:$F$128,B163,'Cálculos'!$C$9:$C$128,">="&$C$4,'Cálculos'!$C$9:$C$128,"<"&$D$4,'Cálculos'!$N$9:$N$128,'Resumen financiero'!$Q$4))) | D163: ="" | E163: =IFERROR(__xludf.DUMMYFUNCTION("IFERROR(INDEX(UNIQUE(FILTER('Configuración'!$D$15:$D$134,'Configuración'!$B$15:$B$134=""Gastos"")),13),"""")"),"") | F163: =IF(COUNT(C163)=0,"",MAX(0,C163))
B164: =IFERROR(__xludf.DUMMYFUNCTION("IFERROR(INDEX(UNIQUE(FILTER('Configuración'!$D$15:$D$134,'Configuración'!$B$15:$B$134=""Gastos"")),14),"""")"),"") | C164: =IF(B164="","",IF('Resumen financiero'!$Q$4="Todas",SUMIFS('Cálculos'!$L$9:$L$128,'Cálculos'!$F$9:$F$128,B164,'Cálculos'!$C$9:$C$128,">="&$C$4,'Cálculos'!$C$9:$C$128,"<"&$D$4),SUMIFS('Cálculos'!$L$9:$L$128,'Cálculos'!$F$9:$F$128,B164,'Cálculos'!$C$9:$C$128,">="&$C$4,'Cálculos'!$C$9:$C$128,"<"&$D$4,'Cálculos'!$N$9:$N$128,'Resumen financiero'!$Q$4))) | D164: ="" | E164: =IFERROR(__xludf.DUMMYFUNCTION("IFERROR(INDEX(UNIQUE(FILTER('Configuración'!$D$15:$D$134,'Configuración'!$B$15:$B$134=""Gastos"")),14),"""")"),"") | F164: =IF(COUNT(C164)=0,"",MAX(0,C164))
B165: =IFERROR(__xludf.DUMMYFUNCTION("IFERROR(INDEX(UNIQUE(FILTER('Configuración'!$D$15:$D$134,'Configuración'!$B$15:$B$134=""Gastos"")),15),"""")"),"") | C165: =IF(B165="","",IF('Resumen financiero'!$Q$4="Todas",SUMIFS('Cálculos'!$L$9:$L$128,'Cálculos'!$F$9:$F$128,B165,'Cálculos'!$C$9:$C$128,">="&$C$4,'Cálculos'!$C$9:$C$128,"<"&$D$4),SUMIFS('Cálculos'!$L$9:$L$128,'Cálculos'!$F$9:$F$128,B165,'Cálculos'!$C$9:$C$128,">="&$C$4,'Cálculos'!$C$9:$C$128,"<"&$D$4,'Cálculos'!$N$9:$N$128,'Resumen financiero'!$Q$4))) | D165: ="" | E165: =IFERROR(__xludf.DUMMYFUNCTION("IFERROR(INDEX(UNIQUE(FILTER('Configuración'!$D$15:$D$134,'Configuración'!$B$15:$B$134=""Gastos"")),15),"""")"),"") | F165: =IF(COUNT(C165)=0,"",MAX(0,C165))
B166: =IFERROR(__xludf.DUMMYFUNCTION("IFERROR(INDEX(UNIQUE(FILTER('Configuración'!$D$15:$D$134,'Configuración'!$B$15:$B$134=""Gastos"")),16),"""")"),"") | C166: =IF(B166="","",IF('Resumen financiero'!$Q$4="Todas",SUMIFS('Cálculos'!$L$9:$L$128,'Cálculos'!$F$9:$F$128,B166,'Cálculos'!$C$9:$C$128,">="&$C$4,'Cálculos'!$C$9:$C$128,"<"&$D$4),SUMIFS('Cálculos'!$L$9:$L$128,'Cálculos'!$F$9:$F$128,B166,'Cálculos'!$C$9:$C$128,">="&$C$4,'Cálculos'!$C$9:$C$128,"<"&$D$4,'Cálculos'!$N$9:$N$128,'Resumen financiero'!$Q$4))) | D166: ="" | E166: =IFERROR(__xludf.DUMMYFUNCTION("IFERROR(INDEX(UNIQUE(FILTER('Configuración'!$D$15:$D$134,'Configuración'!$B$15:$B$134=""Gastos"")),16),"""")"),"") | F166: =IF(COUNT(C166)=0,"",MAX(0,C166))
B167: =IFERROR(__xludf.DUMMYFUNCTION("IFERROR(INDEX(UNIQUE(FILTER('Configuración'!$D$15:$D$134,'Configuración'!$B$15:$B$134=""Gastos"")),17),"""")"),"") | C167: =IF(B167="","",IF('Resumen financiero'!$Q$4="Todas",SUMIFS('Cálculos'!$L$9:$L$128,'Cálculos'!$F$9:$F$128,B167,'Cálculos'!$C$9:$C$128,">="&$C$4,'Cálculos'!$C$9:$C$128,"<"&$D$4),SUMIFS('Cálculos'!$L$9:$L$128,'Cálculos'!$F$9:$F$128,B167,'Cálculos'!$C$9:$C$128,">="&$C$4,'Cálculos'!$C$9:$C$128,"<"&$D$4,'Cálculos'!$N$9:$N$128,'Resumen financiero'!$Q$4))) | D167: ="" | E167: =IFERROR(__xludf.DUMMYFUNCTION("IFERROR(INDEX(UNIQUE(FILTER('Configuración'!$D$15:$D$134,'Configuración'!$B$15:$B$134=""Gastos"")),17),"""")"),"") | F167: =IF(COUNT(C167)=0,"",MAX(0,C167))
B168: =IFERROR(__xludf.DUMMYFUNCTION("IFERROR(INDEX(UNIQUE(FILTER('Configuración'!$D$15:$D$134,'Configuración'!$B$15:$B$134=""Gastos"")),18),"""")"),"") | C168: =IF(B168="","",IF('Resumen financiero'!$Q$4="Todas",SUMIFS('Cálculos'!$L$9:$L$128,'Cálculos'!$F$9:$F$128,B168,'Cálculos'!$C$9:$C$128,">="&$C$4,'Cálculos'!$C$9:$C$128,"<"&$D$4),SUMIFS('Cálculos'!$L$9:$L$128,'Cálculos'!$F$9:$F$128,B168,'Cálculos'!$C$9:$C$128,">="&$C$4,'Cálculos'!$C$9:$C$128,"<"&$D$4,'Cálculos'!$N$9:$N$128,'Resumen financiero'!$Q$4))) | D168: ="" | E168: =IFERROR(__xludf.DUMMYFUNCTION("IFERROR(INDEX(UNIQUE(FILTER('Configuración'!$D$15:$D$134,'Configuración'!$B$15:$B$134=""Gastos"")),18),"""")"),"") | F168: =IF(COUNT(C168)=0,"",MAX(0,C168))
B169: =IFERROR(__xludf.DUMMYFUNCTION("IFERROR(INDEX(UNIQUE(FILTER('Configuración'!$D$15:$D$134,'Configuración'!$B$15:$B$134=""Gastos"")),19),"""")"),"") | C169: =IF(B169="","",IF('Resumen financiero'!$Q$4="Todas",SUMIFS('Cálculos'!$L$9:$L$128,'Cálculos'!$F$9:$F$128,B169,'Cálculos'!$C$9:$C$128,">="&$C$4,'Cálculos'!$C$9:$C$128,"<"&$D$4),SUMIFS('Cálculos'!$L$9:$L$128,'Cálculos'!$F$9:$F$128,B169,'Cálculos'!$C$9:$C$128,">="&$C$4,'Cálculos'!$C$9:$C$128,"<"&$D$4,'Cálculos'!$N$9:$N$128,'Resumen financiero'!$Q$4))) | D169: ="" | E169: =IFERROR(__xludf.DUMMYFUNCTION("IFERROR(INDEX(UNIQUE(FILTER('Configuración'!$D$15:$D$134,'Configuración'!$B$15:$B$134=""Gastos"")),19),"""")"),"") | F169: =IF(COUNT(C169)=0,"",MAX(0,C169))
B170: =IFERROR(__xludf.DUMMYFUNCTION("IFERROR(INDEX(UNIQUE(FILTER('Configuración'!$D$15:$D$134,'Configuración'!$B$15:$B$134=""Gastos"")),20),"""")"),"") | C170: =IF(B170="","",IF('Resumen financiero'!$Q$4="Todas",SUMIFS('Cálculos'!$L$9:$L$128,'Cálculos'!$F$9:$F$128,B170,'Cálculos'!$C$9:$C$128,">="&$C$4,'Cálculos'!$C$9:$C$128,"<"&$D$4),SUMIFS('Cálculos'!$L$9:$L$128,'Cálculos'!$F$9:$F$128,B170,'Cálculos'!$C$9:$C$128,">="&$C$4,'Cálculos'!$C$9:$C$128,"<"&$D$4,'Cálculos'!$N$9:$N$128,'Resumen financiero'!$Q$4))) | D170: ="" | E170: =IFERROR(__xludf.DUMMYFUNCTION("IFERROR(INDEX(UNIQUE(FILTER('Configuración'!$D$15:$D$134,'Configuración'!$B$15:$B$134=""Gastos"")),20),"""")"),"") | F170: =IF(COUNT(C170)=0,"",MAX(0,C170))
B171: =IFERROR(__xludf.DUMMYFUNCTION("IFERROR(INDEX(UNIQUE(FILTER('Configuración'!$D$15:$D$134,'Configuración'!$B$15:$B$134=""Gastos"")),21),"""")"),"") | C171: =IF(B171="","",IF('Resumen financiero'!$Q$4="Todas",SUMIFS('Cálculos'!$L$9:$L$128,'Cálculos'!$F$9:$F$128,B171,'Cálculos'!$C$9:$C$128,">="&$C$4,'Cálculos'!$C$9:$C$128,"<"&$D$4),SUMIFS('Cálculos'!$L$9:$L$128,'Cálculos'!$F$9:$F$128,B171,'Cálculos'!$C$9:$C$128,">="&$C$4,'Cálculos'!$C$9:$C$128,"<"&$D$4,'Cálculos'!$N$9:$N$128,'Resumen financiero'!$Q$4))) | D171: ="" | E171: =IFERROR(__xludf.DUMMYFUNCTION("IFERROR(INDEX(UNIQUE(FILTER('Configuración'!$D$15:$D$134,'Configuración'!$B$15:$B$134=""Gastos"")),21),"""")"),"") | F171: =IF(COUNT(C171)=0,"",MAX(0,C171))
B172: =IFERROR(__xludf.DUMMYFUNCTION("IFERROR(INDEX(UNIQUE(FILTER('Configuración'!$D$15:$D$134,'Configuración'!$B$15:$B$134=""Gastos"")),22),"""")"),"") | C172: =IF(B172="","",IF('Resumen financiero'!$Q$4="Todas",SUMIFS('Cálculos'!$L$9:$L$128,'Cálculos'!$F$9:$F$128,B172,'Cálculos'!$C$9:$C$128,">="&$C$4,'Cálculos'!$C$9:$C$128,"<"&$D$4),SUMIFS('Cálculos'!$L$9:$L$128,'Cálculos'!$F$9:$F$128,B172,'Cálculos'!$C$9:$C$128,">="&$C$4,'Cálculos'!$C$9:$C$128,"<"&$D$4,'Cálculos'!$N$9:$N$128,'Resumen financiero'!$Q$4))) | D172: ="" | E172: =IFERROR(__xludf.DUMMYFUNCTION("IFERROR(INDEX(UNIQUE(FILTER('Configuración'!$D$15:$D$134,'Configuración'!$B$15:$B$134=""Gastos"")),22),"""")"),"") | F172: =IF(COUNT(C172)=0,"",MAX(0,C172))
B173: =IFERROR(__xludf.DUMMYFUNCTION("IFERROR(INDEX(UNIQUE(FILTER('Configuración'!$D$15:$D$134,'Configuración'!$B$15:$B$134=""Gastos"")),23),"""")"),"") | C173: =IF(B173="","",IF('Resumen financiero'!$Q$4="Todas",SUMIFS('Cálculos'!$L$9:$L$128,'Cálculos'!$F$9:$F$128,B173,'Cálculos'!$C$9:$C$128,">="&$C$4,'Cálculos'!$C$9:$C$128,"<"&$D$4),SUMIFS('Cálculos'!$L$9:$L$128,'Cálculos'!$F$9:$F$128,B173,'Cálculos'!$C$9:$C$128,">="&$C$4,'Cálculos'!$C$9:$C$128,"<"&$D$4,'Cálculos'!$N$9:$N$128,'Resumen financiero'!$Q$4))) | D173: ="" | E173: =IFERROR(__xludf.DUMMYFUNCTION("IFERROR(INDEX(UNIQUE(FILTER('Configuración'!$D$15:$D$134,'Configuración'!$B$15:$B$134=""Gastos"")),23),"""")"),"") | F173: =IF(COUNT(C173)=0,"",MAX(0,C173))
B174: =IFERROR(__xludf.DUMMYFUNCTION("IFERROR(INDEX(UNIQUE(FILTER('Configuración'!$D$15:$D$134,'Configuración'!$B$15:$B$134=""Gastos"")),24),"""")"),"") | C174: =IF(B174="","",IF('Resumen financiero'!$Q$4="Todas",SUMIFS('Cálculos'!$L$9:$L$128,'Cálculos'!$F$9:$F$128,B174,'Cálculos'!$C$9:$C$128,">="&$C$4,'Cálculos'!$C$9:$C$128,"<"&$D$4),SUMIFS('Cálculos'!$L$9:$L$128,'Cálculos'!$F$9:$F$128,B174,'Cálculos'!$C$9:$C$128,">="&$C$4,'Cálculos'!$C$9:$C$128,"<"&$D$4,'Cálculos'!$N$9:$N$128,'Resumen financiero'!$Q$4))) | D174: ="" | E174: =IFERROR(__xludf.DUMMYFUNCTION("IFERROR(INDEX(UNIQUE(FILTER('Configuración'!$D$15:$D$134,'Configuración'!$B$15:$B$134=""Gastos"")),24),"""")"),"") | F174: =IF(COUNT(C174)=0,"",MAX(0,C174))
B175: =IFERROR(__xludf.DUMMYFUNCTION("IFERROR(INDEX(UNIQUE(FILTER('Configuración'!$D$15:$D$134,'Configuración'!$B$15:$B$134=""Gastos"")),25),"""")"),"") | C175: =IF(B175="","",IF('Resumen financiero'!$Q$4="Todas",SUMIFS('Cálculos'!$L$9:$L$128,'Cálculos'!$F$9:$F$128,B175,'Cálculos'!$C$9:$C$128,">="&$C$4,'Cálculos'!$C$9:$C$128,"<"&$D$4),SUMIFS('Cálculos'!$L$9:$L$128,'Cálculos'!$F$9:$F$128,B175,'Cálculos'!$C$9:$C$128,">="&$C$4,'Cálculos'!$C$9:$C$128,"<"&$D$4,'Cálculos'!$N$9:$N$128,'Resumen financiero'!$Q$4))) | D175: ="" | E175: =IFERROR(__xludf.DUMMYFUNCTION("IFERROR(INDEX(UNIQUE(FILTER('Configuración'!$D$15:$D$134,'Configuración'!$B$15:$B$134=""Gastos"")),25),"""")"),"") | F175: =IF(COUNT(C175)=0,"",MAX(0,C175))
B176: =IFERROR(__xludf.DUMMYFUNCTION("IFERROR(INDEX(UNIQUE(FILTER('Configuración'!$D$15:$D$134,'Configuración'!$B$15:$B$134=""Gastos"")),26),"""")"),"") | C176: =IF(B176="","",IF('Resumen financiero'!$Q$4="Todas",SUMIFS('Cálculos'!$L$9:$L$128,'Cálculos'!$F$9:$F$128,B176,'Cálculos'!$C$9:$C$128,">="&$C$4,'Cálculos'!$C$9:$C$128,"<"&$D$4),SUMIFS('Cálculos'!$L$9:$L$128,'Cálculos'!$F$9:$F$128,B176,'Cálculos'!$C$9:$C$128,">="&$C$4,'Cálculos'!$C$9:$C$128,"<"&$D$4,'Cálculos'!$N$9:$N$128,'Resumen financiero'!$Q$4))) | D176: ="" | E176: =IFERROR(__xludf.DUMMYFUNCTION("IFERROR(INDEX(UNIQUE(FILTER('Configuración'!$D$15:$D$134,'Configuración'!$B$15:$B$134=""Gastos"")),26),"""")"),"") | F176: =IF(COUNT(C176)=0,"",MAX(0,C176))
B177: =IFERROR(__xludf.DUMMYFUNCTION("IFERROR(INDEX(UNIQUE(FILTER('Configuración'!$D$15:$D$134,'Configuración'!$B$15:$B$134=""Gastos"")),27),"""")"),"") | C177: =IF(B177="","",IF('Resumen financiero'!$Q$4="Todas",SUMIFS('Cálculos'!$L$9:$L$128,'Cálculos'!$F$9:$F$128,B177,'Cálculos'!$C$9:$C$128,">="&$C$4,'Cálculos'!$C$9:$C$128,"<"&$D$4),SUMIFS('Cálculos'!$L$9:$L$128,'Cálculos'!$F$9:$F$128,B177,'Cálculos'!$C$9:$C$128,">="&$C$4,'Cálculos'!$C$9:$C$128,"<"&$D$4,'Cálculos'!$N$9:$N$128,'Resumen financiero'!$Q$4))) | D177: ="" | E177: =IFERROR(__xludf.DUMMYFUNCTION("IFERROR(INDEX(UNIQUE(FILTER('Configuración'!$D$15:$D$134,'Configuración'!$B$15:$B$134=""Gastos"")),27),"""")"),"") | F177: =IF(COUNT(C177)=0,"",MAX(0,C177))
B178: =IFERROR(__xludf.DUMMYFUNCTION("IFERROR(INDEX(UNIQUE(FILTER('Configuración'!$D$15:$D$134,'Configuración'!$B$15:$B$134=""Gastos"")),28),"""")"),"") | C178: =IF(B178="","",IF('Resumen financiero'!$Q$4="Todas",SUMIFS('Cálculos'!$L$9:$L$128,'Cálculos'!$F$9:$F$128,B178,'Cálculos'!$C$9:$C$128,">="&$C$4,'Cálculos'!$C$9:$C$128,"<"&$D$4),SUMIFS('Cálculos'!$L$9:$L$128,'Cálculos'!$F$9:$F$128,B178,'Cálculos'!$C$9:$C$128,">="&$C$4,'Cálculos'!$C$9:$C$128,"<"&$D$4,'Cálculos'!$N$9:$N$128,'Resumen financiero'!$Q$4))) | D178: ="" | E178: =IFERROR(__xludf.DUMMYFUNCTION("IFERROR(INDEX(UNIQUE(FILTER('Configuración'!$D$15:$D$134,'Configuración'!$B$15:$B$134=""Gastos"")),28),"""")"),"") | F178: =IF(COUNT(C178)=0,"",MAX(0,C178))
B179: =IFERROR(__xludf.DUMMYFUNCTION("IFERROR(INDEX(UNIQUE(FILTER('Configuración'!$D$15:$D$134,'Configuración'!$B$15:$B$134=""Gastos"")),29),"""")"),"") | C179: =IF(B179="","",IF('Resumen financiero'!$Q$4="Todas",SUMIFS('Cálculos'!$L$9:$L$128,'Cálculos'!$F$9:$F$128,B179,'Cálculos'!$C$9:$C$128,">="&$C$4,'Cálculos'!$C$9:$C$128,"<"&$D$4),SUMIFS('Cálculos'!$L$9:$L$128,'Cálculos'!$F$9:$F$128,B179,'Cálculos'!$C$9:$C$128,">="&$C$4,'Cálculos'!$C$9:$C$128,"<"&$D$4,'Cálculos'!$N$9:$N$128,'Resumen financiero'!$Q$4))) | D179: ="" | E179: =IFERROR(__xludf.DUMMYFUNCTION("IFERROR(INDEX(UNIQUE(FILTER('Configuración'!$D$15:$D$134,'Configuración'!$B$15:$B$134=""Gastos"")),29),"""")"),"") | F179: =IF(COUNT(C179)=0,"",MAX(0,C179))
B180: =IFERROR(__xludf.DUMMYFUNCTION("IFERROR(INDEX(UNIQUE(FILTER('Configuración'!$D$15:$D$134,'Configuración'!$B$15:$B$134=""Gastos"")),30),"""")"),"") | C180: =IF(B180="","",IF('Resumen financiero'!$Q$4="Todas",SUMIFS('Cálculos'!$L$9:$L$128,'Cálculos'!$F$9:$F$128,B180,'Cálculos'!$C$9:$C$128,">="&$C$4,'Cálculos'!$C$9:$C$128,"<"&$D$4),SUMIFS('Cálculos'!$L$9:$L$128,'Cálculos'!$F$9:$F$128,B180,'Cálculos'!$C$9:$C$128,">="&$C$4,'Cálculos'!$C$9:$C$128,"<"&$D$4,'Cálculos'!$N$9:$N$128,'Resumen financiero'!$Q$4))) | D180: ="" | E180: =IFERROR(__xludf.DUMMYFUNCTION("IFERROR(INDEX(UNIQUE(FILTER('Configuración'!$D$15:$D$134,'Configuración'!$B$15:$B$134=""Gastos"")),30),"""")"),"") | F180: =IF(COUNT(C180)=0,"",MAX(0,C180))
B181: =IFERROR(__xludf.DUMMYFUNCTION("IFERROR(INDEX(UNIQUE(FILTER('Configuración'!$D$15:$D$134,'Configuración'!$B$15:$B$134=""Gastos"")),31),"""")"),"") | C181: =IF(B181="","",IF('Resumen financiero'!$Q$4="Todas",SUMIFS('Cálculos'!$L$9:$L$128,'Cálculos'!$F$9:$F$128,B181,'Cálculos'!$C$9:$C$128,">="&$C$4,'Cálculos'!$C$9:$C$128,"<"&$D$4),SUMIFS('Cálculos'!$L$9:$L$128,'Cálculos'!$F$9:$F$128,B181,'Cálculos'!$C$9:$C$128,">="&$C$4,'Cálculos'!$C$9:$C$128,"<"&$D$4,'Cálculos'!$N$9:$N$128,'Resumen financiero'!$Q$4))) | D181: ="" | E181: =IFERROR(__xludf.DUMMYFUNCTION("IFERROR(INDEX(UNIQUE(FILTER('Configuración'!$D$15:$D$134,'Configuración'!$B$15:$B$134=""Gastos"")),31),"""")"),"") | F181: =IF(COUNT(C181)=0,"",MAX(0,C181))
B182: =IFERROR(__xludf.DUMMYFUNCTION("IFERROR(INDEX(UNIQUE(FILTER('Configuración'!$D$15:$D$134,'Configuración'!$B$15:$B$134=""Gastos"")),32),"""")"),"") | C182: =IF(B182="","",IF('Resumen financiero'!$Q$4="Todas",SUMIFS('Cálculos'!$L$9:$L$128,'Cálculos'!$F$9:$F$128,B182,'Cálculos'!$C$9:$C$128,">="&$C$4,'Cálculos'!$C$9:$C$128,"<"&$D$4),SUMIFS('Cálculos'!$L$9:$L$128,'Cálculos'!$F$9:$F$128,B182,'Cálculos'!$C$9:$C$128,">="&$C$4,'Cálculos'!$C$9:$C$128,"<"&$D$4,'Cálculos'!$N$9:$N$128,'Resumen financiero'!$Q$4))) | D182: ="" | E182: =IFERROR(__xludf.DUMMYFUNCTION("IFERROR(INDEX(UNIQUE(FILTER('Configuración'!$D$15:$D$134,'Configuración'!$B$15:$B$134=""Gastos"")),32),"""")"),"") | F182: =IF(COUNT(C182)=0,"",MAX(0,C182))
